Workbook

Sheet 基本信息
A1: 基本信息
A2: 序号 | B2: 项目 | C2: 原名称 | D2: 数值 | E2: 单位 | F2: 关键词 | G2: 辅助关键词 | H2: 是否必须 | I2: 选项 | J2: 备注 | K2: 关联指标
A3: 1 | B3: 项目运营起始年 | C3: 项目运营起始年 | E3: - | J3: 人工填
A4: 2 | B4: 交流测装机容量 | C4: 交流测装机容量 | E4: MW | F4: 交流侧容量、交流侧装机容量、交流容量、建设装机容量、建设容量 | G4: MW | H4: 是
A5: 3 | B5: 直流侧装机容量或装机/规划容量 | C5: 直流侧装机容量 | E5: MWp | F5: 直流侧装机容量、装机容量、规划容量、总容量 | G5: MWp | H5: 是
A6: 4 | B6: 静态投资 | C6: 静态投资 | E6: 万元 | F6: 静态投资、静态 | G6: 万 | H6: 是
A7: 5 | B7: 建设期利息 | C7: 建设期利息 | E7: 万元 | F7: 建设期利息 | G7: 万 | H7: 是
A8: 6 | B8: 可抵扣税金 | C8: 可抵扣税金 | E8: 万元 | F8: 可抵扣、增值税、可抵扣税金、增值税抵扣、可抵扣增值税 | G8: 万 | H8: 否
A9: 7 | B9: 首年无衰减利用小时 | C9: 首年无衰减利用小时 | E9: h | F9: 首年年利用小时数、利用小时数、首年、首年利用小时 | G9: h | H9: 否
A10: 8 | B10: 本项目光伏组件类型 | C10: 组件类型 | E10: - | F10: N型、P型、单玻、双玻、多晶、P型单玻、P型双玻、N型单玻、N型双玻、多晶单玻、多晶双玻 | H10: 是 | I10: P型单玻、P型双玻、N型单玻、N型双玻、多晶单玻、多晶双玻
A11: 9 | B11: 所在地区 | C11: 所在地区 | D11: 天津 | E11: - | F11: 发电项目、项目所在地、本工程位于、本项目位于、省、市 | I11: 北京、天津、河北冀北地区、河北冀南地区、山西、辽宁、吉林延边自治州外地区、黑龙江、上海、江苏、浙江、安徽、福建、江西赣州市外地区、山东、河南、湖北恩施自治州外地区、湖南湘西自治州外地区、广东、海南、江西赣州市、湖南湘西自治州、湖北恩施自治州、吉林延边自治州、广西、内蒙古蒙东地区、内蒙古蒙西地区、重庆、四川、贵州、云南、西藏、陕西、甘肃、青海、宁夏、新疆
A12: 10 | B12: 电价电量取值标准 | C12: 电价电量取值标准 | E12: - | I12: 标准1、标准2 | J12: 人工填
A13: 11 | B13: 运维方式 | C13: 运维方式 | D13: 自主运维 | E13: - | F13: 委托运维、外委、运维 | H13: 是 | I13: 自主运维、委托运维
A14: 12 | B14: 本项目光伏组件运行方式 | C14: 跟踪方式 | E14: - | F14: 固定式、固定可调、跟踪式 | G14: 本项目、本工程 | H14: 否 | I14: 固定式、固定可调、跟踪式
A15: 13 | B15: 建设/项目地的地形类型 | C15: 地质环境 | E15: - | F15: 地形、地貌、地形地貌、平原、山地、丘陵、水面、鱼塘、渔塘 | G15: 本项目、建设场地、本工程、建设地 | H15: 否 | I15: 平原、山地、水面
A16: 14 | B16: 集电线路长度 | C16: 集电线路长度 | E16: km | F16: 集电线路、35kv | G16: 35kv | H16: 否
A17: 15 | B17: 光伏子阵容量 | C17: 光伏子阵 | D17: 2MW以上 | E17: MW | F17: 光伏子阵、光伏阵列、光伏单元、光伏发电单元 | H17: 否 | K17: 直流侧装机容量或装机/规划容量
A18: 16 | B18: 项目海拔高度 | C18: 海拔高度 | E18: m | F18: 海拔、高程 | G18: m | H18: 是
A19: 17 | B19: 新建、配套建设升压站（变电站）电压等级 | C19: 升压变电站 | E19: kv | F19: 升压站、变电站、开关站 | G19: 新建 | H19: 是
A20: 18 | B20: 其他费用1 | C20: 其他费用1 | E20: 万元/年 | F20: 房屋租金、屋顶租金、房屋租赁、屋顶租赁 | H20: 是
A21: 19 | B21: 其他费用2 | C21: 其他费用2 | E21: 万元/年 | F21: 土地租金、土地租赁 | H21: 是
A22: 20 | B22: 其他费用3 | C22: 其他费用3 | E22: 万元/年 | F22: 储能租金、储能租赁 | H22: 是
A23: 21 | B23: 平均上网电价 | E23: 元/(kW•h) | F23: 电价、上网电价 | G23: 元/(kW•h) | H23: 是
A24: 22 | B24: 平均弃电率 | E24: % | F24: 弃电 | G24: % | H24: 是

Sheet 地区辅助页
A1: 序号 | B1: 填写地区 | D1: 电价电量地区 | E1: =_xlfn.XLOOKUP(基本信息!D11,B:B,D:D,"",0) -> 天津 | G1: 人工成本区域 | H1: =_xlfn.XLOOKUP(基本信息!D11,B:B,G:G,"",0) -> 华北
A2: 1 | B2: 北京 | D2: 北京 | G2: 华北
A3: =A2+1 -> 2 | B3: 天津 | D3: 天津 | G3: 华北
A4: =A3+1 -> 3 | B4: 河北冀北地区 | D4: 冀北 | G4: 华北
A5: =A4+1 -> 4 | B5: 河北冀南地区 | D5: 冀南 | G5: 华北
A6: =A5+1 -> 5 | B6: 山西 | D6: 山西 | G6: 华北
A7: =A6+1 -> 6 | B7: 辽宁 | D7: 辽宁 | G7: 东北
A8: =A7+1 -> 7 | B8: 吉林延边自治州外地区 | D8: 吉林 | G8: 东北
A9: =A8+1 -> 8 | B9: 黑龙江 | D9: 黑龙江 | G9: 东北
A10: =A9+1 -> 9 | B10: 上海 | D10: 上海 | G10: 华东
A11: =A10+1 -> 10 | B11: 江苏 | D11: 江苏 | G11: 华东
A12: =A11+1 -> 11 | B12: 浙江 | D12: 浙江 | G12: 华东
A13: =A12+1 -> 12 | B13: 安徽 | D13: 安徽 | G13: 华东
A14: =A13+1 -> 13 | B14: 福建 | D14: 福建 | G14: 华东
... A38: =A37+1 -> 37 | B38: 新疆 | D38: 新疆 | G38: 西北

Sheet 成本费用取值表
B1: 修理费
B2: 序号 | C2: 项目名称 | D2: 建议值(元/KW) | E2: 按装机容量修正（兆瓦） | J2: 集电线路长度（公里） | L2: 按组件类型修正 | O2: 按跟踪方式修正 | Q2: 按地质环境修正 | U2: 按上年度是否亏损修正 | W2: 按是否出质保期修正 | Y2: 检修业务是否外委
E3: 10（含）以下 | F3: 10-50（含） | G3: 50-100（含） | H3: 100-300（含） | I3: 300以上 | J3: 20（含）以下 | K3: 20-50（含） | L3: 单晶 | M3: 多晶 | N3: 薄膜 | O3: 固定 | P3: 斜/平单轴 | Q3: 平原及其它 | R3: 山地丘陵及沙地 | S3: 屋顶 | T3: 水面 | U3: 亏损企业 | V3: 赢利企业 | W3: 期内 | X3: 期外 | Y3: 是 | Z3: 否
B4: 1 | C4: 发电设备 | D4: 22.4 | E4: 1.05 | F4: 1 | G4: 0.95 | H4: 0.9 | I4: 0.9 | J4: 1 | K4: 1 | L4: 1 | M4: 1 | N4: 1.2 | O4: 1 | P4: 1.2 | Q4: 1 | R4: 1.05 | S4: 1.1 | T4: 1.2 | U4: 0.95 | V4: 1 | W4: 0.15 | X4: 1 | Y4: 0.05 | Z4: 1
B5: 2 | C5: 升压站 | D5: 3.2 | E5: 1 | F5: 1 | G5: 0.95 | H5: 0.9 | I5: 0.9 | J5: 1 | K5: 1 | L5: 1 | M5: 1 | N5: 1 | O5: 1 | P5: 1 | Q5: 1 | R5: 1 | S5: 1 | T5: 1 | U5: 0.95 | V5: 1 | W5: 1 | X5: 1 | Y5: 0.05 | Z5: 1
B6: 3 | C6: 中控室 | D6: 0.64 | E6: 1 | F6: 1 | G6: 1 | H6: 1 | I6: 1 | J6: 1 | K6: 1 | L6: 1 | M6: 1 | N6: 1 | O6: 1 | P6: 1 | Q6: 1 | R6: 1 | S6: 1 | T6: 1 | U6: 0.95 | V6: 1 | W6: 0.7 | X6: 1 | Y6: 0.05 | Z6: 1
B7: 4 | C7: 输配电及线路 | D7: 3.2 | E7: 1 | F7: 1 | G7: 0.95 | H7: 0.9 | I7: 0.9 | J7: 1.1 | K7: 1.2 | L7: 1 | M7: 1 | N7: 1 | O7: 1 | P7: 1 | Q7: 1 | R7: 1 | S7: 1 | T7: 1 | U7: 0.95 | V7: 1 | W7: 0.7 | X7: 1 | Y7: 0.05 | Z7: 1
B8: 5 | C8: 生产非生产建筑物 | D8: 2.56 | E8: 1 | F8: 1 | G8: 1 | H8: 1 | I8: 1 | J8: 1 | K8: 1 | L8: 1 | M8: 1 | N8: 1 | O8: 1 | P8: 1 | Q8: 1 | R8: 1 | S8: 1 | T8: 1 | U8: 0.95 | V8: 1 | W8: 1 | X8: 1 | Y8: 0.05 | Z8: 1
C9: 小计 | D9: 32 | E9: 33.12 | F9: 32 | G9: 30.56 | H9: 29.12 | I9: 29.12 | J9: 32.32 | K9: 32.64 | L9: 32 | M9: 32 | N9: 36.48 | O9: 32 | P9: 36.48 | Q9: 32 | R9: 33.12 | S9: 34.24 | T9: 36.48 | U9: 30.4 | V9: 32 | W9: 11.808 | X9: 32 | Y9: 1.6 | Z9: 32
C10: =IF(SUM(E10:V10)+SUM(Y10:Z10)=7,"正确","错误") -> #REF! | E10: =IF(基本参数!$B$7<=10,1,0) -> 1 | F10: =IF(AND(基本参数!$B$7>10,基本参数!$B$7<=50),1,0) -> 0 | G10: =IF(AND(基本参数!$B$7>50,基本参数!$B$7<=100),1,0) -> 0 | H10: =IF(AND(基本参数!$B$7>100,基本参数!$B$7<=300),1,0) -> 0 | I10: =IF(基本参数!$B$6>300,1,0) -> 0 | J10: =IF(基本信息!$D$15=J3,1,0) -> 0 | K10: =IF(基本信息!$D$15=K3,1,0) -> 0 | L10: =IF(M10+N10=0,1,0) -> 1 | M10: =IF(OR(收入和税金!C5="多晶单玻",收入和税金!C5="多晶双玻"),1,0) -> 0 | O10: =P45+Q45 -> #REF! | P10: =R45 -> #REF! | Q10: =IF(基本信息!#REF!=Q3,1,0) -> #REF! | R10: =IF(基本信息!#REF!=R3,1,0) -> #REF! | S10: =IF(基本信息!#REF!=S3,1,0) -> #REF! | T10: =IF(基本信息!#REF!=T3,1,0) -> #REF! | V10: 1 | Z10: 1
C11: XXMW维修费
C12: 质保期内 | D12: 质保期外
C13: =D4*W4*SUMPRODUCT(Y4:Z4,$Y$10:$Z$10) -> 3.36 | D13: =D4*X4*SUMPRODUCT(Y4:Z4,$Y$10:$Z$10)*SUMPRODUCT(E4:I4,$E$10:$I$10)*SUMPRODUCT(J4:K4,$J$10:$K$10)*SUMPRODUCT(L4:N4,$L$10:$N$10)*SUMPRODUCT(O4:P4,$O$10:$P$10)*SUMPRODUCT(Q4:T4,$Q$10:$T$10)*SUMPRODUCT(U4:V4,$U$10:$V$10) -> #REF!
C14: =SUMPRODUCT(F70:R70,F71:R71) -> 0 | D14: =D5*X5*SUMPRODUCT(Y5:Z5,$Y$10:$Z$10)*SUMPRODUCT(E5:I5,$E$10:$I$10)*SUMPRODUCT(J5:K5,$J$10:$K$10)*SUMPRODUCT(L5:N5,$L$10:$N$10)*SUMPRODUCT(O5:P5,$O$10:$P$10)*SUMPRODUCT(Q5:T5,$Q$10:$T$10)*SUMPRODUCT(U5:V5,$U$10:$V$10) -> #REF! | G14: 质保期 | H14: 10
C15: =SUMPRODUCT(F71:R71,F72:R72) -> 0 | D15: =D6*X6*SUMPRODUCT(Y6:Z6,$Y$10:$Z$10)*SUMPRODUCT(E6:I6,$E$10:$I$10)*SUMPRODUCT(J6:K6,$J$10:$K$10)*SUMPRODUCT(L6:N6,$L$10:$N$10)*SUMPRODUCT(O6:P6,$O$10:$P$10)*SUMPRODUCT(Q6:T6,$Q$10:$T$10)*SUMPRODUCT(U6:V6,$U$10:$V$10) -> #REF!
C16: =SUMPRODUCT(F72:R72,F73:R73) -> 0 | D16: =D7*X7*SUMPRODUCT(Y7:Z7,$Y$10:$Z$10)*SUMPRODUCT(E7:I7,$E$10:$I$10)*SUMPRODUCT(J7:K7,$J$10:$K$10)*SUMPRODUCT(L7:N7,$L$10:$N$10)*SUMPRODUCT(O7:P7,$O$10:$P$10)*SUMPRODUCT(Q7:T7,$Q$10:$T$10)*SUMPRODUCT(U7:V7,$U$10:$V$10) -> #REF!
C17: =SUMPRODUCT(F73:R73,F74:R74) -> 0 | D17: =D8*X8*SUMPRODUCT(Y8:Z8,$Y$10:$Z$10)*SUMPRODUCT(E8:I8,$E$10:$I$10)*SUMPRODUCT(J8:K8,$J$10:$K$10)*SUMPRODUCT(L8:N8,$L$10:$N$10)*SUMPRODUCT(O8:P8,$O$10:$P$10)*SUMPRODUCT(Q8:T8,$Q$10:$T$10)*SUMPRODUCT(U8:V8,$U$10:$V$10) -> #REF!
C18: =SUM(C13:C17) -> 3.36 | D18: =SUM(D13:D17) -> #REF!
B21: 材料费
B22: 项目名称 | C22: 建议值(元/KW) | D22: 按装机容量修正（兆瓦） | I22: 按机组类型修正 | L22: 按跟踪方式修正 | N22: 按地质环境修正 | R22: 按上年度是否亏损修正 | T22: 按是否出质保期修正 | V22: 日常维护及运行外委
D23: 10（含）以下 | E23: 10-50（含） | F23: 50-100（含） | G23: 100-300（含） | H23: 300以上 | I23: 单晶 | J23: 多晶 | K23: 薄膜 | L23: 固定 | M23: 平/斜单轴 | N23: 平原及其它 | O23: 山地丘陵及沙地 | P23: 屋顶 | Q23: 水面 | R23: 亏损企业 | S23: 赢利企业 | T23: 期内 | U23: 期外 | V23: 是 | W23: 否
B24: 基准值 | C24: 8 | D24: 1.05 | E24: 1 | F24: 0.85 | G24: 0.7 | H24: 0.6 | I24: 1 | J24: 1 | K24: 1.2 | L24: 1 | M24: 1.2 | N24: 1 | O24: 1.05 | P24: 1.1 | Q24: 1.2 | R24: 0.95 | S24: 1 | T24: 0.5 | U24: 1 | V24: 0.05 | W24: 1
D25: =E10 -> 1 | E25: =F10 -> 0 | F25: =G10 -> 0 | G25: =H10 -> 0 | H25: =I10 -> 0 | I25: =L10 -> 1 | J25: =M10 -> 0 | K25: =N10 -> 0 | L25: =O10 -> #REF! | M25: =P10 -> #REF! | N25: =Q10 -> #REF! | O25: =R10 -> #REF! | P25: =S10 -> #REF! | ... S25: =V10 -> 1 | V25: =Y10 -> 0 | W25: =Z10 -> 1
C26: XXMW材料费
C27: 质保期内 | D27: 质保期外
C28: =C24*T24*SUMPRODUCT(V24:W24,V25:W25) -> 4 | D28: =C24*U24*SUMPRODUCT(D24:H24,D25:H25)*SUMPRODUCT(I24:K24,I25:K25)*SUMPRODUCT(L24:M24,L25:M25)*SUMPRODUCT(N24:Q24,N25:Q25)*SUMPRODUCT(R24:S24,R25:S25)*SUMPRODUCT(V24:W24,V25:W25) -> #REF!
B31: 其他费用
B32: 项目名称 | C32: 建议值 (元/KW) | D32: 按装机容量修正（兆瓦） | I32: 全场外委
D33: 10（含）以下 | E33: 10-50（含） | F33: 50-100（含） | G33: 100-300（含） | H33: 300以上 | I33: 是 | J33: 否
B34: 基准值 | C34: 40 | D34: 1.5 | E34: 1 | F34: 0.8 | G34: 0.6 | H34: 0.4 | I34: 0.8 | J34: 1
D35: =D25 -> 1 | E35: =E25 -> 0 | F35: =F25 -> 0 | G35: =G25 -> 0 | H35: =H25 -> 0 | I35: =V25 -> 0 | J35: =W25 -> 1
C36: XXMW其他费用
C37: =C34*SUMPRODUCT(D34:H34,D35:H35)*SUMPRODUCT(I34:J34,I35:J35) -> 60
B41: 委托运维费
B42: 项目名称 | C42: 建议值(元/kW) | D42: 按装机容量修正（兆瓦） | K42: 光伏子阵修正 | N42: 按容配比修正 | P42: 按跟踪方式修正 | S42: 按地质环境修正 | U42: 按海拔高度修正 | W42: 是否含升压变电站 | AB42: 投产年限修正
D43: 10(含）以下 | E43: 10-20（含） | F43: 20-40（含） | G43: 40-60（含） | H43: 60-80（含） | I43: 80-100（含） | J43: 100以上 | K43: 1MW以下（含） | L43: 1MW-2MW（含） | M43: 2MW以上 | N43: 1.05（含）以下 | O43: 1.05以上 | P43: 固定式 | Q43: 固定可调 | R43: 跟踪式 | S43: 平原及其它 | T43: 山地、戈壁、沙漠、水面、屋顶 | U43: 海拔2500米及以上 | V43: 海拔2500米以下 | W43: 否 | X43: 10-35kV升压站（无主变） | Y43: 10-35kV升压站（含主变） | Z43: 66kV及以上升压站 | AA43: 220kV及以上升压站 | AB43: 全容量投运5年以内（含） | AC43: 全容量投运5年-10年（含） | AD43: 全容量投运10年-15年（含） | AE43: 全容量投运15年-20年（含） | AF43: 全容量投运20年以上
B44: 光伏电站 | C44: 100 | D44: 1 | E44: 0.95 | F44: 0.9 | G44: 0.85 | H44: 0.8 | I44: 0.75 | J44: 0.7 | K44: 1.1 | L44: 1 | M44: 0.9 | N44: 1 | O44: 1.05 | P44: 1 | Q44: 1.05 | R44: 1.1 | S44: 1 | T44: 1.1 | U44: 1.1 | V44: 1 | W44: 0.4 | X44: 0.6 | Y44: 0.75 | Z44: 1 | AA44: 1.1 | AB44: 0.8 | AC44: 0.9 | AD44: 1 | AE44: 1.1 | AF44: 1.2
C45: =IF(SUM(D45:AA45)=7,"正确","错误") -> #DIV/0! | D45: =IF(基本参数!$B$6<=10,1,0) -> 1 | E45: =IF(AND(基本参数!$B$6>10,基本参数!$B$6<=20),1,0) -> 0 | F45: =IF(AND(基本参数!$B$6>20,基本参数!$B$6<=40),1,0) -> 0 | G45: =IF(AND(基本参数!$B$6>40,基本参数!$B$6<=60),1,0) -> 0 | H45: =IF(AND(基本参数!$B$6>60,基本参数!$B$6<=80),1,0) -> 0 | I45: =IF(AND(基本参数!$B$6>80,基本参数!$B$6<=100),1,0) -> 0 | J45: =IF(基本参数!$B$6>100,1,0) -> 0 | K45: =IF(基本信息!$D$17=K43,1,0) -> 0 | L45: =IF(基本信息!$D$17=L43,1,0) -> 0 | M45: =IF(基本信息!$D$17=M43,1,0) -> 1 | N45: =IF(基本参数!$B$7/基本参数!$B$6<=1.05,1,0) -> #DIV/0! | O45: =IF(基本参数!$B$7/基本参数!$B$6>1.05,1,0) -> #DIV/0! | P45: =IF(基本信息!#REF!=P43,1,0) -> #REF! | Q45: =IF(基本信息!#REF!=Q43,1,0) -> #REF! | R45: =IF(基本信息!#REF!=R43,1,0) -> #REF! | S45: =Q10 -> #REF! | T45: =SUM(R10:T10) -> #REF! | U45: =IF(基本信息!$D$18=U43,1,0) -> 0 | V45: =IF(基本信息!$D$18=V43,1,0) -> 0 | W45: =IF(基本信息!$D$19=W43,1,0) -> 0 | X45: =IF(基本信息!$D$19=X43,1,0) -> 0 | Y45: =IF(基本信息!$D$19=Y43,1,0) -> 0 | Z45: =IF(基本信息!$D$19=Z43,1,0) -> 0 | AA45: =IF(基本信息!$D$19=AA43,1,0) -> 0
C46: XXMW委托运维1-5年 | D46: 6-10年 | E46: 11-15年 | F46: 16-20年 | G46: 20年以上
C47: =C44*SUMPRODUCT(D44:J44,D45:J45)*SUMPRODUCT(K44:M44,K45:M45)*SUMPRODUCT(N44:O44,N45:O45)*SUMPRODUCT(P44:R44,P45:R45)*SUMPRODUCT(S44:T44,S45:T45)*SUMPRODUCT(U44:V44,U45:V45)*SUMPRODUCT(W44:AA44,W45:AA45)*AB44 -> #DIV/0! | D47: =$C$47/$AB$44*AC44 -> #DIV/0! | E47: =$C$47/$AB$44*AD44 -> #DIV/0! | F47: =$C$47/$AB$44*AE44 -> #DIV/0! | G47: =$C$47/$AB$44*AF44 -> #DIV/0!
B51: 人工取值
B52: 人工成本 | C52: 取值 | D52: 华北 | E52: 东北 | F52: 华东 | G52: 华南 | H52: 华中 | I52: 西南 | J52: 西北
C53: =_xlfn.XLOOKUP(地区辅助页!H1,D52:J52,D53:J53,"",0) -> 38.7 | D53: 38.7 | E53: 38.7 | F53: 49.56 | G53: 49.56 | H53: 39.5 | I53: 36 | J53: 38.5
B55: 运维定员 | C55: 取值 | D55: 集中监控模式（MW) | H55: 现地监控模式（MW) | L55: 委托运维模式（MW）
D56: 50以下 | E56: 50-99 | F56: 100-199 | G56: 200以上 | H56: 50以下 | I56: 50-99 | J56: 100-199 | K56: 200以上 | L56: 30（含）以下 | M56: 30-100 | N56: 100-500 | O56: 500-1000 | P56: 1000以上
C57: =SUMPRODUCT(D57:P57,D58:P58) -> #REF! | D57: =0.109*基本参数!$B$6 -> 0 | E57: =0.068*基本参数!$B$6 -> 0 | F57: =0.05*基本参数!$B$6 -> 0 | G57: =0.03*基本参数!$B$6 -> 0 | H57: =0.2*基本参数!$B$6 -> 0 | I57: =0.1*基本参数!$B$6 -> 0 | J57: =0.084*基本参数!$B$6 -> 0 | K57: =0.03*基本参数!$B$6 -> 0 | L57: 1 | M57: 2 | N57: 3 | O57: 4 | P57: 5
C58: =IF(SUM(D58:P58)=1,"正确","错误") -> #REF! | D58: =IF(AND(基本信息!#REF!="集团自主运维标准",基本参数!$B$6<50),1,0) -> #REF! | E58: =IF(AND(基本信息!#REF!="集团自主运维标准",基本参数!$B$6>=50,基本参数!$B$6<100),1,0) -> #REF! | F58: =IF(AND(基本信息!#REF!="集团自主运维标准",基本参数!$B$6>=100,基本参数!$B$6<200),1,0) -> #REF! | G58: =IF(AND(基本信息!#REF!="集团自主运维标准",基本参数!$B$6>=200),1,0) -> #REF! | L58: =IF(AND(基本信息!#REF!="委托运维",基本参数!$B$6<=30),1,0) -> #REF! | M58: =IF(AND(基本信息!#REF!="委托运维",基本参数!$B$6>30,基本参数!$B$6<=100),1,0) -> #REF! | N58: =IF(AND(基本信息!#REF!="委托运维",基本参数!$B$6>100,基本参数!$B$6<=500),1,0) -> #REF! | O58: =IF(AND(基本信息!#REF!="委托运维",基本参数!$B$6>500,基本参数!$B$6<=1000),1,0) -> #REF! | P58: =IF(AND(基本信息!#REF!="委托运维",基本参数!$B$6>1000),1,0) -> #REF!

Sheet 电价电量取值表
A1: 各省光伏电价、弃电率参考值（标准1） | Q1: 各省光伏电价、弃电率参考值（标准2）
A2: 省份 | B2: 电价参考值 | I2: 弃电率参考值 | Q2: 省份 | R2: 电价参考值 | Y2: 弃电率参考值
B3: 2024年电价 | C3: 2025年预测电价 | D3: 2026年预测电价 | E3: 2027年预测电价 | F3: 2028年预测电价 | G3: 2029年预测电价 | H3: 2030年预测电价 | I3: 2024年弃电 | J3: 2025年预测弃电 | K3: 2026年预测弃电 | L3: 2027年预测弃电 | M3: 2028年预测弃电 | N3: 2029年预测弃电 | O3: 2030年预测弃电 | R3: 2024年电价 | S3: 2025年预测电价 | T3: 2026年预测电价 | U3: 2027年预测电价 | V3: 2028年预测电价 | W3: 2029年预测电价 | X3: 2030年预测电价 | Y3: 2024年弃电 | Z3: 2025年预测弃电 | AA3: 2026年预测弃电 | AB3: 2027年预测弃电 | AC3: 2028年预测弃电 | AD3: 2029年预测弃电 | AE3: 2030年预测弃电
A4: 北京 | B4: 0.3598 | C4: 0.3598 | D4: 0.3598 | E4: 0.3598 | F4: 0.3598 | G4: 0.3598 | H4: 0.3598 | I4: 0 | J4: 0.0067 | K4: 0.0133 | L4: 0.02 | M4: 0.0267 | N4: 0.0333 | O4: 0.04 | Q4: 北京 | R4: 0.3598 | S4: 0.3538 | T4: 0.3478 | U4: 0.3418 | V4: 0.3358 | W4: 0.3298 | X4: 0.3238 | Y4: 0 | Z4: 0.004 | AA4: 0.008 | AB4: 0.012 | AC4: 0.016 | AD4: 0.02 | AE4: 0.024
A5: 天津 | B5: 0.4175 | C5: 0.4088 | D5: 0.4002 | E5: 0.3915 | F5: 0.3828 | G5: 0.3742 | H5: 0.3655 | I5: 0.0174 | J5: 0.0195 | K5: 0.0216 | L5: 0.0237 | M5: 0.0258 | N5: 0.0279 | O5: 0.03 | Q5: 天津 | R5: 0.4175 | S5: 0.3967 | T5: 0.3758 | U5: 0.355 | V5: 0.3341 | W5: 0.3133 | X5: 0.2924 | Y5: 0.0174 | Z5: 0.0165 | AA5: 0.0156 | AB5: 0.0147 | AC5: 0.0138 | AD5: 0.0129 | AE5: 0.012
A6: 冀北 | B6: 0.3526 | C6: 0.3413 | D6: 0.33 | E6: 0.3187 | F6: 0.3074 | G6: 0.2961 | H6: 0.2848 | I6: 0.0681 | J6: 0.0901 | K6: 0.1121 | L6: 0.1341 | M6: 0.156 | N6: 0.178 | O6: 0.2 | Q6: 冀北 | R6: 0.3526 | S6: 0.3191 | T6: 0.2856 | U6: 0.2521 | V6: 0.2186 | W6: 0.1851 | X6: 0.1516 | Y6: 0.0681 | Z6: 0.0868 | AA6: 0.1054 | AB6: 0.1241 | AC6: 0.1427 | AD6: 0.1614 | AE6: 0.18
A7: 冀南 | B7: 0.3526 | C7: 0.3408 | D7: 0.329 | E7: 0.3172 | F7: 0.3054 | G7: 0.2936 | H7: 0.2818 | I7: 0.0681 | J7: 0.0901 | K7: 0.1121 | L7: 0.1341 | M7: 0.156 | N7: 0.178 | O7: 0.2 | Q7: 冀南 | R7: 0.3526 | S7: 0.3187 | T7: 0.2848 | U7: 0.251 | V7: 0.2171 | W7: 0.1832 | X7: 0.1493 | Y7: 0.0681 | Z7: 0.0868 | AA7: 0.1054 | AB7: 0.1241 | AC7: 0.1427 | AD7: 0.1614 | AE7: 0.18
A8: 山西 | B8: 0.2033 | C8: 0.207 | D8: 0.207 | E8: 0.207 | F8: 0.207 | G8: 0.207 | H8: 0.207 | I8: 0.0639 | J8: 0.0741 | K8: 0.0843 | L8: 0.0945 | M8: 0.1046 | N8: 0.1148 | O8: 0.125 | Q8: 山西 | R8: 0.2033 | S8: 0.2026 | T8: 0.2019 | U8: 0.2013 | V8: 0.2006 | W8: 0.1999 | X8: 0.1992 | Y8: 0.0639 | Z8: 0.0693 | AA8: 0.0746 | AB8: 0.08 | AC8: 0.0853 | AD8: 0.0907 | AE8: 0.096
A9: 蒙东 | B9: 0.265 | C9: 0.2579 | D9: 0.2508 | E9: 0.2437 | F9: 0.2366 | G9: 0.2295 | H9: 0.2224 | I9: 0.0509 | J9: 0.0658 | K9: 0.0806 | L9: 0.0955 | M9: 0.1103 | N9: 0.1252 | O9: 0.14 | Q9: 蒙东 | R9: 0.265 | S9: 0.2512 | T9: 0.2374 | U9: 0.2236 | V9: 0.2097 | W9: 0.1959 | X9: 0.1821 | Y9: 0.0509 | Z9: 0.0624 | AA9: 0.0739 | AB9: 0.0855 | AC9: 0.097 | AD9: 0.1085 | AE9: 0.12
A10: 蒙西 | B10: 0.2435 | C10: 0.2774 | D10: 0.2647 | E10: 0.2521 | F10: 0.2394 | G10: 0.2268 | H10: 0.2142 | I10: 0.0509 | J10: 0.0674 | K10: 0.0839 | L10: 0.1005 | M10: 0.117 | N10: 0.1335 | O10: 0.15 | Q10: 蒙西 | R10: 0.2435 | S10: 0.2277 | T10: 0.212 | U10: 0.1962 | V10: 0.1804 | W10: 0.1647 | X10: 0.1489 | Y10: 0.0509 | Z10: 0.0624 | AA10: 0.0739 | AB10: 0.0855 | AC10: 0.097 | AD10: 0.1085 | AE10: 0.12
A11: 辽宁 | B11: 0.4022 | C11: 0.3783 | D11: 0.3545 | E11: 0.3306 | F11: 0.3067 | G11: 0.2829 | H11: 0.259 | I11: 0.014 | J11: 0.0367 | K11: 0.0593 | L11: 0.082 | M11: 0.1047 | N11: 0.1273 | O11: 0.15 | Q11: 辽宁 | R11: 0.4022 | S11: 0.3677 | T11: 0.3331 | U11: 0.2986 | V11: 0.264 | W11: 0.2295 | X11: 0.1949 | Y11: 0.014 | Z11: 0.0357 | AA11: 0.0573 | AB11: 0.079 | AC11: 0.1007 | AD11: 0.1223 | AE11: 0.144
A12: 吉林 | B12: 0.3246 | C12: 0.3103 | D12: 0.2959 | E12: 0.2816 | F12: 0.2672 | G12: 0.2529 | H12: 0.2385 | I12: 0.0186 | J12: 0.0422 | K12: 0.0657 | L12: 0.0893 | M12: 0.1129 | N12: 0.1364 | O12: 0.16 | Q12: 吉林 | R12: 0.3246 | S12: 0.3036 | T12: 0.2826 | U12: 0.2616 | V12: 0.2406 | W12: 0.2196 | X12: 0.1986 | Y12: 0.0186 | Z12: 0.0395 | AA12: 0.0604 | AB12: 0.0813 | AC12: 0.1022 | AD12: 0.1231 | AE12: 0.144
A13: 黑龙江 | B13: 0.3422 | C13: 0.328 | D13: 0.3138 | E13: 0.2997 | F13: 0.2855 | G13: 0.2713 | H13: 0.2571 | I13: 0.0441 | J13: 0.0701 | K13: 0.0961 | L13: 0.1221 | M13: 0.148 | N13: 0.174 | O13: 0.2 | Q13: 黑龙江 | R13: 0.3422 | S13: 0.3124 | T13: 0.2825 | U13: 0.2527 | V13: 0.2229 | W13: 0.193 | X13: 0.1632 | Y13: 0.0441 | Z13: 0.0668 | AA13: 0.0894 | AB13: 0.1121 | AC13: 0.1347 | AD13: 0.1574 | AE13: 0.18
A14: 上海 | B14: 0.4736 | C14: 0.463 | D14: 0.4524 | E14: 0.4418 | F14: 0.4312 | G14: 0.4206 | H14: 0.41 | I14: 0.0003 | J14: 0.0003 | K14: 0.0002 | L14: 0.0002 | M14: 0.0001 | N14: 0.0001 | O14: 0 | Q14: 上海 | R14: 0.4736 | S14: 0.4501 | T14: 0.4265 | U14: 0.403 | V14: 0.3795 | W14: 0.3559 | X14: 0.3324 | Y14: 0.0003 | Z14: 0.0003 | AA14: 0.0002 | AB14: 0.0002 | AC14: 0.0001 | AD14: 0.0001 | AE14: 0
A15: 江苏 | B15: 0.4534 | C15: 0.4335 | D15: 0.4136 | E15: 0.3937 | F15: 0.3738 | G15: 0.3539 | H15: 0.334 | I15: 0.0041 | J15: 0.0134 | K15: 0.0227 | L15: 0.0321 | M15: 0.0414 | N15: 0.0507 | O15: 0.06 | Q15: 江苏 | R15: 0.4534 | S15: 0.4156 | T15: 0.3779 | U15: 0.3401 | V15: 0.3023 | W15: 0.2646 | X15: 0.2268 | Y15: 0.0041 | Z15: 0.0134 | AA15: 0.0227 | AB15: 0.0321 | AC15: 0.0414 | AD15: 0.0507 | AE15: 0.06
... A36: 新疆 | B36: 0.1681 | C36: 0.1681 | D36: 0.1681 | E36: 0.1681 | F36: 0.1681 | G36: 0.1681 | H36: 0.1681 | I36: 0.2222 | J36: 0.2218 | K36: 0.2215 | L36: 0.2211 | M36: 0.2207 | N36: 0.2204 | O36: 0.22 | Q36: 新疆 | R36: 0.1681 | S36: 0.1555 | T36: 0.1429 | U36: 0.1303 | V36: 0.1177 | W36: 0.1051 | X36: 0.0925 | Y36: 0.2222 | Z36: 0.2152 | AA36: 0.2081 | AB36: 0.2011 | AC36: 0.1941 | AD36: 0.187 | AE36: 0.18

Sheet 基本参数
A1: 年限和装机容量 | C1: 财务指标一览表
A2: 计算期（年） | B2: =B3+B4 -> 26 | C2: =财务指标一览表!B3 -> 投资回收期（税前） | E2: 年 | F2: =财务指标一览表!D3 -> #N/A | G2: =财务指标一览表!B11 -> 总投资收益率（ROI） | I2: % | J2: =财务指标一览表!D11 -> #VALUE! | K2: =财务指标一览表!B15 -> 盈亏平衡点（生产能力利用率） | M2: % | N2: =财务指标一览表!D15 -> #REF!
A3: 建设期（年） | B3: 1 | C3: =财务指标一览表!B4 -> 投资回收期（税后） | E3: 年 | F3: =财务指标一览表!D4 -> #N/A | G3: =财务指标一览表!B12 -> 投资利税率 | I3: % | J3: =财务指标一览表!D12 -> #VALUE! | K3: =财务指标一览表!B17 -> 度电投资 | M3: 元/kWh | N3: =财务指标一览表!D17 -> #DIV/0!
A4: 实际运行期（年） | B4: 25 | C4: =财务指标一览表!B5 -> 全投资内部收益率（税前） | E4: % | F4: =财务指标一览表!D5 -> #VALUE! | G4: =财务指标一览表!B13 -> 资本金净利润率（ROE） | I4: % | J4: =财务指标一览表!D13 -> #VALUE! | K4: =财务指标一览表!B18 -> 度电利润 | M4: 元/kWh | N4: =财务指标一览表!D18 -> #VALUE!
A5: 项目类型 | B5: 光伏 | C5: =财务指标一览表!B6 -> 全投资内部收益率（税后） | E5: % | F5: =财务指标一览表!D6 -> #VALUE! | G5: =财务指标一览表!B14 -> 资产负债率（最大值） | I5: % | J5: =财务指标一览表!D14 -> #DIV/0! | K5: =财务指标一览表!B19 -> 平准化度电成本（LCOE） | M5: 元/kWh | N5: =财务指标一览表!D19 -> #VALUE!
A6: 交流测装机容量（MW） | B6: =基本信息!D4 -> 0 | C6: =财务指标一览表!B7 -> 全投资净现值（税前） | E6: 万元 | F6: =财务指标一览表!D7 -> #VALUE! | G6: 年份 | J6: 第1年 | K6: 第2年 | L6: 第3年 | M6: 第4年 | N6: 第5年
A7: 直流侧装机容量（MWp） | B7: =基本信息!D5 -> 0 | C7: =财务指标一览表!B8 -> 全投资净现值（税后） | E7: 万元 | F7: =财务指标一览表!D8 -> #VALUE! | G7: 前五年利润总额 | I7: 万元 | J7: =财务指标一览表!D21 -> #VALUE! | K7: =财务指标一览表!E21 -> #VALUE! | L7: =财务指标一览表!F21 -> #VALUE! | M7: =财务指标一览表!G21 -> #VALUE! | N7: =财务指标一览表!H21 -> #VALUE!
A8: 运营期起始年 | B8: =基本信息!D3 -> 0 | C8: =财务指标一览表!B9 -> 资本金内部收益率 | E8: % | F8: =财务指标一览表!D9 -> #VALUE! | G8: 前五年EVA | I8: 万元 | J8: =财务指标一览表!D22 -> #VALUE! | K8: =财务指标一览表!E22 -> #VALUE! | L8: =财务指标一览表!F22 -> #VALUE! | M8: =财务指标一览表!G22 -> #VALUE! | N8: =财务指标一览表!H22 -> #VALUE!
A9: 第一年施工月数 | B9: 12 | C9: =财务指标一览表!B10 -> 资本金财务净现值 | E9: 万元 | F9: =财务指标一览表!D10 -> #VALUE! | G9: 前五年ROE | I9: % | J9: =财务指标一览表!D23 -> #VALUE! | K9: =财务指标一览表!E23 -> #VALUE! | L9: =财务指标一览表!F23 -> #VALUE! | M9: =财务指标一览表!G23 -> #VALUE! | N9: =财务指标一览表!H23 -> #VALUE!
A10: 最后一年施工月数 | B10: 12 | C10: 其他指标
A11: 建设期投资 | C11: 总投资（含流动资金） | E11: 万元 | F11: =投资计划与资金筹措表!C5 -> 0 | G11: 动态投资 | I11: 万元 | J11: =B12+B20 -> 0 | K11: 动态千瓦造价 | M11: 元/kWh | N11: =J11/B7*10 -> #DIV/0!
A12: 静态投资 | B12: =基本信息!D6 -> 0 | C12: 年均理论利用小时 | E12: h | F12: =收入和税金!C3*SUM(收入和税金!D5:AB5)/100/B4 -> 0 | G12: 弃电率（全寿期平均值） | I12: % | J12: =SUM(收入和税金!D7:AB7)/B4 -> #VALUE! | K12: 电价（全寿期平均值） | M12: 元/kWh | N12: =SUM(电价电量计算表!D13:AB13)/B4 -> #VALUE!
A13: 其中：无形资产（万元） | B13: 0
A14: 其中：其他资产（万元） | B14: 0
A15: 可抵扣税金（万元） | B15: =基本信息!D8 -> 0 | C15: 增值税部分
A16: 申请一次性留底退税 | B16: 否
A17: 资本金比例（%） | B17: 20
A18: 建设期利息计算方式 | B18: 手动输入
A19: 建设期利息（万元，手动输入） | B19: =基本信息!D7 -> 0
A20: 建设期利息（万元，最终） | B20: =IF(B18="自动计算",B12*(1-B17%)*B9*B36%/(24+B36%*B17%*B9),B19) -> 0
A21: 基准收益率
A22: 资本金基准收益率（%） | B22: 8
A23: 行业基准收益率（所得税前）（%） | B23: 8
A24: 行业基准收益率（所得税后）（%） | B24: 7
A25: 资本成本率（%） | B25: 3.29 | C25: wacc值，融资成本，借贷成本
A26: 流动资金
A27: 单位千瓦指标（元/kW） | B27: 30
A28: 自有流动资金比例（%） | B28: 100
A29: 流动资金贷款利率（%） | B29: =B31 -> 3
A30: 短期贷款
A31: 短期贷款利率（%） | B31: 3 | C31: 弥补亏损还长贷
A32: 长期借款
A33: 预定还款期（年） | B33: 15
A34: 运营期宽限（年） | B34: 0
A35: 还本付息方式 | B35: 等额还本利息照付
A36: 长期贷款利率（%） | B36: 3.5
A37: 年份 | B37: 第1年 | C37: 第2年 | D37: 第3年 | E37: 第4年 | F37: 第5年 | G37: 第6年 | H37: 第7年 | I37: 第8年 | J37: 第9年 | K37: 第10年 | L37: 第11年 | M37: 第12年 | N37: 第13年 | O37: 第14年 | P37: 第15年 | Q37: 第16年 | R37: 第17年 | S37: 第18年 | T37: 第19年 | U37: 第20年 | V37: 第21年 | W37: 第22年 | X37: 第23年 | Y37: 第24年 | Z37: 第25年 | AA37: 第26年
A38: 约定还款

Sheet 成本费用
A1: 折旧费
A2: 计算方式（选择） | C2: 年限折旧法
A3: 残值率 | B3: % | C3: 3
A4: 折旧年限 | B4: 年 | C4: 20
B5: 年份 | C5: 第1年 | D5: 第2年 | E5: 第3年 | F5: 第4年 | G5: 第5年 | H5: 第6年 | I5: 第7年 | J5: 第8年 | K5: 第9年 | L5: 第10年 | M5: 第11年 | N5: 第12年 | O5: 第13年 | P5: 第14年 | Q5: 第15年 | R5: 第16年 | S5: 第17年 | T5: 第18年 | U5: 第19年 | V5: 第20年 | W5: 第21年 | X5: 第22年 | Y5: 第23年 | Z5: 第24年 | AA5: 第25年 | AB5: 第26年
A6: 折旧费：年限折旧法 | B6: 万元 | D6: =$C89*(1-$C$3/100)/$C$4 -> 0 | E6: =$C89*(1-$C$3/100)/$C$4 -> 0 | F6: =$C89*(1-$C$3/100)/$C$4 -> 0 | G6: =$C89*(1-$C$3/100)/$C$4 -> 0 | H6: =$C89*(1-$C$3/100)/$C$4 -> 0 | I6: =$C89*(1-$C$3/100)/$C$4 -> 0 | J6: =$C89*(1-$C$3/100)/$C$4 -> 0 | K6: =$C89*(1-$C$3/100)/$C$4 -> 0 | ... W6: =$C89*(1-$C$3/100)/$C$4 -> 0 | X6: 0 | Y6: 0 | Z6: 0 | AA6: 0 | AB6: 0
A7: 折旧费：手动输入 | B7: 万元
A8: 最终折旧费 | B8: 万元 | D8: =IF($C$2="年限折旧法",D6,D7) -> 0 | E8: =IF($C$2="年限折旧法",E6,E7) -> 0 | F8: =IF($C$2="年限折旧法",F6,F7) -> 0 | G8: =IF($C$2="年限折旧法",G6,G7) -> 0 | H8: =IF($C$2="年限折旧法",H6,H7) -> 0 | I8: =IF($C$2="年限折旧法",I6,I7) -> 0 | J8: =IF($C$2="年限折旧法",J6,J7) -> 0 | K8: =IF($C$2="年限折旧法",K6,K7) -> 0 | ... AB8: =IF($C$2="年限折旧法",AB6,AB7) -> 0
A9: 维修费
A10: 计算方式（选择） | C10: 按比例
B11: 年份 | C11: 第1年 | D11: 第2年 | E11: 第3年 | F11: 第4年 | G11: 第5年 | H11: 第6年 | I11: 第7年 | J11: 第8年 | K11: 第9年 | L11: 第10年 | M11: 第11年 | N11: 第12年 | O11: 第13年 | P11: 第14年 | Q11: 第15年 | R11: 第16年 | S11: 第17年 | T11: 第18年 | U11: 第19年 | V11: 第20年 | W11: 第21年 | X11: 第22年 | Y11: 第23年 | Z11: 第24年 | AA11: 第25年 | AB11: 第26年
A12: 按费率 | B12: % | D12: 0 | E12: =D12 -> 0 | F12: =E12 -> 0 | G12: =F12 -> 0 | H12: =G12 -> 0 | I12: =H12 -> 0 | J12: =I12 -> 0 | K12: =J12 -> 0 | L12: =K12 -> 0 | ... AB12: =AA12 -> 0
B13: 万元 | D13: =$C$89*D12% -> 0 | E13: =$C$89*E12% -> 0 | F13: =$C$89*F12% -> 0 | G13: =$C$89*G12% -> 0 | H13: =$C$89*H12% -> 0 | I13: =$C$89*I12% -> 0 | J13: =$C$89*J12% -> 0 | K13: =$C$89*K12% -> 0 | ... AB13: =$C$89*AB12% -> 0
A14: 按比例 | B14: 元/kW | D14: =IF(COLUMN()-3<=成本费用取值表!$H$14,成本费用取值表!$C$18,成本费用取值表!$D$18)*IF(基本信息!#REF!="自主运维",1,0) -> #REF! | E14: =IF(COLUMN()-3<=成本费用取值表!$H$14,成本费用取值表!$C$18,成本费用取值表!$D$18)*IF(基本信息!#REF!="自主运维",1,0) -> #REF! | F14: =IF(COLUMN()-3<=成本费用取值表!$H$14,成本费用取值表!$C$18,成本费用取值表!$D$18)*IF(基本信息!#REF!="自主运维",1,0) -> #REF! | G14: =IF(COLUMN()-3<=成本费用取值表!$H$14,成本费用取值表!$C$18,成本费用取值表!$D$18)*IF(基本信息!#REF!="自主运维",1,0) -> #REF! | H14: =IF(COLUMN()-3<=成本费用取值表!$H$14,成本费用取值表!$C$18,成本费用取值表!$D$18)*IF(基本信息!#REF!="自主运维",1,0) -> #REF! | I14: =IF(COLUMN()-3<=成本费用取值表!$H$14,成本费用取值表!$C$18,成本费用取值表!$D$18)*IF(基本信息!#REF!="自主运维",1,0) -> #REF! | J14: =IF(COLUMN()-3<=成本费用取值表!$H$14,成本费用取值表!$C$18,成本费用取值表!$D$18)*IF(基本信息!#REF!="自主运维",1,0) -> #REF! | K14: =IF(COLUMN()-3<=成本费用取值表!$H$14,成本费用取值表!$C$18,成本费用取值表!$D$18)*IF(基本信息!#REF!="自主运维",1,0) -> #REF! | ... AB14: =IF(COLUMN()-3<=成本费用取值表!$H$14,成本费用取值表!$C$18,成本费用取值表!$D$18)*IF(基本信息!#REF!="自主运维",1,0) -> #REF!
B15: 万元 | D15: =D14*基本参数!$B7/10 -> #REF! | E15: =E14*基本参数!$B7/10 -> #REF! | F15: =F14*基本参数!$B7/10 -> #REF! | G15: =G14*基本参数!$B7/10 -> #REF! | H15: =H14*基本参数!$B7/10 -> #REF! | I15: =I14*基本参数!$B7/10 -> #REF! | J15: =J14*基本参数!$B7/10 -> #REF! | K15: =K14*基本参数!$B7/10 -> #REF! | ... AB15: =AB14*基本参数!$B7/10 -> #REF!
A16: 手动输入 | B16: 万元
A17: 最终维修费 | B17: 万元 | D17: =IF($C$10="按费率",D13,IF($C$10="按比例",D15,D16))*IF(OR(基本参数!$B$2<=COLUMN()-3,COLUMN()-3<基本参数!$B$3),0,1) -> #REF! | E17: =IF($C$10="按费率",E13,IF($C$10="按比例",E15,E16))*IF(OR(基本参数!$B$2<=COLUMN()-3,COLUMN()-3<基本参数!$B$3),0,1) -> #REF! | F17: =IF($C$10="按费率",F13,IF($C$10="按比例",F15,F16))*IF(OR(基本参数!$B$2<=COLUMN()-3,COLUMN()-3<基本参数!$B$3),0,1) -> #REF! | G17: =IF($C$10="按费率",G13,IF($C$10="按比例",G15,G16))*IF(OR(基本参数!$B$2<=COLUMN()-3,COLUMN()-3<基本参数!$B$3),0,1) -> #REF! | H17: =IF($C$10="按费率",H13,IF($C$10="按比例",H15,H16))*IF(OR(基本参数!$B$2<=COLUMN()-3,COLUMN()-3<基本参数!$B$3),0,1) -> #REF! | I17: =IF($C$10="按费率",I13,IF($C$10="按比例",I15,I16))*IF(OR(基本参数!$B$2<=COLUMN()-3,COLUMN()-3<基本参数!$B$3),0,1) -> #REF! | J17: =IF($C$10="按费率",J13,IF($C$10="按比例",J15,J16))*IF(OR(基本参数!$B$2<=COLUMN()-3,COLUMN()-3<基本参数!$B$3),0,1) -> #REF! | K17: =IF($C$10="按费率",K13,IF($C$10="按比例",K15,K16))*IF(OR(基本参数!$B$2<=COLUMN()-3,COLUMN()-3<基本参数!$B$3),0,1) -> #REF! | ... AB17: =IF($C$10="按费率",AB13,IF($C$10="按比例",AB15,AB16))*IF(OR(基本参数!$B$2<=COLUMN()-3,COLUMN()-3<基本参数!$B$3),0,1) -> #REF!
A18: 人工工资及福利
A19: 计算方式（选择） | C19: 自动计算
B20: 年份 | C20: 第1年 | D20: 第2年 | E20: 第3年 | F20: 第4年 | G20: 第5年 | H20: 第6年 | I20: 第7年 | J20: 第8年 | K20: 第9年 | L20: 第10年 | M20: 第11年 | N20: 第12年 | O20: 第13年 | P20: 第14年 | Q20: 第15年 | R20: 第16年 | S20: 第17年 | T20: 第18年 | U20: 第19年 | V20: 第20年 | W20: 第21年 | X20: 第22年 | Y20: 第23年 | Z20: 第24年 | AA20: 第25年 | AB20: 第26年
A21: 人员数量 | B21: 人 | D21: =成本费用取值表!C57 -> #REF! | E21: =D21 -> #REF! | F21: =E21 -> #REF! | G21: =F21 -> #REF! | H21: =G21 -> #REF! | I21: =H21 -> #REF! | J21: =I21 -> #REF! | K21: =J21 -> #REF! | L21: =K21 -> #REF! | ... AB21: =AA21 -> #REF!
A22: 人工年平均工资 | B22: 万元 | D22: =成本费用取值表!C53 -> 38.7 | E22: =D22 -> 38.7 | F22: =E22 -> 38.7 | G22: =F22 -> 38.7 | H22: =G22 -> 38.7 | I22: =H22 -> 38.7 | J22: =I22 -> 38.7 | K22: =J22 -> 38.7 | L22: =K22 -> 38.7 | ... AB22: =AA22 -> 38.7
A23: 福利费及其他 | B23: % | D23: 0 | E23: =D23 -> 0 | F23: =E23 -> 0 | G23: =F23 -> 0 | H23: =G23 -> 0 | I23: =H23 -> 0 | J23: =I23 -> 0 | K23: =J23 -> 0 | L23: =K23 -> 0 | ... AB23: =AA23 -> 0
A24: 手动输入 | B24: 万元
A25: 最终人工费 | B25: 万元 | D25: =IF($C$19="自动计算",D21*D22*(1+D23/100),D24)*IF(OR(基本参数!$B$2<=COLUMN()-3,COLUMN()-3<基本参数!$B$3),0,1) -> #REF! | E25: =IF($C$19="自动计算",E21*E22*(1+E23/100),E24)*IF(OR(基本参数!$B$2<=COLUMN()-3,COLUMN()-3<基本参数!$B$3),0,1) -> #REF! | F25: =IF($C$19="自动计算",F21*F22*(1+F23/100),F24)*IF(OR(基本参数!$B$2<=COLUMN()-3,COLUMN()-3<基本参数!$B$3),0,1) -> #REF! | G25: =IF($C$19="自动计算",G21*G22*(1+G23/100),G24)*IF(OR(基本参数!$B$2<=COLUMN()-3,COLUMN()-3<基本参数!$B$3),0,1) -> #REF! | H25: =IF($C$19="自动计算",H21*H22*(1+H23/100),H24)*IF(OR(基本参数!$B$2<=COLUMN()-3,COLUMN()-3<基本参数!$B$3),0,1) -> #REF! | I25: =IF($C$19="自动计算",I21*I22*(1+I23/100),I24)*IF(OR(基本参数!$B$2<=COLUMN()-3,COLUMN()-3<基本参数!$B$3),0,1) -> #REF! | J25: =IF($C$19="自动计算",J21*J22*(1+J23/100),J24)*IF(OR(基本参数!$B$2<=COLUMN()-3,COLUMN()-3<基本参数!$B$3),0,1) -> #REF! | K25: =IF($C$19="自动计算",K21*K22*(1+K23/100),K24)*IF(OR(基本参数!$B$2<=COLUMN()-3,COLUMN()-3<基本参数!$B$3),0,1) -> #REF! | ... AB25: =IF($C$19="自动计算",AB21*AB22*(1+AB23/100),AB24)*IF(OR(基本参数!$B$2<=COLUMN()-3,COLUMN()-3<基本参数!$B$3),0,1) -> #REF!
A26: 保险费
A27: 计算方式（选择） | C27: 按固定资产原值
A28: 费率 | B28: % | C28: =IF(成本费用取值表!T10=1,0.1246,0.0447) -> #REF!
B29: 年份 | C29: 第1年 | D29: 第2年 | E29: 第3年 | F29: 第4年 | G29: 第5年 | H29: 第6年 | I29: 第7年 | J29: 第8年 | K29: 第9年 | L29: 第10年 | M29: 第11年 | N29: 第12年 | O29: 第13年 | P29: 第14年 | Q29: 第15年 | R29: 第16年 | S29: 第17年 | T29: 第18年 | U29: 第19年 | V29: 第20年 | W29: 第21年 | X29: 第22年 | Y29: 第23年 | Z29: 第24年 | AA29: 第25年 | AB29: 第26年
A30: 按固定资产原值 | B30: 万元 | D30: =D89*$C$28/100 -> #REF! | E30: =E89*$C$28/100 -> #REF! | F30: =F89*$C$28/100 -> #REF! | G30: =G89*$C$28/100 -> #REF! | H30: =H89*$C$28/100 -> #REF! | I30: =I89*$C$28/100 -> #REF! | J30: =J89*$C$28/100 -> #REF! | K30: =K89*$C$28/100 -> #REF! | ... AB30: =AB89*$C$28/100 -> #REF!
A31: 按固定资产净值 | B31: 万元 | D31: =D90*$C$28/100 -> #REF! | E31: =E90*$C$28/100 -> #REF! | F31: =F90*$C$28/100 -> #REF! | G31: =G90*$C$28/100 -> #REF! | H31: =H90*$C$28/100 -> #REF! | I31: =I90*$C$28/100 -> #REF! | J31: =J90*$C$28/100 -> #REF! | K31: =K90*$C$28/100 -> #REF! | ... AB31: =AB90*$C$28/100 -> #REF!
A32: 手动输入 | B32: 万元
A33: 最终保险费 | B33: 万元 | D33: =IF($C$27="按固定资产原值",D30,IF($C$27="按固定资产净值",D31,D32))*IF(OR(基本参数!$B$2<=COLUMN()-3,COLUMN()-3<基本参数!$B$3),0,1) -> #REF! | E33: =IF($C$27="按固定资产原值",E30,IF($C$27="按固定资产净值",E31,E32))*IF(OR(基本参数!$B$2<=COLUMN()-3,COLUMN()-3<基本参数!$B$3),0,1) -> #REF! | F33: =IF($C$27="按固定资产原值",F30,IF($C$27="按固定资产净值",F31,F32))*IF(OR(基本参数!$B$2<=COLUMN()-3,COLUMN()-3<基本参数!$B$3),0,1) -> #REF! | G33: =IF($C$27="按固定资产原值",G30,IF($C$27="按固定资产净值",G31,G32))*IF(OR(基本参数!$B$2<=COLUMN()-3,COLUMN()-3<基本参数!$B$3),0,1) -> #REF! | H33: =IF($C$27="按固定资产原值",H30,IF($C$27="按固定资产净值",H31,H32))*IF(OR(基本参数!$B$2<=COLUMN()-3,COLUMN()-3<基本参数!$B$3),0,1) -> #REF! | I33: =IF($C$27="按固定资产原值",I30,IF($C$27="按固定资产净值",I31,I32))*IF(OR(基本参数!$B$2<=COLUMN()-3,COLUMN()-3<基本参数!$B$3),0,1) -> #REF! | J33: =IF($C$27="按固定资产原值",J30,IF($C$27="按固定资产净值",J31,J32))*IF(OR(基本参数!$B$2<=COLUMN()-3,COLUMN()-3<基本参数!$B$3),0,1) -> #REF! | K33: =IF($C$27="按固定资产原值",K30,IF($C$27="按固定资产净值",K31,K32))*IF(OR(基本参数!$B$2<=COLUMN()-3,COLUMN()-3<基本参数!$B$3),0,1) -> #REF! | ... AB33: =IF($C$27="按固定资产原值",AB30,IF($C$27="按固定资产净值",AB31,AB32))*IF(OR(基本参数!$B$2<=COLUMN()-3,COLUMN()-3<基本参数!$B$3),0,1) -> #REF!
A34: 材料费
A35: 计算方式（选择） | C35: 按比例
B36: 年份 | C36: 第1年 | D36: 第2年 | E36: 第3年 | F36: 第4年 | G36: 第5年 | H36: 第6年 | I36: 第7年 | J36: 第8年 | K36: 第9年 | L36: 第10年 | M36: 第11年 | N36: 第12年 | O36: 第13年 | P36: 第14年 | Q36: 第15年 | R36: 第16年 | S36: 第17年 | T36: 第18年 | U36: 第19年 | V36: 第20年 | W36: 第21年 | X36: 第22年 | Y36: 第23年 | Z36: 第24年 | AA36: 第25年 | AB36: 第26年
A37: 按比例 | B37: 元/kW | D37: =IF(COLUMN()-3<=成本费用取值表!$H$14,成本费用取值表!$C$28,成本费用取值表!$D$28)*IF(基本信息!#REF!="自主运维",1,0) -> #REF! | E37: =IF(COLUMN()-3<=成本费用取值表!$H$14,成本费用取值表!$C$28,成本费用取值表!$D$28)*IF(基本信息!#REF!="自主运维",1,0) -> #REF! | F37: =IF(COLUMN()-3<=成本费用取值表!$H$14,成本费用取值表!$C$28,成本费用取值表!$D$28)*IF(基本信息!#REF!="自主运维",1,0) -> #REF! | G37: =IF(COLUMN()-3<=成本费用取值表!$H$14,成本费用取值表!$C$28,成本费用取值表!$D$28)*IF(基本信息!#REF!="自主运维",1,0) -> #REF! | H37: =IF(COLUMN()-3<=成本费用取值表!$H$14,成本费用取值表!$C$28,成本费用取值表!$D$28)*IF(基本信息!#REF!="自主运维",1,0) -> #REF! | I37: =IF(COLUMN()-3<=成本费用取值表!$H$14,成本费用取值表!$C$28,成本费用取值表!$D$28)*IF(基本信息!#REF!="自主运维",1,0) -> #REF! | J37: =IF(COLUMN()-3<=成本费用取值表!$H$14,成本费用取值表!$C$28,成本费用取值表!$D$28)*IF(基本信息!#REF!="自主运维",1,0) -> #REF! | K37: =IF(COLUMN()-3<=成本费用取值表!$H$14,成本费用取值表!$C$28,成本费用取值表!$D$28)*IF(基本信息!#REF!="自主运维",1,0) -> #REF! | ... AB37: =IF(COLUMN()-3<=成本费用取值表!$H$14,成本费用取值表!$C$28,成本费用取值表!$D$28)*IF(基本信息!#REF!="自主运维",1,0) -> #REF!
B38: 万元 | D38: =D37*基本参数!$B$7/10 -> #REF! | E38: =E37*基本参数!$B$7/10 -> #REF! | F38: =F37*基本参数!$B$7/10 -> #REF! | G38: =G37*基本参数!$B$7/10 -> #REF! | H38: =H37*基本参数!$B$7/10 -> #REF! | I38: =I37*基本参数!$B$7/10 -> #REF! | J38: =J37*基本参数!$B$7/10 -> #REF! | K38: =K37*基本参数!$B$7/10 -> #REF! | ... AB38: =AB37*基本参数!$B$7/10 -> #REF!
A39: 手动输入 | B39: 万元
A40: 最终材料费 | B40: 万元 | D40: =IF($C$35="按比例",D38,D39)*IF(OR(基本参数!$B$2<=COLUMN()-3,COLUMN()-3<基本参数!$B$3),0,1) -> #REF! | E40: =IF($C$35="按比例",E38,E39)*IF(OR(基本参数!$B$2<=COLUMN()-3,COLUMN()-3<基本参数!$B$3),0,1) -> #REF! | F40: =IF($C$35="按比例",F38,F39)*IF(OR(基本参数!$B$2<=COLUMN()-3,COLUMN()-3<基本参数!$B$3),0,1) -> #REF! | G40: =IF($C$35="按比例",G38,G39)*IF(OR(基本参数!$B$2<=COLUMN()-3,COLUMN()-3<基本参数!$B$3),0,1) -> #REF! | H40: =IF($C$35="按比例",H38,H39)*IF(OR(基本参数!$B$2<=COLUMN()-3,COLUMN()-3<基本参数!$B$3),0,1) -> #REF! | I40: =IF($C$35="按比例",I38,I39)*IF(OR(基本参数!$B$2<=COLUMN()-3,COLUMN()-3<基本参数!$B$3),0,1) -> #REF! | J40: =IF($C$35="按比例",J38,J39)*IF(OR(基本参数!$B$2<=COLUMN()-3,COLUMN()-3<基本参数!$B$3),0,1) -> #REF! | K40: =IF($C$35="按比例",K38,K39)*IF(OR(基本参数!$B$2<=COLUMN()-3,COLUMN()-3<基本参数!$B$3),0,1) -> #REF! | ... AB40: =IF($C$35="按比例",AB38,AB39)*IF(OR(基本参数!$B$2<=COLUMN()-3,COLUMN()-3<基本参数!$B$3),0,1) -> #REF!
A41: 委托运维费
A42: 计算方式（选择） | C42: 按比例
B43: 年份 | C43: 第1年 | D43: 第2年 | E43: 第3年 | F43: 第4年 | G43: 第5年 | H43: 第6年 | I43: 第7年 | J43: 第8年 | K43: 第9年 | L43: 第10年 | M43: 第11年 | N43: 第12年 | O43: 第13年 | P43: 第14年 | Q43: 第15年 | R43: 第16年 | S43: 第17年 | T43: 第18年 | U43: 第19年 | V43: 第20年 | W43: 第21年 | X43: 第22年 | Y43: 第23年 | Z43: 第24年 | AA43: 第25年 | AB43: 第26年
A44: 按比例 | B44: 元/kW | D44: =_xlfn.IFS(COLUMN()-3<=5,成本费用取值表!$C$47,COLUMN()-3<=10,成本费用取值表!$D$47,COLUMN()-3<=15,成本费用取值表!$E$47,COLUMN()-3<=20,成本费用取值表!$F$47,COLUMN()-3>20,成本费用取值表!$G$47)*IF(基本信息!#REF!="委托运维",1,0) -> #DIV/0! | E44: =_xlfn.IFS(COLUMN()-3<=5,成本费用取值表!$C$47,COLUMN()-3<=10,成本费用取值表!$D$47,COLUMN()-3<=15,成本费用取值表!$E$47,COLUMN()-3<=20,成本费用取值表!$F$47,COLUMN()-3>20,成本费用取值表!$G$47)*IF(基本信息!#REF!="委托运维",1,0) -> #DIV/0! | F44: =_xlfn.IFS(COLUMN()-3<=5,成本费用取值表!$C$47,COLUMN()-3<=10,成本费用取值表!$D$47,COLUMN()-3<=15,成本费用取值表!$E$47,COLUMN()-3<=20,成本费用取值表!$F$47,COLUMN()-3>20,成本费用取值表!$G$47)*IF(基本信息!#REF!="委托运维",1,0) -> #DIV/0! | G44: =_xlfn.IFS(COLUMN()-3<=5,成本费用取值表!$C$47,COLUMN()-3<=10,成本费用取值表!$D$47,COLUMN()-3<=15,成本费用取值表!$E$47,COLUMN()-3<=20,成本费用取值表!$F$47,COLUMN()-3>20,成本费用取值表!$G$47)*IF(基本信息!#REF!="委托运维",1,0) -> #DIV/0! | H44: =_xlfn.IFS(COLUMN()-3<=5,成本费用取值表!$C$47,COLUMN()-3<=10,成本费用取值表!$D$47,COLUMN()-3<=15,成本费用取值表!$E$47,COLUMN()-3<=20,成本费用取值表!$F$47,COLUMN()-3>20,成本费用取值表!$G$47)*IF(基本信息!#REF!="委托运维",1,0) -> #DIV/0! | I44: =_xlfn.IFS(COLUMN()-3<=5,成本费用取值表!$C$47,COLUMN()-3<=10,成本费用取值表!$D$47,COLUMN()-3<=15,成本费用取值表!$E$47,COLUMN()-3<=20,成本费用取值表!$F$47,COLUMN()-3>20,成本费用取值表!$G$47)*IF(基本信息!#REF!="委托运维",1,0) -> #DIV/0! | J44: =_xlfn.IFS(COLUMN()-3<=5,成本费用取值表!$C$47,COLUMN()-3<=10,成本费用取值表!$D$47,COLUMN()-3<=15,成本费用取值表!$E$47,COLUMN()-3<=20,成本费用取值表!$F$47,COLUMN()-3>20,成本费用取值表!$G$47)*IF(基本信息!#REF!="委托运维",1,0) -> #DIV/0! | K44: =_xlfn.IFS(COLUMN()-3<=5,成本费用取值表!$C$47,COLUMN()-3<=10,成本费用取值表!$D$47,COLUMN()-3<=15,成本费用取值表!$E$47,COLUMN()-3<=20,成本费用取值表!$F$47,COLUMN()-3>20,成本费用取值表!$G$47)*IF(基本信息!#REF!="委托运维",1,0) -> #DIV/0! | ... AB44: =_xlfn.IFS(COLUMN()-3<=5,成本费用取值表!$C$47,COLUMN()-3<=10,成本费用取值表!$D$47,COLUMN()-3<=15,成本费用取值表!$E$47,COLUMN()-3<=20,成本费用取值表!$F$47,COLUMN()-3>20,成本费用取值表!$G$47)*IF(基本信息!#REF!="委托运维",1,0) -> #DIV/0!
B45: 万元 | D45: =D44*基本参数!$B$6/10 -> #DIV/0! | E45: =E44*基本参数!$B$6/10 -> #DIV/0! | F45: =F44*基本参数!$B$6/10 -> #DIV/0! | G45: =G44*基本参数!$B$6/10 -> #DIV/0! | H45: =H44*基本参数!$B$6/10 -> #DIV/0! | I45: =I44*基本参数!$B$6/10 -> #DIV/0! | J45: =J44*基本参数!$B$6/10 -> #DIV/0! | K45: =K44*基本参数!$B$6/10 -> #DIV/0! | ... AB45: =AB44*基本参数!$B$6/10 -> #DIV/0!
A46: 手动输入 | B46: 万元
A47: 最终委托运维费 | B47: 万元 | D47: =IF($C$42="按比例",D45,D46)*IF(OR(基本参数!$B$2<=COLUMN()-3,COLUMN()-3<基本参数!$B$3),0,1) -> #DIV/0! | E47: =IF($C$42="按比例",E45,E46)*IF(OR(基本参数!$B$2<=COLUMN()-3,COLUMN()-3<基本参数!$B$3),0,1) -> #DIV/0! | F47: =IF($C$42="按比例",F45,F46)*IF(OR(基本参数!$B$2<=COLUMN()-3,COLUMN()-3<基本参数!$B$3),0,1) -> #DIV/0! | G47: =IF($C$42="按比例",G45,G46)*IF(OR(基本参数!$B$2<=COLUMN()-3,COLUMN()-3<基本参数!$B$3),0,1) -> #DIV/0! | H47: =IF($C$42="按比例",H45,H46)*IF(OR(基本参数!$B$2<=COLUMN()-3,COLUMN()-3<基本参数!$B$3),0,1) -> #DIV/0! | I47: =IF($C$42="按比例",I45,I46)*IF(OR(基本参数!$B$2<=COLUMN()-3,COLUMN()-3<基本参数!$B$3),0,1) -> #DIV/0! | J47: =IF($C$42="按比例",J45,J46)*IF(OR(基本参数!$B$2<=COLUMN()-3,COLUMN()-3<基本参数!$B$3),0,1) -> #DIV/0! | K47: =IF($C$42="按比例",K45,K46)*IF(OR(基本参数!$B$2<=COLUMN()-3,COLUMN()-3<基本参数!$B$3),0,1) -> #DIV/0! | ... AB47: =IF($C$42="按比例",AB45,AB46)*IF(OR(基本参数!$B$2<=COLUMN()-3,COLUMN()-3<基本参数!$B$3),0,1) -> #DIV/0!
A48: 摊销费
A49: 计算方式（选择） | C49: 自动计算
B50: 年份 | C50: 第1年 | D50: 第2年 | E50: 第3年 | F50: 第4年 | G50: 第5年 | H50: 第6年 | I50: 第7年 | J50: 第8年 | K50: 第9年 | L50: 第10年 | M50: 第11年 | N50: 第12年 | O50: 第13年 | P50: 第14年 | Q50: 第15年 | R50: 第16年 | S50: 第17年 | T50: 第18年 | U50: 第19年 | V50: 第20年 | W50: 第21年 | X50: 第22年 | Y50: 第23年 | Z50: 第24年 | AA50: 第25年 | AB50: 第26年
A51: 无形资产摊销 | B51: 年 | C51: 5
B52: 万元 | D52: =IF(COLUMN()-3<=$C$51,基本参数!$B$13/$C$51,0) -> 0 | E52: =IF(COLUMN()-3<=$C$51,基本参数!$B$13/$C$51,0) -> 0 | F52: =IF(COLUMN()-3<=$C$51,基本参数!$B$13/$C$51,0) -> 0 | G52: =IF(COLUMN()-3<=$C$51,基本参数!$B$13/$C$51,0) -> 0 | H52: =IF(COLUMN()-3<=$C$51,基本参数!$B$13/$C$51,0) -> 0 | I52: =IF(COLUMN()-3<=$C$51,基本参数!$B$13/$C$51,0) -> 0 | J52: =IF(COLUMN()-3<=$C$51,基本参数!$B$13/$C$51,0) -> 0 | K52: =IF(COLUMN()-3<=$C$51,基本参数!$B$13/$C$51,0) -> 0 | ... AB52: =IF(COLUMN()-3<=$C$51,基本参数!$B$13/$C$51,0) -> 0
A53: 其他资产摊销 | B53: 年 | C53: 5
B54: 万元 | D54: =IF(COLUMN()-3<=$C$53,基本参数!$B$14/$C$53,0) -> 0 | E54: =IF(COLUMN()-3<=$C$53,基本参数!$B$14/$C$53,0) -> 0 | F54: =IF(COLUMN()-3<=$C$53,基本参数!$B$14/$C$53,0) -> 0 | G54: =IF(COLUMN()-3<=$C$53,基本参数!$B$14/$C$53,0) -> 0 | H54: =IF(COLUMN()-3<=$C$53,基本参数!$B$14/$C$53,0) -> 0 | I54: =IF(COLUMN()-3<=$C$53,基本参数!$B$14/$C$53,0) -> 0 | J54: =IF(COLUMN()-3<=$C$53,基本参数!$B$14/$C$53,0) -> 0 | K54: =IF(COLUMN()-3<=$C$53,基本参数!$B$14/$C$53,0) -> 0 | ... AB54: =IF(COLUMN()-3<=$C$53,基本参数!$B$14/$C$53,0) -> 0
A55: 手动输入 | B55: 万元
A56: 最终摊销费 | B56: 万元 | D56: =IF($C$49="自动计算",D52+D54,D55) -> 0 | E56: =IF($C$49="自动计算",E52+E54,E55) -> 0 | F56: =IF($C$49="自动计算",F52+F54,F55) -> 0 | G56: =IF($C$49="自动计算",G52+G54,G55) -> 0 | H56: =IF($C$49="自动计算",H52+H54,H55) -> 0 | I56: =IF($C$49="自动计算",I52+I54,I55) -> 0 | J56: =IF($C$49="自动计算",J52+J54,J55) -> 0 | K56: =IF($C$49="自动计算",K52+K54,K55) -> 0 | ... AB56: =IF($C$49="自动计算",AB52+AB54,AB55) -> 0
A57: 其他费用
B58: 年份 | C58: 第1年 | D58: 第2年 | E58: 第3年 | F58: 第4年 | G58: 第5年 | H58: 第6年 | I58: 第7年 | J58: 第8年 | K58: 第9年 | L58: 第10年 | M58: 第11年 | N58: 第12年 | O58: 第13年 | P58: 第14年 | Q58: 第15年 | R58: 第16年 | S58: 第17年 | T58: 第18年 | U58: 第19年 | V58: 第20年 | W58: 第21年 | X58: 第22年 | Y58: 第23年 | Z58: 第24年 | AA58: 第25年 | AB58: 第26年
A59: 其他费用 | B59: 元/kW | D59: =IF(基本信息!#REF!="自主运维",成本费用取值表!$C$37,0) -> #REF! | E59: =D59 -> #REF! | F59: =E59 -> #REF! | G59: =F59 -> #REF! | H59: =G59 -> #REF! | I59: =H59 -> #REF! | J59: =I59 -> #REF! | K59: =J59 -> #REF! | L59: =K59 -> #REF! | ... AB59: =AA59 -> #REF!
B60: 万元 | D60: =D59*基本参数!$B$7/10 -> #REF! | E60: =E59*基本参数!$B$7/10 -> #REF! | F60: =F59*基本参数!$B$7/10 -> #REF! | G60: =G59*基本参数!$B$7/10 -> #REF! | H60: =H59*基本参数!$B$7/10 -> #REF! | I60: =I59*基本参数!$B$7/10 -> #REF! | J60: =J59*基本参数!$B$7/10 -> #REF! | K60: =K59*基本参数!$B$7/10 -> #REF! | ... AB60: =AB59*基本参数!$B$7/10 -> #REF!
A61: 其他费用1 | B61: 万元 | D61: =基本信息!D20 -> 0 | E61: =D61 -> 0 | F61: =E61 -> 0 | G61: =F61 -> 0 | H61: =G61 -> 0 | I61: =H61 -> 0 | J61: =I61 -> 0 | K61: =J61 -> 0 | L61: =K61 -> 0 | ... AB61: =AA61 -> 0
A62: 其他费用2 | B62: 万元 | D62: =基本信息!D21 -> 0 | E62: =D62 -> 0 | F62: =E62 -> 0 | G62: =F62 -> 0 | H62: =G62 -> 0 | I62: =H62 -> 0 | J62: =I62 -> 0 | K62: =J62 -> 0 | L62: =K62 -> 0 | ... AB62: =AA62 -> 0
A63: 其他费用3 | B63: 万元 | D63: =基本信息!D22 -> 0 | E63: =D63 -> 0 | F63: =E63 -> 0 | G63: =F63 -> 0 | H63: =G63 -> 0 | I63: =H63 -> 0 | J63: =I63 -> 0 | K63: =J63 -> 0 | L63: =K63 -> 0 | ... AB63: =AA63 -> 0
A64: 其他费用4 | B64: 万元 | D64: 0 | E64: =D64 -> 0 | F64: =E64 -> 0 | G64: =F64 -> 0 | H64: =G64 -> 0 | I64: =H64 -> 0 | J64: =I64 -> 0 | K64: =J64 -> 0 | L64: =K64 -> 0 | ... AB64: =AA64 -> 0
A65: 其他费用5 | B65: 万元 | D65: 0 | E65: =D65 -> 0 | F65: =E65 -> 0 | G65: =F65 -> 0 | H65: =G65 -> 0 | I65: =H65 -> 0 | J65: =I65 -> 0 | K65: =J65 -> 0 | L65: =K65 -> 0 | ... AB65: =AA65 -> 0
A66: 最终其他费用 | B66: 万元 | D66: =(D60+SUM(D61:D65))*IF(OR(基本参数!$B$2<=COLUMN()-3,COLUMN()-3<基本参数!$B$3),0,1) -> #REF! | E66: =(E60+SUM(E61:E65))*IF(OR(基本参数!$B$2<=COLUMN()-3,COLUMN()-3<基本参数!$B$3),0,1) -> #REF! | F66: =(F60+SUM(F61:F65))*IF(OR(基本参数!$B$2<=COLUMN()-3,COLUMN()-3<基本参数!$B$3),0,1) -> #REF! | G66: =(G60+SUM(G61:G65))*IF(OR(基本参数!$B$2<=COLUMN()-3,COLUMN()-3<基本参数!$B$3),0,1) -> #REF! | H66: =(H60+SUM(H61:H65))*IF(OR(基本参数!$B$2<=COLUMN()-3,COLUMN()-3<基本参数!$B$3),0,1) -> #REF! | I66: =(I60+SUM(I61:I65))*IF(OR(基本参数!$B$2<=COLUMN()-3,COLUMN()-3<基本参数!$B$3),0,1) -> #REF! | J66: =(J60+SUM(J61:J65))*IF(OR(基本参数!$B$2<=COLUMN()-3,COLUMN()-3<基本参数!$B$3),0,1) -> #REF! | K66: =(K60+SUM(K61:K65))*IF(OR(基本参数!$B$2<=COLUMN()-3,COLUMN()-3<基本参数!$B$3),0,1) -> #REF! | ... AB66: =(AB60+SUM(AB61:AB65))*IF(OR(基本参数!$B$2<=COLUMN()-3,COLUMN()-3<基本参数!$B$3),0,1) -> #REF!
A67: 进项税
B68: 年份 | C68: 第1年 | D68: 第2年 | E68: 第3年 | F68: 第4年 | G68: 第5年 | H68: 第6年 | I68: 第7年 | J68: 第8年 | K68: 第9年 | L68: 第10年 | M68: 第11年 | N68: 第12年 | O68: 第13年 | P68: 第14年 | Q68: 第15年 | R68: 第16年 | S68: 第17年 | T68: 第18年 | U68: 第19年 | V68: 第20年 | W68: 第21年 | X68: 第22年 | Y68: 第23年 | Z68: 第24年 | AA68: 第25年 | AB68: 第26年
A69: 进项税1 | B69: 万元 | D69: 0 | E69: =D69 -> 0 | F69: =E69 -> 0 | G69: =F69 -> 0 | H69: =G69 -> 0 | I69: =H69 -> 0 | J69: =I69 -> 0 | K69: =J69 -> 0 | L69: =K69 -> 0 | ... AB69: =AA69 -> 0
A70: 进项税2 | B70: 万元 | D70: 0 | E70: =D70 -> 0 | F70: =E70 -> 0 | G70: =F70 -> 0 | H70: =G70 -> 0 | I70: =H70 -> 0 | J70: =I70 -> 0 | K70: =J70 -> 0 | L70: =K70 -> 0 | ... AB70: =AA70 -> 0
A71: 进项税3 | B71: 万元 | D71: 0 | E71: =D71 -> 0 | F71: =E71 -> 0 | G71: =F71 -> 0 | H71: =G71 -> 0 | I71: =H71 -> 0 | J71: =I71 -> 0 | K71: =J71 -> 0 | L71: =K71 -> 0 | ... AB71: =AA71 -> 0
A72: 进项税4 | B72: 万元 | D72: 0 | E72: =D72 -> 0 | F72: =E72 -> 0 | G72: =F72 -> 0 | H72: =G72 -> 0 | I72: =H72 -> 0 | J72: =I72 -> 0 | K72: =J72 -> 0 | L72: =K72 -> 0 | ... AB72: =AA72 -> 0
A73: 进项税5 | B73: 万元 | D73: 0 | E73: =D73 -> 0 | F73: =E73 -> 0 | G73: =F73 -> 0 | H73: =G73 -> 0 | I73: =H73 -> 0 | J73: =I73 -> 0 | K73: =J73 -> 0 | L73: =K73 -> 0 | ... AB73: =AA73 -> 0
A74: 进项税合计 | B74: 万元 | D74: =SUM(D69:D73)*IF(OR(基本参数!$B$2<=COLUMN()-3,COLUMN()-3<基本参数!$B$3),0,1) -> 0 | E74: =SUM(E69:E73)*IF(OR(基本参数!$B$2<=COLUMN()-3,COLUMN()-3<基本参数!$B$3),0,1) -> 0 | F74: =SUM(F69:F73)*IF(OR(基本参数!$B$2<=COLUMN()-3,COLUMN()-3<基本参数!$B$3),0,1) -> 0 | G74: =SUM(G69:G73)*IF(OR(基本参数!$B$2<=COLUMN()-3,COLUMN()-3<基本参数!$B$3),0,1) -> 0 | H74: =SUM(H69:H73)*IF(OR(基本参数!$B$2<=COLUMN()-3,COLUMN()-3<基本参数!$B$3),0,1) -> 0 | I74: =SUM(I69:I73)*IF(OR(基本参数!$B$2<=COLUMN()-3,COLUMN()-3<基本参数!$B$3),0,1) -> 0 | J74: =SUM(J69:J73)*IF(OR(基本参数!$B$2<=COLUMN()-3,COLUMN()-3<基本参数!$B$3),0,1) -> 0 | K74: =SUM(K69:K73)*IF(OR(基本参数!$B$2<=COLUMN()-3,COLUMN()-3<基本参数!$B$3),0,1) -> 0 | ... AB74: =SUM(AB69:AB73)*IF(OR(基本参数!$B$2<=COLUMN()-3,COLUMN()-3<基本参数!$B$3),0,1) -> 0
A75: 长期借款利息（辅助行）
B76: 年份 | C76: 第1年 | D76: 第2年 | E76: 第3年 | F76: 第4年 | G76: 第5年 | H76: 第6年 | I76: 第7年 | J76: 第8年 | K76: 第9年 | L76: 第10年 | M76: 第11年 | N76: 第12年 | O76: 第13年 | P76: 第14年 | Q76: 第15年 | R76: 第16年 | S76: 第17年 | T76: 第18年 | U76: 第19年 | V76: 第20年 | W76: 第21年 | X76: 第22年 | Y76: 第23年 | Z76: 第24年 | AA76: 第25年 | AB76: 第26年
A77: 借款额 | B77: 万元 | C77: =SUM(投资计划与资金筹措表!D14:E14) -> 0
A78: 等额还本利息照付：年初借款余额 | B78: 万元 | D78: =C77 -> 0 | E78: =D78-D79 -> 0 | F78: =E78-E79 -> 0 | G78: =F78-F79 -> 0 | H78: =G78-G79 -> 0 | I78: =H78-H79 -> 0 | J78: =I78-I79 -> 0 | K78: =J78-J79 -> 0 | L78: =K78-K79 -> 0 | ... AB78: =AA78-AA79 -> 0
A79: 本年还本 | B79: 万元 | D79: =IF(OR(COLUMN()-2<=基本参数!$B$3,COLUMN()-2>基本参数!$B$33+基本参数!$B$3),0,$C$77/基本参数!$B$33) -> 0 | E79: =IF(OR(COLUMN()-2<=基本参数!$B$3,COLUMN()-2>基本参数!$B$33+基本参数!$B$3),0,$C$77/基本参数!$B$33) -> 0 | F79: =IF(OR(COLUMN()-2<=基本参数!$B$3,COLUMN()-2>基本参数!$B$33+基本参数!$B$3),0,$C$77/基本参数!$B$33) -> 0 | G79: =IF(OR(COLUMN()-2<=基本参数!$B$3,COLUMN()-2>基本参数!$B$33+基本参数!$B$3),0,$C$77/基本参数!$B$33) -> 0 | H79: =IF(OR(COLUMN()-2<=基本参数!$B$3,COLUMN()-2>基本参数!$B$33+基本参数!$B$3),0,$C$77/基本参数!$B$33) -> 0 | I79: =IF(OR(COLUMN()-2<=基本参数!$B$3,COLUMN()-2>基本参数!$B$33+基本参数!$B$3),0,$C$77/基本参数!$B$33) -> 0 | J79: =IF(OR(COLUMN()-2<=基本参数!$B$3,COLUMN()-2>基本参数!$B$33+基本参数!$B$3),0,$C$77/基本参数!$B$33) -> 0 | K79: =IF(OR(COLUMN()-2<=基本参数!$B$3,COLUMN()-2>基本参数!$B$33+基本参数!$B$3),0,$C$77/基本参数!$B$33) -> 0 | ... AB79: =IF(OR(COLUMN()-2<=基本参数!$B$3,COLUMN()-2>基本参数!$B$33+基本参数!$B$3),0,$C$77/基本参数!$B$33) -> 0
A80: 利息 | B80: 万元 | D80: =IF(COLUMN()-2>基本参数!$B$3,D78*(基本参数!$B$36/100),0) -> 0 | E80: =IF(COLUMN()-2>基本参数!$B$3,E78*(基本参数!$B$36/100),0) -> 0 | F80: =IF(COLUMN()-2>基本参数!$B$3,F78*(基本参数!$B$36/100),0) -> 0 | G80: =IF(COLUMN()-2>基本参数!$B$3,G78*(基本参数!$B$36/100),0) -> 0 | H80: =IF(COLUMN()-2>基本参数!$B$3,H78*(基本参数!$B$36/100),0) -> 0 | I80: =IF(COLUMN()-2>基本参数!$B$3,I78*(基本参数!$B$36/100),0) -> 0 | J80: =IF(COLUMN()-2>基本参数!$B$3,J78*(基本参数!$B$36/100),0) -> 0 | K80: =IF(COLUMN()-2>基本参数!$B$3,K78*(基本参数!$B$36/100),0) -> 0 | ... AB80: =IF(COLUMN()-2>基本参数!$B$3,AB78*(基本参数!$B$36/100),0) -> 0
A81: 等额本息：每年还本付息总额 | B81: 万元 | D81: =IF(AND(COLUMN()-2>基本参数!$B$3,COLUMN()-2<=基本参数!$B$3+基本参数!$B$33),$C$77*(基本参数!$B$36%*(1+基本参数!$B$36%)^(基本参数!$B$33)/((1+基本参数!$B$36%)^(基本参数!$B$33)-1)),0) -> 0 | E81: =IF(AND(COLUMN()-2>基本参数!$B$3,COLUMN()-2<=基本参数!$B$3+基本参数!$B$33),$C$77*(基本参数!$B$36%*(1+基本参数!$B$36%)^(基本参数!$B$33)/((1+基本参数!$B$36%)^(基本参数!$B$33)-1)),0) -> 0 | F81: =IF(AND(COLUMN()-2>基本参数!$B$3,COLUMN()-2<=基本参数!$B$3+基本参数!$B$33),$C$77*(基本参数!$B$36%*(1+基本参数!$B$36%)^(基本参数!$B$33)/((1+基本参数!$B$36%)^(基本参数!$B$33)-1)),0) -> 0 | G81: =IF(AND(COLUMN()-2>基本参数!$B$3,COLUMN()-2<=基本参数!$B$3+基本参数!$B$33),$C$77*(基本参数!$B$36%*(1+基本参数!$B$36%)^(基本参数!$B$33)/((1+基本参数!$B$36%)^(基本参数!$B$33)-1)),0) -> 0 | H81: =IF(AND(COLUMN()-2>基本参数!$B$3,COLUMN()-2<=基本参数!$B$3+基本参数!$B$33),$C$77*(基本参数!$B$36%*(1+基本参数!$B$36%)^(基本参数!$B$33)/((1+基本参数!$B$36%)^(基本参数!$B$33)-1)),0) -> 0 | I81: =IF(AND(COLUMN()-2>基本参数!$B$3,COLUMN()-2<=基本参数!$B$3+基本参数!$B$33),$C$77*(基本参数!$B$36%*(1+基本参数!$B$36%)^(基本参数!$B$33)/((1+基本参数!$B$36%)^(基本参数!$B$33)-1)),0) -> 0 | J81: =IF(AND(COLUMN()-2>基本参数!$B$3,COLUMN()-2<=基本参数!$B$3+基本参数!$B$33),$C$77*(基本参数!$B$36%*(1+基本参数!$B$36%)^(基本参数!$B$33)/((1+基本参数!$B$36%)^(基本参数!$B$33)-1)),0) -> 0 | K81: =IF(AND(COLUMN()-2>基本参数!$B$3,COLUMN()-2<=基本参数!$B$3+基本参数!$B$33),$C$77*(基本参数!$B$36%*(1+基本参数!$B$36%)^(基本参数!$B$33)/((1+基本参数!$B$36%)^(基本参数!$B$33)-1)),0) -> 0 | ... AB81: =IF(AND(COLUMN()-2>基本参数!$B$3,COLUMN()-2<=基本参数!$B$3+基本参数!$B$33),$C$77*(基本参数!$B$36%*(1+基本参数!$B$36%)^(基本参数!$B$33)/((1+基本参数!$B$36%)^(基本参数!$B$33)-1)),0) -> 0
A82: 年初借款余额 | B82: 万元 | D82: =C77 -> 0 | E82: =D82-D83 -> 0 | F82: =E82-E83 -> 0 | G82: =F82-F83 -> 0 | H82: =G82-G83 -> 0 | I82: =H82-H83 -> 0 | J82: =I82-I83 -> 0 | K82: =J82-J83 -> 0 | L82: =K82-K83 -> 0 | ... AB82: =AA82-AA83 -> 0
A83: 本年还本 | B83: 万元 | D83: =D81-D84 -> 0 | E83: =E81-E84 -> 0 | F83: =F81-F84 -> 0 | G83: =G81-G84 -> 0 | H83: =H81-H84 -> 0 | I83: =I81-I84 -> 0 | J83: =J81-J84 -> 0 | K83: =K81-K84 -> 0 | ... AB83: =AB81-AB84 -> 0
A84: 利息 | B84: 万元 | D84: =IF(COLUMN()-2>基本参数!$B$3,D82*基本参数!$B$36%,0) -> 0 | E84: =IF(COLUMN()-2>基本参数!$B$3,E82*基本参数!$B$36%,0) -> 0 | F84: =IF(COLUMN()-2>基本参数!$B$3,F82*基本参数!$B$36%,0) -> 0 | G84: =IF(COLUMN()-2>基本参数!$B$3,G82*基本参数!$B$36%,0) -> 0 | H84: =IF(COLUMN()-2>基本参数!$B$3,H82*基本参数!$B$36%,0) -> 0 | I84: =IF(COLUMN()-2>基本参数!$B$3,I82*基本参数!$B$36%,0) -> 0 | J84: =IF(COLUMN()-2>基本参数!$B$3,J82*基本参数!$B$36%,0) -> 0 | K84: =IF(COLUMN()-2>基本参数!$B$3,K82*基本参数!$B$36%,0) -> 0 | ... AB84: =IF(COLUMN()-2>基本参数!$B$3,AB82*基本参数!$B$36%,0) -> 0
A85: 约定还款：年初借款余额 | B85: 万元 | D85: =C77 -> 0 | E85: =D85-D86 -> 0 | F85: =E85-E86 -> 0 | G85: =F85-F86 -> 0 | H85: =G85-G86 -> 0 | I85: =H85-H86 -> 0 | J85: =I85-I86 -> 0 | K85: =J85-J86 -> 0 | L85: =K85-K86 -> 0 | ... AB85: =AA85-AA86 -> 0
A86: 本年还本 | B86: 万元 | D86: =基本参数!C38 -> 0 | E86: =基本参数!D38 -> 0 | F86: =基本参数!E38 -> 0 | G86: =基本参数!F38 -> 0 | H86: =基本参数!G38 -> 0 | I86: =基本参数!H38 -> 0 | J86: =基本参数!I38 -> 0 | K86: =基本参数!J38 -> 0 | ... AB86: =基本参数!AA38 -> 0
A87: 利息 | B87: 万元 | D87: =IF(COLUMN()-2>基本参数!$B$3,D85*基本参数!$B$36%,0) -> 0 | E87: =IF(COLUMN()-2>基本参数!$B$3,E85*基本参数!$B$36%,0) -> 0 | F87: =IF(COLUMN()-2>基本参数!$B$3,F85*基本参数!$B$36%,0) -> 0 | G87: =IF(COLUMN()-2>基本参数!$B$3,G85*基本参数!$B$36%,0) -> 0 | H87: =IF(COLUMN()-2>基本参数!$B$3,H85*基本参数!$B$36%,0) -> 0 | I87: =IF(COLUMN()-2>基本参数!$B$3,I85*基本参数!$B$36%,0) -> 0 | J87: =IF(COLUMN()-2>基本参数!$B$3,J85*基本参数!$B$36%,0) -> 0 | K87: =IF(COLUMN()-2>基本参数!$B$3,K85*基本参数!$B$36%,0) -> 0 | ... AB87: =IF(COLUMN()-2>基本参数!$B$3,AB85*基本参数!$B$36%,0) -> 0
A88: 在建工程 | C88: =投资计划与资金筹措表!D6+投资计划与资金筹措表!D7 -> 0
A89: 固定资产原值 | C89: =C88-基本参数!B13-基本参数!B14-基本参数!B15 -> 0 | D89: =IF(COLUMN()-2<=基本参数!$B$2,C89,0) -> 0 | E89: =IF(COLUMN()-2<=基本参数!$B$2,D89,0) -> 0 | F89: =IF(COLUMN()-2<=基本参数!$B$2,E89,0) -> 0 | G89: =IF(COLUMN()-2<=基本参数!$B$2,F89,0) -> 0 | H89: =IF(COLUMN()-2<=基本参数!$B$2,G89,0) -> 0 | I89: =IF(COLUMN()-2<=基本参数!$B$2,H89,0) -> 0 | J89: =IF(COLUMN()-2<=基本参数!$B$2,I89,0) -> 0 | K89: =IF(COLUMN()-2<=基本参数!$B$2,J89,0) -> 0 | ... AB89: =IF(COLUMN()-2<=基本参数!$B$2,AA89,0) -> 0
A90: 固定资产净值 | B90: 万元 | D90: =IF(COLUMN()-2<=基本参数!$B$2,C89-SUM($C$8:D8),0) -> 0 | E90: =IF(COLUMN()-2<=基本参数!$B$2,D89-SUM($C$8:E8),0) -> 0 | F90: =IF(COLUMN()-2<=基本参数!$B$2,E89-SUM($C$8:F8),0) -> 0 | G90: =IF(COLUMN()-2<=基本参数!$B$2,F89-SUM($C$8:G8),0) -> 0 | H90: =IF(COLUMN()-2<=基本参数!$B$2,G89-SUM($C$8:H8),0) -> 0 | I90: =IF(COLUMN()-2<=基本参数!$B$2,H89-SUM($C$8:I8),0) -> 0 | J90: =IF(COLUMN()-2<=基本参数!$B$2,I89-SUM($C$8:J8),0) -> 0 | K90: =IF(COLUMN()-2<=基本参数!$B$2,J89-SUM($C$8:K8),0) -> 0 | ... AB90: =IF(COLUMN()-2<=基本参数!$B$2,AA89-SUM($C$8:AB8),0) -> 0

Sheet 收入和税金
A1: 发电量
A2: 发电量计算方式 | C2: 自动计算
A3: 首年无衰减无弃电利用小时 | B3: 小时 | C3: =基本信息!D9 -> 0
B4: 年份 | C4: 第1年 | D4: 第2年 | E4: 第3年 | F4: 第4年 | G4: 第5年 | H4: 第6年 | I4: 第7年 | J4: 第8年 | K4: 第9年 | L4: 第10年 | M4: 第11年 | N4: 第12年 | O4: 第13年 | P4: 第14年 | Q4: 第15年 | R4: 第16年 | S4: 第17年 | T4: 第18年 | U4: 第19年 | V4: 第20年 | W4: 第21年 | X4: 第22年 | Y4: 第23年 | Z4: 第24年 | AA4: 第25年 | AB4: 第26年
A5: 发电量系数计算方式 | C5: =基本信息!D10 -> 0 | D5: =IF($C$5="P型单玻",D64,IF($C$5="P型双玻",D65,IF($C$5="N型单玻",D66,IF($C$5="N型双玻",D67,IF($C$5="多晶单玻",D68,IF($C$5="多晶双玻",D69,D6))))))*IF(COLUMN()-2>基本参数!$B$2,0,1) -> 98 | E5: =IF($C$5="P型单玻",E64,IF($C$5="P型双玻",E65,IF($C$5="N型单玻",E66,IF($C$5="N型双玻",E67,IF($C$5="多晶单玻",E68,IF($C$5="多晶双玻",E69,E6))))))*IF(COLUMN()-2>基本参数!$B$2,0,1) -> 97.45 | F5: =IF($C$5="P型单玻",F64,IF($C$5="P型双玻",F65,IF($C$5="N型单玻",F66,IF($C$5="N型双玻",F67,IF($C$5="多晶单玻",F68,IF($C$5="多晶双玻",F69,F6))))))*IF(COLUMN()-2>基本参数!$B$2,0,1) -> 96.9 | G5: =IF($C$5="P型单玻",G64,IF($C$5="P型双玻",G65,IF($C$5="N型单玻",G66,IF($C$5="N型双玻",G67,IF($C$5="多晶单玻",G68,IF($C$5="多晶双玻",G69,G6))))))*IF(COLUMN()-2>基本参数!$B$2,0,1) -> 96.35 | H5: =IF($C$5="P型单玻",H64,IF($C$5="P型双玻",H65,IF($C$5="N型单玻",H66,IF($C$5="N型双玻",H67,IF($C$5="多晶单玻",H68,IF($C$5="多晶双玻",H69,H6))))))*IF(COLUMN()-2>基本参数!$B$2,0,1) -> 95.8 | I5: =IF($C$5="P型单玻",I64,IF($C$5="P型双玻",I65,IF($C$5="N型单玻",I66,IF($C$5="N型双玻",I67,IF($C$5="多晶单玻",I68,IF($C$5="多晶双玻",I69,I6))))))*IF(COLUMN()-2>基本参数!$B$2,0,1) -> 95.25 | J5: =IF($C$5="P型单玻",J64,IF($C$5="P型双玻",J65,IF($C$5="N型单玻",J66,IF($C$5="N型双玻",J67,IF($C$5="多晶单玻",J68,IF($C$5="多晶双玻",J69,J6))))))*IF(COLUMN()-2>基本参数!$B$2,0,1) -> 94.7 | K5: =IF($C$5="P型单玻",K64,IF($C$5="P型双玻",K65,IF($C$5="N型单玻",K66,IF($C$5="N型双玻",K67,IF($C$5="多晶单玻",K68,IF($C$5="多晶双玻",K69,K6))))))*IF(COLUMN()-2>基本参数!$B$2,0,1) -> 94.15 | ... AB5: =IF($C$5="P型单玻",AB64,IF($C$5="P型双玻",AB65,IF($C$5="N型单玻",AB66,IF($C$5="N型双玻",AB67,IF($C$5="多晶单玻",AB68,IF($C$5="多晶双玻",AB69,AB6))))))*IF(COLUMN()-2>基本参数!$B$2,0,1) -> 84.8
A6: 手动输入发电量系数 | B6: % | D6: 98 | E6: 97.45 | F6: 96.9 | G6: 96.35 | H6: 95.8 | I6: 95.25 | J6: 94.7 | K6: 94.15 | L6: 93.6 | M6: 93.05 | N6: 92.5 | O6: 91.95 | P6: 91.4 | Q6: 90.85 | R6: 90.3 | S6: 89.75 | T6: 89.2 | U6: 88.65 | V6: 88.1 | W6: 87.55 | X6: 87 | Y6: 86.45 | Z6: 85.9 | AA6: 85.35 | AB6: 84.8
A7: 弃电率计算方式 | C7: =基本信息!D12 -> 0 | D7: =IF($C$7="手动输入",D8,VLOOKUP(地区辅助页!$E$1,IF($C$7="标准1",电价电量取值表!$A:$O,电价电量取值表!$Q:$AE),IF(电价电量计算表!D15>2030,15,电价电量计算表!D15-2025+10),FALSE))*IF(COLUMN()-2>基本参数!$B$2,0,100) -> #VALUE! | E7: =IF($C$7="手动输入",E8,VLOOKUP(地区辅助页!$E$1,IF($C$7="标准1",电价电量取值表!$A:$O,电价电量取值表!$Q:$AE),IF(电价电量计算表!E15>2030,15,电价电量计算表!E15-2025+10),FALSE))*IF(COLUMN()-2>基本参数!$B$2,0,100) -> #VALUE! | F7: =IF($C$7="手动输入",F8,VLOOKUP(地区辅助页!$E$1,IF($C$7="标准1",电价电量取值表!$A:$O,电价电量取值表!$Q:$AE),IF(电价电量计算表!F15>2030,15,电价电量计算表!F15-2025+10),FALSE))*IF(COLUMN()-2>基本参数!$B$2,0,100) -> #VALUE! | G7: =IF($C$7="手动输入",G8,VLOOKUP(地区辅助页!$E$1,IF($C$7="标准1",电价电量取值表!$A:$O,电价电量取值表!$Q:$AE),IF(电价电量计算表!G15>2030,15,电价电量计算表!G15-2025+10),FALSE))*IF(COLUMN()-2>基本参数!$B$2,0,100) -> #VALUE! | H7: =IF($C$7="手动输入",H8,VLOOKUP(地区辅助页!$E$1,IF($C$7="标准1",电价电量取值表!$A:$O,电价电量取值表!$Q:$AE),IF(电价电量计算表!H15>2030,15,电价电量计算表!H15-2025+10),FALSE))*IF(COLUMN()-2>基本参数!$B$2,0,100) -> #VALUE! | I7: =IF($C$7="手动输入",I8,VLOOKUP(地区辅助页!$E$1,IF($C$7="标准1",电价电量取值表!$A:$O,电价电量取值表!$Q:$AE),IF(电价电量计算表!I15>2030,15,电价电量计算表!I15-2025+10),FALSE))*IF(COLUMN()-2>基本参数!$B$2,0,100) -> #VALUE! | J7: =IF($C$7="手动输入",J8,VLOOKUP(地区辅助页!$E$1,IF($C$7="标准1",电价电量取值表!$A:$O,电价电量取值表!$Q:$AE),IF(电价电量计算表!J15>2030,15,电价电量计算表!J15-2025+10),FALSE))*IF(COLUMN()-2>基本参数!$B$2,0,100) -> #VALUE! | K7: =IF($C$7="手动输入",K8,VLOOKUP(地区辅助页!$E$1,IF($C$7="标准1",电价电量取值表!$A:$O,电价电量取值表!$Q:$AE),IF(电价电量计算表!K15>2030,15,电价电量计算表!K15-2025+10),FALSE))*IF(COLUMN()-2>基本参数!$B$2,0,100) -> #VALUE! | ... AB7: =IF($C$7="手动输入",AB8,VLOOKUP(地区辅助页!$E$1,IF($C$7="标准1",电价电量取值表!$A:$O,电价电量取值表!$Q:$AE),IF(电价电量计算表!AB15>2030,15,电价电量计算表!AB15-2025+10),FALSE))*IF(COLUMN()-2>基本参数!$B$2,0,100) -> #VALUE!
A8: 手动输入弃电率 | B8: %
A9: 手动输入上网电量 | B9: MWh | D9: 0 | E9: =D9 -> 0 | F9: =E9 -> 0 | G9: =F9 -> 0 | H9: =G9 -> 0 | I9: =H9 -> 0 | J9: =I9 -> 0 | K9: =J9 -> 0 | L9: =K9 -> 0 | ... AB9: =AA9 -> 0
A10: 最终上网电量 | B10: MWh | D10: =IF($C$2="手动输入",D9,$C$3*IF($C$5="手动输入",D6,D5)/100*IF($C$7="手动输入",100-D8,100-D7)/100*基本参数!$B$7) -> #VALUE! | E10: =IF($C$2="手动输入",E9,$C$3*IF($C$5="手动输入",E6,E5)/100*IF($C$7="手动输入",100-E8,100-E7)/100*基本参数!$B$7) -> #VALUE! | F10: =IF($C$2="手动输入",F9,$C$3*IF($C$5="手动输入",F6,F5)/100*IF($C$7="手动输入",100-F8,100-F7)/100*基本参数!$B$7) -> #VALUE! | G10: =IF($C$2="手动输入",G9,$C$3*IF($C$5="手动输入",G6,G5)/100*IF($C$7="手动输入",100-G8,100-G7)/100*基本参数!$B$7) -> #VALUE! | H10: =IF($C$2="手动输入",H9,$C$3*IF($C$5="手动输入",H6,H5)/100*IF($C$7="手动输入",100-H8,100-H7)/100*基本参数!$B$7) -> #VALUE! | I10: =IF($C$2="手动输入",I9,$C$3*IF($C$5="手动输入",I6,I5)/100*IF($C$7="手动输入",100-I8,100-I7)/100*基本参数!$B$7) -> #VALUE! | J10: =IF($C$2="手动输入",J9,$C$3*IF($C$5="手动输入",J6,J5)/100*IF($C$7="手动输入",100-J8,100-J7)/100*基本参数!$B$7) -> #VALUE! | K10: =IF($C$2="手动输入",K9,$C$3*IF($C$5="手动输入",K6,K5)/100*IF($C$7="手动输入",100-K8,100-K7)/100*基本参数!$B$7) -> #VALUE! | ... AB10: =IF($C$2="手动输入",AB9,$C$3*IF($C$5="手动输入",AB6,AB5)/100*IF($C$7="手动输入",100-AB8,100-AB7)/100*基本参数!$B$7) -> #VALUE!
A11: 应付利润比例
A12: 应付利润比例 | B12: % | C12: 100
A13: 增值税
A14: 增值税政策 | B14: 即征即退50% | C14: 否
B15: 年份 | C15: 第1年 | D15: 第2年 | E15: 第3年 | F15: 第4年 | G15: 第5年 | H15: 第6年 | I15: 第7年 | J15: 第8年 | K15: 第9年 | L15: 第10年 | M15: 第11年 | N15: 第12年 | O15: 第13年 | P15: 第14年 | Q15: 第15年 | R15: 第16年 | S15: 第17年 | T15: 第18年 | U15: 第19年 | V15: 第20年 | W15: 第21年 | X15: 第22年 | Y15: 第23年 | Z15: 第24年 | AA15: 第25年 | AB15: 第26年
A16: 最终税率 | B16: % | D16: 13 | E16: =D16 -> 13 | F16: =E16 -> 13 | G16: =F16 -> 13 | H16: =G16 -> 13 | I16: =H16 -> 13 | J16: =I16 -> 13 | K16: =J16 -> 13 | L16: =K16 -> 13 | ... AB16: =AA16 -> 13
A17: 企业所得税
A18: 计算方式（选择） | C18: 自动计算
A19: 企业所得税政策 | B19: 西部大开发 | C19: =IF(_xlfn.XLOOKUP(基本信息!D11,地区辅助页!B:B,地区辅助页!A:A,"",0)>20,"是","否") -> 否
B20: 年份 | C20: 第1年 | D20: 第2年 | E20: 第3年 | F20: 第4年 | G20: 第5年 | H20: 第6年 | I20: 第7年 | J20: 第8年 | K20: 第9年 | L20: 第10年 | M20: 第11年 | N20: 第12年 | O20: 第13年 | P20: 第14年 | Q20: 第15年 | R20: 第16年 | S20: 第17年 | T20: 第18年 | U20: 第19年 | V20: 第20年 | W20: 第21年 | X20: 第22年 | Y20: 第23年 | Z20: 第24年 | AA20: 第25年 | AB20: 第26年
A21: 自动计算 | B21: % | D21: =IF($C$19="是",IF(基本参数!$B$8+COLUMN()-3<=2030,15,25),25)*0 -> 0 | E21: =IF($C$19="是",IF(基本参数!$B$8+COLUMN()-3<=2030,15,25),25)*0 -> 0 | F21: =IF($C$19="是",IF(基本参数!$B$8+COLUMN()-3<=2030,15,25),25)*0 -> 0 | G21: =IF($C$19="是",IF(基本参数!$B$8+COLUMN()-3<=2030,15,25),25)*0.5 -> 12.5 | H21: =IF($C$19="是",IF(基本参数!$B$8+COLUMN()-3<=2030,15,25),25)*0.5 -> 12.5 | I21: =IF($C$19="是",IF(基本参数!$B$8+COLUMN()-3<=2030,15,25),25)*0.5 -> 12.5 | J21: =IF($C$19="是",IF(基本参数!$B$8+COLUMN()-3<=2030,15,25),25) -> 25 | K21: =IF($C$19="是",IF(基本参数!$B$8+COLUMN()-3<=2030,15,25),25) -> 25 | L21: =IF($C$19="是",IF(基本参数!$B$8+COLUMN()-3<=2030,15,25),25) -> 25 | M21: =IF($C$19="是",IF(基本参数!$B$8+COLUMN()-3<=2030,15,25),25) -> 25 | N21: =IF($C$19="是",IF(基本参数!$B$8+COLUMN()-3<=2030,15,25),25) -> 25 | O21: =IF($C$19="是",IF(基本参数!$B$8+COLUMN()-3<=2030,15,25),25) -> 25 | P21: =IF($C$19="是",IF(基本参数!$B$8+COLUMN()-3<=2030,15,25),25) -> 25 | Q21: =IF($C$19="是",IF(基本参数!$B$8+COLUMN()-3<=2030,15,25),25) -> 25 | ... AB21: =IF($C$19="是",IF(基本参数!$B$8+COLUMN()-3<=2030,15,25),25) -> 25
A22: 手动输入 | B22: % | D22: 0 | E22: 0 | F22: 0 | G22: 12.5 | H22: 12.5 | I22: 12.5 | J22: 25 | K22: 25 | L22: 25 | M22: 25 | N22: 25 | O22: 25 | P22: 25 | Q22: 25 | R22: 25 | S22: 25 | T22: 25 | U22: 25 | V22: 25 | W22: 25 | X22: 25 | Y22: 25 | Z22: 25 | AA22: 25 | AB22: 25
A23: 最终税率 | B23: % | D23: =IF($C$18="自动计算",D21,D22) -> 0 | E23: =IF($C$18="自动计算",E21,E22) -> 0 | F23: =IF($C$18="自动计算",F21,F22) -> 0 | G23: =IF($C$18="自动计算",G21,G22) -> 12.5 | H23: =IF($C$18="自动计算",H21,H22) -> 12.5 | I23: =IF($C$18="自动计算",I21,I22) -> 12.5 | J23: =IF($C$18="自动计算",J21,J22) -> 25 | K23: =IF($C$18="自动计算",K21,K22) -> 25 | ... AB23: =IF($C$18="自动计算",AB21,AB22) -> 25
A24: 城市维护建设税
B25: 年份 | C25: 第1年 | D25: 第2年 | E25: 第3年 | F25: 第4年 | G25: 第5年 | H25: 第6年 | I25: 第7年 | J25: 第8年 | K25: 第9年 | L25: 第10年 | M25: 第11年 | N25: 第12年 | O25: 第13年 | P25: 第14年 | Q25: 第15年 | R25: 第16年 | S25: 第17年 | T25: 第18年 | U25: 第19年 | V25: 第20年 | W25: 第21年 | X25: 第22年 | Y25: 第23年 | Z25: 第24年 | AA25: 第25年 | AB25: 第26年
A26: 最终税率 | B26: % | D26: 5 | E26: =D26 -> 5 | F26: =E26 -> 5 | G26: =F26 -> 5 | H26: =G26 -> 5 | I26: =H26 -> 5 | J26: =I26 -> 5 | K26: =J26 -> 5 | L26: =K26 -> 5 | ... AB26: =AA26 -> 5
A27: 教育费附加
B28: 年份 | C28: 第1年 | D28: 第2年 | E28: 第3年 | F28: 第4年 | G28: 第5年 | H28: 第6年 | I28: 第7年 | J28: 第8年 | K28: 第9年 | L28: 第10年 | M28: 第11年 | N28: 第12年 | O28: 第13年 | P28: 第14年 | Q28: 第15年 | R28: 第16年 | S28: 第17年 | T28: 第18年 | U28: 第19年 | V28: 第20年 | W28: 第21年 | X28: 第22年 | Y28: 第23年 | Z28: 第24年 | AA28: 第25年 | AB28: 第26年
A29: 最终税率 | B29: % | D29: 5 | E29: =D29 -> 5 | F29: =E29 -> 5 | G29: =F29 -> 5 | H29: =G29 -> 5 | I29: =H29 -> 5 | J29: =I29 -> 5 | K29: =J29 -> 5 | L29: =K29 -> 5 | ... AB29: =AA29 -> 5
A30: 法定盈余公积金比例
B31: 年份 | C31: 第1年 | D31: 第2年 | E31: 第3年 | F31: 第4年 | G31: 第5年 | H31: 第6年 | I31: 第7年 | J31: 第8年 | K31: 第9年 | L31: 第10年 | M31: 第11年 | N31: 第12年 | O31: 第13年 | P31: 第14年 | Q31: 第15年 | R31: 第16年 | S31: 第17年 | T31: 第18年 | U31: 第19年 | V31: 第20年 | W31: 第21年 | X31: 第22年 | Y31: 第23年 | Z31: 第24年 | AA31: 第25年 | AB31: 第26年
A32: 最终比例 | B32: % | D32: 10 | E32: =D32 -> 10 | F32: =E32 -> 10 | G32: =F32 -> 10 | H32: =G32 -> 10 | I32: =H32 -> 10 | J32: =I32 -> 10 | K32: =J32 -> 10 | L32: =K32 -> 10 | ... AB32: =AA32 -> 10
A33: 任意盈余公积金比例
B34: 年份 | C34: 第1年 | D34: 第2年 | E34: 第3年 | F34: 第4年 | G34: 第5年 | H34: 第6年 | I34: 第7年 | J34: 第8年 | K34: 第9年 | L34: 第10年 | M34: 第11年 | N34: 第12年 | O34: 第13年 | P34: 第14年 | Q34: 第15年 | R34: 第16年 | S34: 第17年 | T34: 第18年 | U34: 第19年 | V34: 第20年 | W34: 第21年 | X34: 第22年 | Y34: 第23年 | Z34: 第24年 | AA34: 第25年 | AB34: 第26年
A35: 最终比例 | B35: % | D35: 0 | E35: =D35 -> 0 | F35: =E35 -> 0 | G35: =F35 -> 0 | H35: =G35 -> 0 | I35: =H35 -> 0 | J35: =I35 -> 0 | K35: =J35 -> 0 | L35: =K35 -> 0 | ... AB35: =AA35 -> 0
A36: 其他收入（应交所得税）
B37: 年份 | C37: 第1年 | D37: 第2年 | E37: 第3年 | F37: 第4年 | G37: 第5年 | H37: 第6年 | I37: 第7年 | J37: 第8年 | K37: 第9年 | L37: 第10年 | M37: 第11年 | N37: 第12年 | O37: 第13年 | P37: 第14年 | Q37: 第15年 | R37: 第16年 | S37: 第17年 | T37: 第18年 | U37: 第19年 | V37: 第20年 | W37: 第21年 | X37: 第22年 | Y37: 第23年 | Z37: 第24年 | AA37: 第25年 | AB37: 第26年
A38: 一次性留抵退税 | B38: 万元 | D38: =IF(基本参数!$B$16="是",IF(COLUMN()-2=基本参数!$B$3+1,SUM(基本参数!$B$15:$B$15),0),0) -> 0 | E38: =IF(基本参数!$B$16="是",IF(COLUMN()-2=基本参数!$B$3+1,SUM(基本参数!$B$15:$B$15),0),0) -> 0 | F38: =IF(基本参数!$B$16="是",IF(COLUMN()-2=基本参数!$B$3+1,SUM(基本参数!$B$15:$B$15),0),0) -> 0 | G38: =IF(基本参数!$B$16="是",IF(COLUMN()-2=基本参数!$B$3+1,SUM(基本参数!$B$15:$B$15),0),0) -> 0 | H38: =IF(基本参数!$B$16="是",IF(COLUMN()-2=基本参数!$B$3+1,SUM(基本参数!$B$15:$B$15),0),0) -> 0 | I38: =IF(基本参数!$B$16="是",IF(COLUMN()-2=基本参数!$B$3+1,SUM(基本参数!$B$15:$B$15),0),0) -> 0 | J38: =IF(基本参数!$B$16="是",IF(COLUMN()-2=基本参数!$B$3+1,SUM(基本参数!$B$15:$B$15),0),0) -> 0 | K38: =IF(基本参数!$B$16="是",IF(COLUMN()-2=基本参数!$B$3+1,SUM(基本参数!$B$15:$B$15),0),0) -> 0 | ... AB38: =IF(基本参数!$B$16="是",IF(COLUMN()-2=基本参数!$B$3+1,SUM(基本参数!$B$15:$B$15),0),0) -> 0
A39: 增值税率 | B39: % | C39: 0
A40: 收入2金额 | B40: 万元 | D40: 0 | E40: =D40 -> 0 | F40: =E40 -> 0 | G40: =F40 -> 0 | H40: =G40 -> 0 | I40: =H40 -> 0 | J40: =I40 -> 0 | K40: =J40 -> 0 | L40: =K40 -> 0 | ... AB40: =AA40 -> 0
A41: 收入2增值税率 | B41: % | C41: 13
A42: 收入3金额 | B42: 万元 | D42: 0 | E42: =D42 -> 0 | F42: =E42 -> 0 | G42: =F42 -> 0 | H42: =G42 -> 0 | I42: =H42 -> 0 | J42: =I42 -> 0 | K42: =J42 -> 0 | L42: =K42 -> 0 | ... AB42: =AA42 -> 0
A43: 收入3增值税率 | B43: % | C43: 13
A44: 收入4金额 | B44: 万元 | D44: 0 | E44: =D44 -> 0 | F44: =E44 -> 0 | G44: =F44 -> 0 | H44: =G44 -> 0 | I44: =H44 -> 0 | J44: =I44 -> 0 | K44: =J44 -> 0 | L44: =K44 -> 0 | ... AB44: =AA44 -> 0
A45: 收入4增值税率 | B45: % | C45: 13
A46: 收入5金额 | B46: 万元 | D46: 0 | E46: =D46 -> 0 | F46: =E46 -> 0 | G46: =F46 -> 0 | H46: =G46 -> 0 | I46: =H46 -> 0 | J46: =I46 -> 0 | K46: =J46 -> 0 | L46: =K46 -> 0 | ... AB46: =AA46 -> 0
A47: 收入5增值税率 | B47: % | C47: 13
A48: 最终收入合计（应税）含增值税 | B48: 万元 | D48: =D38+D40 -> 0 | E48: =E38+E40 -> 0 | F48: =F38+F40 -> 0 | G48: =G38+G40 -> 0 | H48: =H38+H40 -> 0 | I48: =I38+I40 -> 0 | J48: =J38+J40 -> 0 | K48: =K38+K40 -> 0 | ... AB48: =AB38+AB40 -> 0
A49: 最终收入合计（应税）不含增值税 | B49: 万元 | D49: =D38/(1+$C$39%)+D40/(1+$C$41%)+D42/(1+$C$43%)+D44/(1+$C$45%)+D46/(1+$C$47%) -> 0 | E49: =E38/(1+$C$39%)+E40/(1+$C$41%)+E42/(1+$C$43%)+E44/(1+$C$45%)+E46/(1+$C$47%) -> 0 | F49: =F38/(1+$C$39%)+F40/(1+$C$41%)+F42/(1+$C$43%)+F44/(1+$C$45%)+F46/(1+$C$47%) -> 0 | G49: =G38/(1+$C$39%)+G40/(1+$C$41%)+G42/(1+$C$43%)+G44/(1+$C$45%)+G46/(1+$C$47%) -> 0 | H49: =H38/(1+$C$39%)+H40/(1+$C$41%)+H42/(1+$C$43%)+H44/(1+$C$45%)+H46/(1+$C$47%) -> 0 | I49: =I38/(1+$C$39%)+I40/(1+$C$41%)+I42/(1+$C$43%)+I44/(1+$C$45%)+I46/(1+$C$47%) -> 0 | J49: =J38/(1+$C$39%)+J40/(1+$C$41%)+J42/(1+$C$43%)+J44/(1+$C$45%)+J46/(1+$C$47%) -> 0 | K49: =K38/(1+$C$39%)+K40/(1+$C$41%)+K42/(1+$C$43%)+K44/(1+$C$45%)+K46/(1+$C$47%) -> 0 | ... AB49: =AB38/(1+$C$39%)+AB40/(1+$C$41%)+AB42/(1+$C$43%)+AB44/(1+$C$45%)+AB46/(1+$C$47%) -> 0
A50: 其他收入（免交所得税）
B51: 年份 | C51: 第1年 | D51: 第2年 | E51: 第3年 | F51: 第4年 | G51: 第5年 | H51: 第6年 | I51: 第7年 | J51: 第8年 | K51: 第9年 | L51: 第10年 | M51: 第11年 | N51: 第12年 | O51: 第13年 | P51: 第14年 | Q51: 第15年 | R51: 第16年 | S51: 第17年 | T51: 第18年 | U51: 第19年 | V51: 第20年 | W51: 第21年 | X51: 第22年 | Y51: 第23年 | Z51: 第24年 | AA51: 第25年 | AB51: 第26年
A52: 收入1金额 | B52: 万元 | D52: 0 | E52: =D52 -> 0 | F52: =E52 -> 0 | G52: =F52 -> 0 | H52: =G52 -> 0 | I52: =H52 -> 0 | J52: =I52 -> 0 | K52: =J52 -> 0 | L52: =K52 -> 0 | ... AB52: =AA52 -> 0
A53: 收入1增值税率 | B53: % | C53: 13
A54: 收入2金额 | B54: 万元 | D54: 0 | E54: =D54 -> 0 | F54: =E54 -> 0 | G54: =F54 -> 0 | H54: =G54 -> 0 | I54: =H54 -> 0 | J54: =I54 -> 0 | K54: =J54 -> 0 | L54: =K54 -> 0 | ... AB54: =AA54 -> 0
A55: 收入2增值税率 | B55: % | C55: 13
A56: 收入3金额 | B56: 万元 | D56: 0 | E56: =D56 -> 0 | F56: =E56 -> 0 | G56: =F56 -> 0 | H56: =G56 -> 0 | I56: =H56 -> 0 | J56: =I56 -> 0 | K56: =J56 -> 0 | L56: =K56 -> 0 | ... AB56: =AA56 -> 0
A57: 收入3增值税率 | B57: % | C57: 13
A58: 收入4金额 | B58: 万元 | D58: 0 | E58: =D58 -> 0 | F58: =E58 -> 0 | G58: =F58 -> 0 | H58: =G58 -> 0 | I58: =H58 -> 0 | J58: =I58 -> 0 | K58: =J58 -> 0 | L58: =K58 -> 0 | ... AB58: =AA58 -> 0
A59: 收入4增值税率 | B59: % | C59: 13
A60: 收入5金额 | B60: 万元 | D60: 0 | E60: =D60 -> 0 | F60: =E60 -> 0 | G60: =F60 -> 0 | H60: =G60 -> 0 | I60: =H60 -> 0 | J60: =I60 -> 0 | K60: =J60 -> 0 | L60: =K60 -> 0 | ... AB60: =AA60 -> 0
A61: 收入5增值税率 | B61: % | C61: 13
A62: 最终收入合计（免税）含增值税 | B62: 万元 | D62: =D52+D54+D56+D58+D60 -> 0 | E62: =E52+E54+E56+E58+E60 -> 0 | F62: =F52+F54+F56+F58+F60 -> 0 | G62: =G52+G54+G56+G58+G60 -> 0 | H62: =H52+H54+H56+H58+H60 -> 0 | I62: =I52+I54+I56+I58+I60 -> 0 | J62: =J52+J54+J56+J58+J60 -> 0 | K62: =K52+K54+K56+K58+K60 -> 0 | ... AB62: =AB52+AB54+AB56+AB58+AB60 -> 0
A63: 最终收入合计（免税）不含增值税 | B63: 万元 | D63: =D52/(1+$C$53%)+D54/(1+$C$55%)+D56/(1+$C$57%)+D58/(1+$C$59%)+D60/(1+$C$61%) -> 0 | E63: =E52/(1+$C$53%)+E54/(1+$C$55%)+E56/(1+$C$57%)+E58/(1+$C$59%)+E60/(1+$C$61%) -> 0 | F63: =F52/(1+$C$53%)+F54/(1+$C$55%)+F56/(1+$C$57%)+F58/(1+$C$59%)+F60/(1+$C$61%) -> 0 | G63: =G52/(1+$C$53%)+G54/(1+$C$55%)+G56/(1+$C$57%)+G58/(1+$C$59%)+G60/(1+$C$61%) -> 0 | H63: =H52/(1+$C$53%)+H54/(1+$C$55%)+H56/(1+$C$57%)+H58/(1+$C$59%)+H60/(1+$C$61%) -> 0 | I63: =I52/(1+$C$53%)+I54/(1+$C$55%)+I56/(1+$C$57%)+I58/(1+$C$59%)+I60/(1+$C$61%) -> 0 | J63: =J52/(1+$C$53%)+J54/(1+$C$55%)+J56/(1+$C$57%)+J58/(1+$C$59%)+J60/(1+$C$61%) -> 0 | K63: =K52/(1+$C$53%)+K54/(1+$C$55%)+K56/(1+$C$57%)+K58/(1+$C$59%)+K60/(1+$C$61%) -> 0 | ... AB63: =AB52/(1+$C$53%)+AB54/(1+$C$55%)+AB56/(1+$C$57%)+AB58/(1+$C$59%)+AB60/(1+$C$61%) -> 0
A64: P型单玻组件（首年2%，后续每年0.55%） | C64: 100 | D64: 98 | E64: 97.45 | F64: 96.9 | G64: 96.35 | H64: 95.8 | I64: 95.25 | J64: 94.7 | K64: 94.15 | L64: 93.6 | M64: 93.05 | N64: 92.5 | O64: 91.95 | P64: 91.4 | Q64: 90.85 | R64: 90.3 | S64: 89.75 | T64: 89.2 | U64: 88.65 | V64: 88.1 | W64: 87.55 | X64: 87 | Y64: 86.45 | Z64: 85.9 | AA64: 85.35 | AB64: 84.8
A65: P型双玻组件（首年2%，后续每年0.5%） | C65: 100 | D65: 98 | E65: 97.5 | F65: 97 | G65: 96.5 | H65: 96 | I65: 95.5 | J65: 95 | K65: 94.5 | L65: 94 | M65: 93.5 | N65: 93 | O65: 92.5 | P65: 92 | Q65: 91.5 | R65: 91 | S65: 90.5 | T65: 90 | U65: 89.5 | V65: 89 | W65: 88.5 | X65: 88 | Y65: 87.5 | Z65: 87 | AA65: 86.5 | AB65: 86
A66: N型单玻组件（首年1%，后续每年0.45%） | C66: 100 | D66: 99 | E66: 98.55 | F66: 98.1 | G66: 97.65 | H66: 97.2 | I66: 96.75 | J66: 96.3 | K66: 95.85 | L66: 95.4 | M66: 94.95 | N66: 94.5 | O66: 94.05 | P66: 93.6 | Q66: 93.15 | R66: 92.7 | S66: 92.25 | T66: 91.8 | U66: 91.35 | V66: 90.9 | W66: 90.45 | X66: 90 | Y66: 89.55 | Z66: 89.1 | AA66: 88.65 | AB66: 88.2
A67: N型双玻组件（首年1%，后续每年0.4%） | C67: 100 | D67: 99 | E67: 98.6 | F67: 98.2 | G67: 97.8 | H67: 97.4 | I67: 97 | J67: 96.6 | K67: 96.2 | L67: 95.8 | M67: 95.4 | N67: 95 | O67: 94.6 | P67: 94.2 | Q67: 93.8 | R67: 93.4 | S67: 93 | T67: 92.6 | U67: 92.2 | V67: 91.8 | W67: 91.4 | X67: 91 | Y67: 90.6 | Z67: 90.2 | AA67: 89.8 | AB67: 89.4
A68: 多晶单玻组件（首年2%，后续每年0.55%） | C68: 100 | D68: 98 | E68: 97.45 | F68: 96.9 | G68: 96.35 | H68: 95.8 | I68: 95.25 | J68: 94.7 | K68: 94.15 | L68: 93.6 | M68: 93.05 | N68: 92.5 | O68: 91.95 | P68: 91.4 | Q68: 90.85 | R68: 90.3 | S68: 89.75 | T68: 89.2 | U68: 88.65 | V68: 88.1 | W68: 87.55 | X68: 87 | Y68: 86.45 | Z68: 85.9 | AA68: 85.35 | AB68: 84.8
A69: 多晶双玻组件（首年2%，后续每年0.5%） | C69: 100 | D69: 98 | E69: 97.5 | F69: 97 | G69: 96.5 | H69: 96 | I69: 95.5 | J69: 95 | K69: 94.5 | L69: 94 | M69: 93.5 | N69: 93 | O69: 92.5 | P69: 92 | Q69: 91.5 | R69: 91 | S69: 90.5 | T69: 90 | U69: 89.5 | V69: 89 | W69: 88.5 | X69: 88 | Y69: 87.5 | Z69: 87 | AA69: 86.5 | AB69: 86

Sheet 电价电量计算表
A1: 电价
A2: 电价取值标准 | B2: 标准1
A3: 手动输入电价算法 | B3: 综合电价
B4: 年份 | C4: 第1年 | D4: 第2年 | E4: 第3年 | F4: 第4年 | G4: 第5年 | H4: 第6年 | I4: 第7年 | J4: 第8年 | K4: 第9年 | L4: 第10年 | M4: 第11年 | N4: 第12年 | O4: 第13年 | P4: 第14年 | Q4: 第15年 | R4: 第16年 | S4: 第17年 | T4: 第18年 | U4: 第19年 | V4: 第20年 | W4: 第21年 | X4: 第22年 | Y4: 第23年 | Z4: 第24年 | AA4: 第25年 | AB4: 第26年
A5: 综合结算电价（直接手动输入） | B5: 元/kWh | D5: 0.3 | E5: 0.3 | F5: 0.3 | G5: 0.3 | H5: 0.3 | I5: 0.3 | J5: 0.3 | K5: 0.3 | L5: 0.3 | M5: 0.3 | N5: 0.3 | O5: 0.3 | P5: 0.3 | Q5: 0.3 | R5: 0.3 | S5: 0.3 | T5: 0.3 | U5: 0.3 | V5: 0.3 | W5: 0.3 | X5: 0.3 | Y5: 0.3 | Z5: 0.3 | AA5: 0.3 | AB5: 0.3
A6: 分项电价1 | B6: 元/kWh | D6: 0.4 | E6: 0.4 | F6: 0.4 | G6: 0.4 | H6: 0.4 | I6: 0.4 | J6: 0.4 | K6: 0.4 | L6: 0.4 | M6: 0.4 | N6: 0.4 | O6: 0.4 | P6: 0.4 | Q6: 0.4 | R6: 0.4 | S6: 0.4 | T6: 0.4 | U6: 0.4 | V6: 0.4 | W6: 0.4 | X6: 0.4 | Y6: 0.4 | Z6: 0.4 | AA6: 0.4 | AB6: 0.4
B7: 占比（%） | D7: 100 | E7: 100 | F7: 100 | G7: 100 | H7: 100 | I7: 100 | J7: 100 | K7: 100 | L7: 100 | M7: 100 | N7: 100 | O7: 100 | P7: 100 | Q7: 100 | R7: 100 | S7: 100 | T7: 100 | U7: 100 | V7: 100 | W7: 100 | X7: 100 | Y7: 100 | Z7: 100 | AA7: 100 | AB7: 100
A8: 分项电价2 | B8: 元/kWh
B9: 占比（%）
A10: 分项电价3 | B10: 元/kWh
B11: 占比（%）
A12: 综合结算电价（根据分项加权平均） | B12: 元/kWh | D12: =D6*IF($B$7="占比（%）",D7%,D7/D14)+D8*IF($B$9="占比（%）",D9%,D9/D14)+D10*IF($B$11="占比（%）",D11%,D11/D14) -> 0.4 | E12: =E6*IF($B$7="占比（%）",E7%,E7/E14)+E8*IF($B$9="占比（%）",E9%,E9/E14)+E10*IF($B$11="占比（%）",E11%,E11/E14) -> 0.4 | F12: =F6*IF($B$7="占比（%）",F7%,F7/F14)+F8*IF($B$9="占比（%）",F9%,F9/F14)+F10*IF($B$11="占比（%）",F11%,F11/F14) -> 0.4 | G12: =G6*IF($B$7="占比（%）",G7%,G7/G14)+G8*IF($B$9="占比（%）",G9%,G9/G14)+G10*IF($B$11="占比（%）",G11%,G11/G14) -> 0.4 | H12: =H6*IF($B$7="占比（%）",H7%,H7/H14)+H8*IF($B$9="占比（%）",H9%,H9/H14)+H10*IF($B$11="占比（%）",H11%,H11/H14) -> 0.4 | I12: =I6*IF($B$7="占比（%）",I7%,I7/I14)+I8*IF($B$9="占比（%）",I9%,I9/I14)+I10*IF($B$11="占比（%）",I11%,I11/I14) -> 0.4 | J12: =J6*IF($B$7="占比（%）",J7%,J7/J14)+J8*IF($B$9="占比（%）",J9%,J9/J14)+J10*IF($B$11="占比（%）",J11%,J11/J14) -> 0.4 | K12: =K6*IF($B$7="占比（%）",K7%,K7/K14)+K8*IF($B$9="占比（%）",K9%,K9/K14)+K10*IF($B$11="占比（%）",K11%,K11/K14) -> 0.4 | ... AB12: =AB6*IF($B$7="占比（%）",AB7%,AB7/AB14)+AB8*IF($B$9="占比（%）",AB9%,AB9/AB14)+AB10*IF($B$11="占比（%）",AB11%,AB11/AB14) -> 0.4
A13: 综合结算电价（最终） | B13: 元/kWh | D13: =IF($B$2="手动输入",IF($B$3="综合电价",D5,D12),VLOOKUP(地区辅助页!$E$1,IF($B$2="标准1",电价电量取值表!$A:$H,电价电量取值表!$Q:$X),IF(D15>2030,8,D15-2025+3),FALSE))*IF(OR(基本参数!$B$2<=COLUMN()-3,COLUMN()-3<基本参数!$B$3),0,1) -> #VALUE! | E13: =IF($B$2="手动输入",IF($B$3="综合电价",E5,E12),VLOOKUP(地区辅助页!$E$1,IF($B$2="标准1",电价电量取值表!$A:$H,电价电量取值表!$Q:$X),IF(E15>2030,8,E15-2025+3),FALSE))*IF(OR(基本参数!$B$2<=COLUMN()-3,COLUMN()-3<基本参数!$B$3),0,1) -> #VALUE! | F13: =IF($B$2="手动输入",IF($B$3="综合电价",F5,F12),VLOOKUP(地区辅助页!$E$1,IF($B$2="标准1",电价电量取值表!$A:$H,电价电量取值表!$Q:$X),IF(F15>2030,8,F15-2025+3),FALSE))*IF(OR(基本参数!$B$2<=COLUMN()-3,COLUMN()-3<基本参数!$B$3),0,1) -> #VALUE! | G13: =IF($B$2="手动输入",IF($B$3="综合电价",G5,G12),VLOOKUP(地区辅助页!$E$1,IF($B$2="标准1",电价电量取值表!$A:$H,电价电量取值表!$Q:$X),IF(G15>2030,8,G15-2025+3),FALSE))*IF(OR(基本参数!$B$2<=COLUMN()-3,COLUMN()-3<基本参数!$B$3),0,1) -> #VALUE! | H13: =IF($B$2="手动输入",IF($B$3="综合电价",H5,H12),VLOOKUP(地区辅助页!$E$1,IF($B$2="标准1",电价电量取值表!$A:$H,电价电量取值表!$Q:$X),IF(H15>2030,8,H15-2025+3),FALSE))*IF(OR(基本参数!$B$2<=COLUMN()-3,COLUMN()-3<基本参数!$B$3),0,1) -> #VALUE! | I13: =IF($B$2="手动输入",IF($B$3="综合电价",I5,I12),VLOOKUP(地区辅助页!$E$1,IF($B$2="标准1",电价电量取值表!$A:$H,电价电量取值表!$Q:$X),IF(I15>2030,8,I15-2025+3),FALSE))*IF(OR(基本参数!$B$2<=COLUMN()-3,COLUMN()-3<基本参数!$B$3),0,1) -> #VALUE! | J13: =IF($B$2="手动输入",IF($B$3="综合电价",J5,J12),VLOOKUP(地区辅助页!$E$1,IF($B$2="标准1",电价电量取值表!$A:$H,电价电量取值表!$Q:$X),IF(J15>2030,8,J15-2025+3),FALSE))*IF(OR(基本参数!$B$2<=COLUMN()-3,COLUMN()-3<基本参数!$B$3),0,1) -> #VALUE! | K13: =IF($B$2="手动输入",IF($B$3="综合电价",K5,K12),VLOOKUP(地区辅助页!$E$1,IF($B$2="标准1",电价电量取值表!$A:$H,电价电量取值表!$Q:$X),IF(K15>2030,8,K15-2025+3),FALSE))*IF(OR(基本参数!$B$2<=COLUMN()-3,COLUMN()-3<基本参数!$B$3),0,1) -> #VALUE! | ... AB13: =IF($B$2="手动输入",IF($B$3="综合电价",AB5,AB12),VLOOKUP(地区辅助页!$E$1,IF($B$2="标准1",电价电量取值表!$A:$H,电价电量取值表!$Q:$X),IF(AB15>2030,8,AB15-2025+3),FALSE))*IF(OR(基本参数!$B$2<=COLUMN()-3,COLUMN()-3<基本参数!$B$3),0,1) -> #VALUE!
A14: 上网利用小时数 | B14: 小时 | D14: =收入和税金!D10/基本参数!$B$7 -> #VALUE! | E14: =收入和税金!E10/基本参数!$B$7 -> #VALUE! | F14: =收入和税金!F10/基本参数!$B$7 -> #VALUE! | G14: =收入和税金!G10/基本参数!$B$7 -> #VALUE! | H14: =收入和税金!H10/基本参数!$B$7 -> #VALUE! | I14: =收入和税金!I10/基本参数!$B$7 -> #VALUE! | J14: =收入和税金!J10/基本参数!$B$7 -> #VALUE! | K14: =收入和税金!K10/基本参数!$B$7 -> #VALUE! | ... AB14: =收入和税金!AB10/基本参数!$B$7 -> #VALUE!
A15: 年份 | D15: =基本参数!B8 -> 0 | E15: =D15+1 -> 1 | F15: =E15+1 -> 2 | G15: =F15+1 -> 3 | H15: =G15+1 -> 4 | I15: =H15+1 -> 5 | J15: =I15+1 -> 6 | K15: =J15+1 -> 7 | L15: =K15+1 -> 8 | ... AB15: =AA15+1 -> 24
A16: 分项发电量占总发电量比例 | D16: =IF($B$7="占比（%）",D7,D7/D14*100)+IF($B$9="占比（%）",D9,D9/D14*100)+IF($B$11="占比（%）",D11,D11/D14*100) -> 100 | E16: =IF($B$7="占比（%）",E7,E7/E14*100)+IF($B$9="占比（%）",E9,E9/E14*100)+IF($B$11="占比（%）",E11,E11/E14*100) -> 100 | F16: =IF($B$7="占比（%）",F7,F7/F14*100)+IF($B$9="占比（%）",F9,F9/F14*100)+IF($B$11="占比（%）",F11,F11/F14*100) -> 100 | G16: =IF($B$7="占比（%）",G7,G7/G14*100)+IF($B$9="占比（%）",G9,G9/G14*100)+IF($B$11="占比（%）",G11,G11/G14*100) -> 100 | H16: =IF($B$7="占比（%）",H7,H7/H14*100)+IF($B$9="占比（%）",H9,H9/H14*100)+IF($B$11="占比（%）",H11,H11/H14*100) -> 100 | I16: =IF($B$7="占比（%）",I7,I7/I14*100)+IF($B$9="占比（%）",I9,I9/I14*100)+IF($B$11="占比（%）",I11,I11/I14*100) -> 100 | J16: =IF($B$7="占比（%）",J7,J7/J14*100)+IF($B$9="占比（%）",J9,J9/J14*100)+IF($B$11="占比（%）",J11,J11/J14*100) -> 100 | K16: =IF($B$7="占比（%）",K7,K7/K14*100)+IF($B$9="占比（%）",K9,K9/K14*100)+IF($B$11="占比（%）",K11,K11/K14*100) -> 100 | ... AB16: =IF($B$7="占比（%）",AB7,AB7/AB14*100)+IF($B$9="占比（%）",AB9,AB9/AB14*100)+IF($B$11="占比（%）",AB11,AB11/AB14*100) -> 100

Sheet 投资计划与资金筹措表
A1: 投资计划与资金筹措表
A2: 人民币单位：万元
A3: 序号 | B3: 项目 | C3: 合计 | D3: 计算期
D4: 第1年 | E4: 第2年
A5: 1 | B5: 总投资 | C5: =SUM(D5:E5) -> 0 | D5: =SUM(D6:D8) -> 0 | E5: =SUM(E6:E8) -> 0
A6: 1.1 | B6: 建设投资 | C6: =SUM(D6:E6) -> 0 | D6: =基本参数!B12 -> 0 | E6: 0
A7: 1.2 | B7: 建设期利息 | C7: =SUM(D7:E7) -> 0 | D7: =基本参数!B20 -> 0 | E7: 0
A8: 1.3 | B8: 流动资金 | C8: =SUM(D8:E8) -> 0 | D8: =IF(COLUMN()-3=基本参数!$B$3+1,基本参数!$B$7/10*基本参数!$B$27,0) -> 0 | E8: =IF(COLUMN()-3=基本参数!$B$3+1,基本参数!$B$7/10*基本参数!$B$27,0) -> 0
A9: 2 | B9: 资金筹措 | C9: =SUM(D9:E9) -> 0 | D9: =D10+D13 -> 0 | E9: =E10+E13 -> 0
A10: 2.1 | B10: 资本金（资金筹措） | C10: =SUM(D10:E10) -> 0 | D10: =D11+D12 -> 0 | E10: =E11+E12 -> 0
A11: 2.1.1 | B11: 建设投资资本金 | C11: =SUM(D11:E11) -> 0 | D11: =基本参数!$B$17%*(D5-D8) -> 0 | E11: =基本参数!$B$17%*(E5-E8) -> 0
A12: 2.1.2 | B12: 流动资金资本金 | C12: =SUM(D12:E12) -> 0 | D12: =D8*基本参数!$B$28% -> 0 | E12: =E8*基本参数!$B$28% -> 0
A13: 2.2 | B13: 借款 | C13: =SUM(D13:E13) -> 0 | D13: =D14+D17 -> 0 | E13: =E14+E17 -> 0
A14: 2.2.1 | B14: 长期借款 | C14: =SUM(D14:E14) -> 0 | D14: =SUM(D15:D16) -> 0 | E14: =SUM(E15:E16) -> 0
B15: 长期借款本金 | C15: =SUM(D15:E15) -> 0 | D15: =D6-D11 -> 0 | E15: =E6-E11 -> 0
B16: 建设期利息 | C16: =SUM(D16:E16) -> 0 | D16: =D7 -> 0 | E16: =E7 -> 0
A17: 2.2.2 | B17: 流动资金借款 | C17: =SUM(D17:E17) -> 0 | D17: =D8-D12 -> 0 | E17: =E8-E12 -> 0

Sheet 总成本费用表
A1: 总成本费用表
A2: 人民币单位：万元
A3: 序号 | B3: 项目 | C3: 合计 | D3: 建设期 | E3: 运行期
D4: 第1年 | E4: 第2年 | F4: 第3年 | G4: 第4年 | H4: 第5年 | I4: 第6年 | J4: 第7年 | K4: 第8年 | L4: 第9年 | M4: 第10年 | N4: 第11年 | O4: 第12年 | P4: 第13年 | Q4: 第14年 | R4: 第15年 | S4: 第16年 | T4: 第17年 | U4: 第18年 | V4: 第19年 | W4: 第20年 | X4: 第21年 | Y4: 第22年 | Z4: 第23年 | AA4: 第24年 | AB4: 第25年 | AC4: 第26年
A5: 1 | B5: 折旧费 | C5: =SUM(D5:AC5) -> 0 | D5: =成本费用!C8 -> 0 | E5: =成本费用!D8 -> 0 | F5: =成本费用!E8 -> 0 | G5: =成本费用!F8 -> 0 | H5: =成本费用!G8 -> 0 | I5: =成本费用!H8 -> 0 | J5: =成本费用!I8 -> 0 | K5: =成本费用!J8 -> 0 | ... AC5: =成本费用!AB8 -> 0
A6: 2 | B6: 维修费 | C6: =SUM(D6:AC6) -> #REF! | D6: =成本费用!C17 -> 0 | E6: =成本费用!D17 -> #REF! | F6: =成本费用!E17 -> #REF! | G6: =成本费用!F17 -> #REF! | H6: =成本费用!G17 -> #REF! | I6: =成本费用!H17 -> #REF! | J6: =成本费用!I17 -> #REF! | K6: =成本费用!J17 -> #REF! | ... AC6: =成本费用!AB17 -> #REF!
A7: 3 | B7: 工资及福利 | C7: =SUM(D7:AC7) -> #REF! | D7: =成本费用!C25 -> 0 | E7: =成本费用!D25 -> #REF! | F7: =成本费用!E25 -> #REF! | G7: =成本费用!F25 -> #REF! | H7: =成本费用!G25 -> #REF! | I7: =成本费用!H25 -> #REF! | J7: =成本费用!I25 -> #REF! | K7: =成本费用!J25 -> #REF! | ... AC7: =成本费用!AB25 -> #REF!
A8: 4 | B8: 保险费 | C8: =SUM(D8:AC8) -> #REF! | D8: =成本费用!C33 -> 0 | E8: =成本费用!D33 -> #REF! | F8: =成本费用!E33 -> #REF! | G8: =成本费用!F33 -> #REF! | H8: =成本费用!G33 -> #REF! | I8: =成本费用!H33 -> #REF! | J8: =成本费用!I33 -> #REF! | K8: =成本费用!J33 -> #REF! | ... AC8: =成本费用!AB33 -> #REF!
A9: 5 | B9: 材料费 | C9: =SUM(D9:AC9) -> #REF! | D9: =成本费用!C40 -> 0 | E9: =成本费用!D40 -> #REF! | F9: =成本费用!E40 -> #REF! | G9: =成本费用!F40 -> #REF! | H9: =成本费用!G40 -> #REF! | I9: =成本费用!H40 -> #REF! | J9: =成本费用!I40 -> #REF! | K9: =成本费用!J40 -> #REF! | ... AC9: =成本费用!AB40 -> #REF!
A10: 6 | B10: 委托运维费 | C10: =SUM(D10:AC10) -> #DIV/0! | D10: =成本费用!C47 -> 0 | E10: =成本费用!D47 -> #DIV/0! | F10: =成本费用!E47 -> #DIV/0! | G10: =成本费用!F47 -> #DIV/0! | H10: =成本费用!G47 -> #DIV/0! | I10: =成本费用!H47 -> #DIV/0! | J10: =成本费用!I47 -> #DIV/0! | K10: =成本费用!J47 -> #DIV/0! | ... AC10: =成本费用!AB47 -> #DIV/0!
A11: 7 | B11: 摊销费 | C11: =SUM(D11:AC11) -> 0 | D11: =成本费用!C56 -> 0 | E11: =成本费用!D56 -> 0 | F11: =成本费用!E56 -> 0 | G11: =成本费用!F56 -> 0 | H11: =成本费用!G56 -> 0 | I11: =成本费用!H56 -> 0 | J11: =成本费用!I56 -> 0 | K11: =成本费用!J56 -> 0 | ... AC11: =成本费用!AB56 -> 0
A12: 8 | B12: 利息支出 | C12: =SUM(D12:AC12) -> #VALUE! | D12: =借款还本付息计划表!D13+借款还本付息计划表!D9+借款还本付息计划表!D19 -> 0 | E12: =借款还本付息计划表!E13+借款还本付息计划表!E9+借款还本付息计划表!E19 -> 0 | F12: =借款还本付息计划表!F13+借款还本付息计划表!F9+借款还本付息计划表!F19 -> #VALUE! | G12: =借款还本付息计划表!G13+借款还本付息计划表!G9+借款还本付息计划表!G19 -> #VALUE! | H12: =借款还本付息计划表!H13+借款还本付息计划表!H9+借款还本付息计划表!H19 -> #VALUE! | I12: =借款还本付息计划表!I13+借款还本付息计划表!I9+借款还本付息计划表!I19 -> #VALUE! | J12: =借款还本付息计划表!J13+借款还本付息计划表!J9+借款还本付息计划表!J19 -> #VALUE! | K12: =借款还本付息计划表!K13+借款还本付息计划表!K9+借款还本付息计划表!K19 -> #VALUE! | ... AC12: =借款还本付息计划表!AC13+借款还本付息计划表!AC9+借款还本付息计划表!AC19 -> #VALUE!
A13: 9 | B13: 其他费用 | C13: =SUM(D13:AC13) -> #REF! | D13: =成本费用!C66 -> 0 | E13: =成本费用!D66 -> #REF! | F13: =成本费用!E66 -> #REF! | G13: =成本费用!F66 -> #REF! | H13: =成本费用!G66 -> #REF! | I13: =成本费用!H66 -> #REF! | J13: =成本费用!I66 -> #REF! | K13: =成本费用!J66 -> #REF! | ... AC13: =成本费用!AB66 -> #REF!
A14: 9.1 | B14: 其他费用 | C14: =SUM(D14:AC14) -> #REF! | D14: =成本费用!C60 -> 0 | E14: =成本费用!D60 -> #REF! | F14: =成本费用!E60 -> #REF! | G14: =成本费用!F60 -> #REF! | H14: =成本费用!G60 -> #REF! | I14: =成本费用!H60 -> #REF! | J14: =成本费用!I60 -> #REF! | K14: =成本费用!J60 -> #REF! | ... AC14: =成本费用!AB60 -> #REF!
A15: 9.2 | B15: =成本费用!A61 -> 其他费用1 | C15: =SUM(D15:AC15) -> 0 | D15: =成本费用!C61 -> 0 | E15: =成本费用!D61 -> 0 | F15: =成本费用!E61 -> 0 | G15: =成本费用!F61 -> 0 | H15: =成本费用!G61 -> 0 | I15: =成本费用!H61 -> 0 | J15: =成本费用!I61 -> 0 | K15: =成本费用!J61 -> 0 | ... AC15: =成本费用!AB61 -> 0
A16: 9.3 | B16: =成本费用!A62 -> 其他费用2 | C16: =SUM(D16:AC16) -> 0 | D16: =成本费用!C62 -> 0 | E16: =成本费用!D62 -> 0 | F16: =成本费用!E62 -> 0 | G16: =成本费用!F62 -> 0 | H16: =成本费用!G62 -> 0 | I16: =成本费用!H62 -> 0 | J16: =成本费用!I62 -> 0 | K16: =成本费用!J62 -> 0 | ... AC16: =成本费用!AB62 -> 0
A17: 9.4 | B17: =成本费用!A63 -> 其他费用3 | C17: =SUM(D17:AC17) -> 0 | D17: =成本费用!C63 -> 0 | E17: =成本费用!D63 -> 0 | F17: =成本费用!E63 -> 0 | G17: =成本费用!F63 -> 0 | H17: =成本费用!G63 -> 0 | I17: =成本费用!H63 -> 0 | J17: =成本费用!I63 -> 0 | K17: =成本费用!J63 -> 0 | ... AC17: =成本费用!AB63 -> 0
A18: 9.5 | B18: 其他费用4 | C18: =SUM(D18:AC18) -> 0 | D18: =成本费用!C64 -> 0 | E18: =成本费用!D64 -> 0 | F18: =成本费用!E64 -> 0 | G18: =成本费用!F64 -> 0 | H18: =成本费用!G64 -> 0 | I18: =成本费用!H64 -> 0 | J18: =成本费用!I64 -> 0 | K18: =成本费用!J64 -> 0 | ... AC18: =成本费用!AB64 -> 0
A19: 9.6 | B19: 其他费用5 | C19: =SUM(D19:AC19) -> 0 | D19: =成本费用!C65 -> 0 | E19: =成本费用!D65 -> 0 | F19: =成本费用!E65 -> 0 | G19: =成本费用!F65 -> 0 | H19: =成本费用!G65 -> 0 | I19: =成本费用!H65 -> 0 | J19: =成本费用!I65 -> 0 | K19: =成本费用!J65 -> 0 | ... AC19: =成本费用!AB65 -> 0
A20: 10 | B20: 总成本费用 | C20: =SUM(D20:AC20) -> #REF! | D20: =D21+D5+D11+D12 -> 0 | E20: =E21+E5+E11+E12 -> #REF! | F20: =F21+F5+F11+F12 -> #REF! | G20: =G21+G5+G11+G12 -> #REF! | H20: =H21+H5+H11+H12 -> #REF! | I20: =I21+I5+I11+I12 -> #REF! | J20: =J21+J5+J11+J12 -> #REF! | K20: =K21+K5+K11+K12 -> #REF! | ... AC20: =AC21+AC5+AC11+AC12 -> #REF!
A21: 11 | B21: 经营成本 | C21: =SUM(D21:AC21) -> #REF! | D21: =D6+D7+D8+D9+D10+D13 -> 0 | E21: =E6+E7+E8+E9+E10+E13 -> #REF! | F21: =F6+F7+F8+F9+F10+F13 -> #REF! | G21: =G6+G7+G8+G9+G10+G13 -> #REF! | H21: =H6+H7+H8+H9+H10+H13 -> #REF! | I21: =I6+I7+I8+I9+I10+I13 -> #REF! | J21: =J6+J7+J8+J9+J10+J13 -> #REF! | K21: =K6+K7+K8+K9+K10+K13 -> #REF! | ... AC21: =AC6+AC7+AC8+AC9+AC10+AC13 -> #REF!
A22: 12 | B22: 固定成本(无材料费) | C22: =SUM(D22:AC22) -> #REF! | D22: =D5+D6+D7+D8+D10+D11+D12+D13 -> 0 | E22: =E5+E6+E7+E8+E10+E11+E12+E13 -> #REF! | F22: =F5+F6+F7+F8+F10+F11+F12+F13 -> #REF! | G22: =G5+G6+G7+G8+G10+G11+G12+G13 -> #REF! | H22: =H5+H6+H7+H8+H10+H11+H12+H13 -> #REF! | I22: =I5+I6+I7+I8+I10+I11+I12+I13 -> #REF! | J22: =J5+J6+J7+J8+J10+J11+J12+J13 -> #REF! | K22: =K5+K6+K7+K8+K10+K11+K12+K13 -> #REF! | ... AC22: =AC5+AC6+AC7+AC8+AC10+AC11+AC12+AC13 -> #REF!
A23: 13 | B23: 可变成本 | C23: =SUM(D23:AC23) -> #REF! | D23: =D9 -> 0 | E23: =E9 -> #REF! | F23: =F9 -> #REF! | G23: =G9 -> #REF! | H23: =H9 -> #REF! | I23: =I9 -> #REF! | J23: =J9 -> #REF! | K23: =K9 -> #REF! | ... AC23: =AC9 -> #REF!

Sheet 借款还本付息计划表
A1: 借款还本付息计划表
A2: 人民币单位：万元
A3: 序号 | B3: 项目 | C3: 合计 | D3: 建设期 | E3: 运行期
D4: 第1年 | E4: 第2年 | F4: 第3年 | G4: 第4年 | H4: 第5年 | I4: 第6年 | J4: 第7年 | K4: 第8年 | L4: 第9年 | M4: 第10年 | N4: 第11年 | O4: 第12年 | P4: 第13年 | Q4: 第14年 | R4: 第15年 | S4: 第16年 | T4: 第17年 | U4: 第18年 | V4: 第19年 | W4: 第20年 | X4: 第21年 | Y4: 第22年 | Z4: 第23年 | AA4: 第24年 | AB4: 第25年 | AC4: 第26年
A5: 1 | B5: 长期借款 | C5: =SUM(D5:AC5) -> 0 | D5: =投资计划与资金筹措表!D14 -> 0 | E5: =投资计划与资金筹措表!E14 -> 0
A6: 1.1 | B6: 年初借款余额 | D6: =IF(基本参数!$B$35="约定还款",成本费用!C85,IF(基本参数!$B$35="等额还本付息",成本费用!C82,成本费用!C78)) -> 0 | E6: =IF(基本参数!$B$35="约定还款",成本费用!D85,IF(基本参数!$B$35="等额还本付息",成本费用!D82,成本费用!D78)) -> 0 | F6: =IF(基本参数!$B$35="约定还款",成本费用!E85,IF(基本参数!$B$35="等额还本付息",成本费用!E82,成本费用!E78)) -> 0 | G6: =IF(基本参数!$B$35="约定还款",成本费用!F85,IF(基本参数!$B$35="等额还本付息",成本费用!F82,成本费用!F78)) -> 0 | H6: =IF(基本参数!$B$35="约定还款",成本费用!G85,IF(基本参数!$B$35="等额还本付息",成本费用!G82,成本费用!G78)) -> 0 | I6: =IF(基本参数!$B$35="约定还款",成本费用!H85,IF(基本参数!$B$35="等额还本付息",成本费用!H82,成本费用!H78)) -> 0 | J6: =IF(基本参数!$B$35="约定还款",成本费用!I85,IF(基本参数!$B$35="等额还本付息",成本费用!I82,成本费用!I78)) -> 0 | K6: =IF(基本参数!$B$35="约定还款",成本费用!J85,IF(基本参数!$B$35="等额还本付息",成本费用!J82,成本费用!J78)) -> 0 | ... AC6: =IF(基本参数!$B$35="约定还款",成本费用!AB85,IF(基本参数!$B$35="等额还本付息",成本费用!AB82,成本费用!AB78)) -> 0
A7: 1.2 | B7: 当期还本付息 | C7: =SUM(D7:AC7) -> 0 | D7: =D8+D9 -> 0 | E7: =E8+E9 -> 0 | F7: =F8+F9 -> 0 | G7: =G8+G9 -> 0 | H7: =H8+H9 -> 0 | I7: =I8+I9 -> 0 | J7: =J8+J9 -> 0 | K7: =K8+K9 -> 0 | ... AC7: =AC8+AC9 -> 0
A8: 1.2.1 | B8: 本年还本 | C8: =SUM(D8:AC8) -> 0 | D8: =IF(基本参数!$B$35="约定还款",成本费用!C86,IF(基本参数!$B$35="等额还本付息",成本费用!C83,成本费用!C79)) -> 0 | E8: =IF(基本参数!$B$35="约定还款",成本费用!D86,IF(基本参数!$B$35="等额还本付息",成本费用!D83,成本费用!D79)) -> 0 | F8: =IF(基本参数!$B$35="约定还款",成本费用!E86,IF(基本参数!$B$35="等额还本付息",成本费用!E83,成本费用!E79)) -> 0 | G8: =IF(基本参数!$B$35="约定还款",成本费用!F86,IF(基本参数!$B$35="等额还本付息",成本费用!F83,成本费用!F79)) -> 0 | H8: =IF(基本参数!$B$35="约定还款",成本费用!G86,IF(基本参数!$B$35="等额还本付息",成本费用!G83,成本费用!G79)) -> 0 | I8: =IF(基本参数!$B$35="约定还款",成本费用!H86,IF(基本参数!$B$35="等额还本付息",成本费用!H83,成本费用!H79)) -> 0 | J8: =IF(基本参数!$B$35="约定还款",成本费用!I86,IF(基本参数!$B$35="等额还本付息",成本费用!I83,成本费用!I79)) -> 0 | K8: =IF(基本参数!$B$35="约定还款",成本费用!J86,IF(基本参数!$B$35="等额还本付息",成本费用!J83,成本费用!J79)) -> 0 | ... AC8: =IF(基本参数!$B$35="约定还款",成本费用!AB86,IF(基本参数!$B$35="等额还本付息",成本费用!AB83,成本费用!AB79)) -> 0
A9: 1.2.2 | B9: 本年付息 | C9: =SUM(D9:AC9) -> 0 | D9: =IF(基本参数!$B$35="约定还款",成本费用!C87,IF(基本参数!$B$35="等额还本付息",成本费用!C84,成本费用!C80)) -> 0 | E9: =IF(基本参数!$B$35="约定还款",成本费用!D87,IF(基本参数!$B$35="等额还本付息",成本费用!D84,成本费用!D80)) -> 0 | F9: =IF(基本参数!$B$35="约定还款",成本费用!E87,IF(基本参数!$B$35="等额还本付息",成本费用!E84,成本费用!E80)) -> 0 | G9: =IF(基本参数!$B$35="约定还款",成本费用!F87,IF(基本参数!$B$35="等额还本付息",成本费用!F84,成本费用!F80)) -> 0 | H9: =IF(基本参数!$B$35="约定还款",成本费用!G87,IF(基本参数!$B$35="等额还本付息",成本费用!G84,成本费用!G80)) -> 0 | I9: =IF(基本参数!$B$35="约定还款",成本费用!H87,IF(基本参数!$B$35="等额还本付息",成本费用!H84,成本费用!H80)) -> 0 | J9: =IF(基本参数!$B$35="约定还款",成本费用!I87,IF(基本参数!$B$35="等额还本付息",成本费用!I84,成本费用!I80)) -> 0 | K9: =IF(基本参数!$B$35="约定还款",成本费用!J87,IF(基本参数!$B$35="等额还本付息",成本费用!J84,成本费用!J80)) -> 0 | ... AC9: =IF(基本参数!$B$35="约定还款",成本费用!AB87,IF(基本参数!$B$35="等额还本付息",成本费用!AB84,成本费用!AB80)) -> 0
A10: 1.3 | B10: 期末借款余额 | D10: =D5+D6-D8 -> 0 | E10: =E5+E6-E8 -> 0 | F10: =F5+F6-F8 -> 0 | G10: =G5+G6-G8 -> 0 | H10: =H5+H6-H8 -> 0 | I10: =I5+I6-I8 -> 0 | J10: =J5+J6-J8 -> 0 | K10: =K5+K6-K8 -> 0 | ... AC10: =AC5+AC6-AC8 -> 0
A11: 2 | B11: 流动资金借款 | C11: =SUM(D11:AC11) -> 0 | D11: =投资计划与资金筹措表!D17 -> 0 | E11: =投资计划与资金筹措表!E17 -> 0
A12: 2.1 | B12: 流动资金借款累计 | D12: =SUM($D$11:D11) -> 0 | E12: =SUM($D$11:E11) -> 0 | F12: =SUM($D$11:F11) -> 0 | G12: =SUM($D$11:G11) -> 0 | H12: =SUM($D$11:H11) -> 0 | I12: =SUM($D$11:I11) -> 0 | J12: =SUM($D$11:J11) -> 0 | K12: =SUM($D$11:K11) -> 0 | ... AC12: =SUM($D$11:AC11) -> 0
A13: 2.2 | B13: 流动资金利息 | C13: =SUM(D13:AC13) -> 0 | D13: =D12*基本参数!$B$29% -> 0 | E13: =E12*基本参数!$B$29% -> 0 | F13: =F12*基本参数!$B$29% -> 0 | G13: =G12*基本参数!$B$29% -> 0 | H13: =H12*基本参数!$B$29% -> 0 | I13: =I12*基本参数!$B$29% -> 0 | J13: =J12*基本参数!$B$29% -> 0 | K13: =K12*基本参数!$B$29% -> 0 | ... AC13: =AC12*基本参数!$B$29% -> 0
A14: 2.3 | B14: 偿还流动资金借款本金 | C14: =SUM(D14:AC14) -> 0 | D14: =IF(COLUMN()-3=基本参数!$B$2,$C$11,0) -> 0 | E14: =IF(COLUMN()-3=基本参数!$B$2,$C$11,0) -> 0 | F14: =IF(COLUMN()-3=基本参数!$B$2,$C$11,0) -> 0 | G14: =IF(COLUMN()-3=基本参数!$B$2,$C$11,0) -> 0 | H14: =IF(COLUMN()-3=基本参数!$B$2,$C$11,0) -> 0 | I14: =IF(COLUMN()-3=基本参数!$B$2,$C$11,0) -> 0 | J14: =IF(COLUMN()-3=基本参数!$B$2,$C$11,0) -> 0 | K14: =IF(COLUMN()-3=基本参数!$B$2,$C$11,0) -> 0 | ... AC14: =IF(COLUMN()-3=基本参数!$B$2,$C$11,0) -> 0
B15: 流动资金借款余额 | D15: =D12-D14 -> 0 | E15: =E12-E14 -> 0 | F15: =F12-F14 -> 0 | G15: =G12-G14 -> 0 | H15: =H12-H14 -> 0 | I15: =I12-I14 -> 0 | J15: =J12-J14 -> 0 | K15: =K12-K14 -> 0 | ... AC15: =AC12-AC14 -> 0
A16: 3 | B16: 年初短期借款余额 | D16: 0 | E16: =D20 -> 0 | F16: =E20 -> #VALUE! | G16: =F20 -> #VALUE! | H16: =G20 -> #VALUE! | I16: =H20 -> #VALUE! | J16: =I20 -> #VALUE! | K16: =J20 -> #VALUE! | L16: =K20 -> #VALUE! | ... AC16: =AB20 -> #VALUE!
B17: 本期新增短期借款 | D17: =MAX(0,财务计划现金流量表!D40) -> 0 | E17: =MAX(0,财务计划现金流量表!E40) -> #VALUE! | F17: =MAX(0,财务计划现金流量表!F40) -> #VALUE! | G17: =MAX(0,财务计划现金流量表!G40) -> #VALUE! | H17: =MAX(0,财务计划现金流量表!H40) -> #VALUE! | I17: =MAX(0,财务计划现金流量表!I40) -> #VALUE! | J17: =MAX(0,财务计划现金流量表!J40) -> #VALUE! | K17: =MAX(0,财务计划现金流量表!K40) -> #VALUE! | ... AC17: =MAX(0,财务计划现金流量表!AC40) -> #VALUE!
A18: 3.1 | B18: 偿还短期借款本金 | C18: =SUM(D18:AC18) -> #VALUE! | D18: 0 | E18: =MIN(E16,MAX(0,财务计划现金流量表!E39-财务计划现金流量表!E38)) -> #VALUE! | F18: =MIN(F16,MAX(0,财务计划现金流量表!F39-财务计划现金流量表!F38)) -> #VALUE! | G18: =MIN(G16,MAX(0,财务计划现金流量表!G39-财务计划现金流量表!G38)) -> #VALUE! | H18: =MIN(H16,MAX(0,财务计划现金流量表!H39-财务计划现金流量表!H38)) -> #VALUE! | I18: =MIN(I16,MAX(0,财务计划现金流量表!I39-财务计划现金流量表!I38)) -> #VALUE! | J18: =MIN(J16,MAX(0,财务计划现金流量表!J39-财务计划现金流量表!J38)) -> #VALUE! | K18: =MIN(K16,MAX(0,财务计划现金流量表!K39-财务计划现金流量表!K38)) -> #VALUE! | L18: =MIN(L16,MAX(0,财务计划现金流量表!L39-财务计划现金流量表!L38)) -> #VALUE! | ... AC18: =MIN(AC16,MAX(0,财务计划现金流量表!AC39-财务计划现金流量表!AC38)) -> #VALUE!
A19: 3.2 | B19: 短期借款利息 | C19: =SUM(D19:AC19) -> #VALUE! | D19: =D16*基本参数!$B$31/100 -> 0 | E19: =E16*基本参数!$B$31/100 -> 0 | F19: =F16*基本参数!$B$31/100 -> #VALUE! | G19: =G16*基本参数!$B$31/100 -> #VALUE! | H19: =H16*基本参数!$B$31/100 -> #VALUE! | I19: =I16*基本参数!$B$31/100 -> #VALUE! | J19: =J16*基本参数!$B$31/100 -> #VALUE! | K19: =K16*基本参数!$B$31/100 -> #VALUE! | ... AC19: =AC16*基本参数!$B$31/100 -> #VALUE!
B20: 短期借款期末余额 | D20: =D16-D18+D17 -> 0 | E20: =E16-E18+E17 -> #VALUE! | F20: =F16-F18+F17 -> #VALUE! | G20: =G16-G18+G17 -> #VALUE! | H20: =H16-H18+H17 -> #VALUE! | I20: =I16-I18+I17 -> #VALUE! | J20: =J16-J18+J17 -> #VALUE! | K20: =K16-K18+K17 -> #VALUE! | ... AC20: =AC16-AC18+AC17 -> #VALUE!
A21: 计算指标 | B21: 利息备付率(%) | D21: 0 | E21: =IF(COLUMN()-3<=(基本参数!$B$33+1),利润与利润分配表!E29/总成本费用表!E12,0) -> #VALUE! | F21: =IF(COLUMN()-3<=(基本参数!$B$33+1),利润与利润分配表!F29/总成本费用表!F12,0) -> #VALUE! | G21: =IF(COLUMN()-3<=(基本参数!$B$33+1),利润与利润分配表!G29/总成本费用表!G12,0) -> #VALUE! | H21: =IF(COLUMN()-3<=(基本参数!$B$33+1),利润与利润分配表!H29/总成本费用表!H12,0) -> #VALUE! | I21: =IF(COLUMN()-3<=(基本参数!$B$33+1),利润与利润分配表!I29/总成本费用表!I12,0) -> #VALUE! | J21: =IF(COLUMN()-3<=(基本参数!$B$33+1),利润与利润分配表!J29/总成本费用表!J12,0) -> #VALUE! | K21: =IF(COLUMN()-3<=(基本参数!$B$33+1),利润与利润分配表!K29/总成本费用表!K12,0) -> #VALUE! | L21: =IF(COLUMN()-3<=(基本参数!$B$33+1),利润与利润分配表!L29/总成本费用表!L12,0) -> #VALUE! | ... AC21: =IF(COLUMN()-3<=(基本参数!$B$33+1),利润与利润分配表!AC29/总成本费用表!AC12,0) -> 0
B22: 偿债备付率(%) | D22: 0 | E22: =IF(COLUMN()-3<=(基本参数!$B$33+1),(利润与利润分配表!E30-利润与利润分配表!E20)/((E8+E9)+(E14+E13)+(E18+E19)),0) -> #VALUE! | F22: =IF(COLUMN()-3<=(基本参数!$B$33+1),(利润与利润分配表!F30-利润与利润分配表!F20)/((F8+F9)+(F14+F13)+(F18+F19)),0) -> #VALUE! | G22: =IF(COLUMN()-3<=(基本参数!$B$33+1),(利润与利润分配表!G30-利润与利润分配表!G20)/((G8+G9)+(G14+G13)+(G18+G19)),0) -> #VALUE! | H22: =IF(COLUMN()-3<=(基本参数!$B$33+1),(利润与利润分配表!H30-利润与利润分配表!H20)/((H8+H9)+(H14+H13)+(H18+H19)),0) -> #VALUE! | I22: =IF(COLUMN()-3<=(基本参数!$B$33+1),(利润与利润分配表!I30-利润与利润分配表!I20)/((I8+I9)+(I14+I13)+(I18+I19)),0) -> #VALUE! | J22: =IF(COLUMN()-3<=(基本参数!$B$33+1),(利润与利润分配表!J30-利润与利润分配表!J20)/((J8+J9)+(J14+J13)+(J18+J19)),0) -> #VALUE! | K22: =IF(COLUMN()-3<=(基本参数!$B$33+1),(利润与利润分配表!K30-利润与利润分配表!K20)/((K8+K9)+(K14+K13)+(K18+K19)),0) -> #VALUE! | L22: =IF(COLUMN()-3<=(基本参数!$B$33+1),(利润与利润分配表!L30-利润与利润分配表!L20)/((L8+L9)+(L14+L13)+(L18+L19)),0) -> #VALUE! | ... AC22: =IF(COLUMN()-3<=(基本参数!$B$33+1),(利润与利润分配表!AC30-利润与利润分配表!AC20)/((AC8+AC9)+(AC14+AC13)+(AC18+AC19)),0) -> 0
A23: 辅助行 | B23: 累计盈余资金 | C23: =财务计划现金流量表!C37 -> 0 | D23: =财务计划现金流量表!D37 -> 0 | H23: =财务计划现金流量表!H37 -> #VALUE! | I23: =财务计划现金流量表!I37 -> #VALUE! | J23: =财务计划现金流量表!J37 -> #VALUE! | K23: =财务计划现金流量表!K37 -> #VALUE! | L23: =财务计划现金流量表!L37 -> #VALUE! | M23: =财务计划现金流量表!M37 -> #VALUE! | N23: =财务计划现金流量表!N37 -> #VALUE! | O23: =财务计划现金流量表!O37 -> #VALUE! | ... AC23: =财务计划现金流量表!AC37 -> #VALUE!

Sheet 利润与利润分配表
A1: 利润与利润分配表
A2: 人民币单位：万元
A3: 序号 | B3: 项目 | C3: 合计 | D3: 建设期 | E3: 运行期
D4: 第1年 | E4: 第2年 | F4: 第3年 | G4: 第4年 | H4: 第5年 | I4: 第6年 | J4: 第7年 | K4: 第8年 | L4: 第9年 | M4: 第10年 | N4: 第11年 | O4: 第12年 | P4: 第13年 | Q4: 第14年 | R4: 第15年 | S4: 第16年 | T4: 第17年 | U4: 第18年 | V4: 第19年 | W4: 第20年 | X4: 第21年 | Y4: 第22年 | Z4: 第23年 | AA4: 第24年 | AB4: 第25年 | AC4: 第26年
A5: 1 | B5: 上网电量（MWh） | C5: =SUM(D5:AC5) -> #VALUE! | D5: =收入和税金!C10 -> 0 | E5: =收入和税金!D10 -> #VALUE! | F5: =收入和税金!E10 -> #VALUE! | G5: =收入和税金!F10 -> #VALUE! | H5: =收入和税金!G10 -> #VALUE! | I5: =收入和税金!H10 -> #VALUE! | J5: =收入和税金!I10 -> #VALUE! | K5: =收入和税金!J10 -> #VALUE! | ... AC5: =收入和税金!AB10 -> #VALUE!
A6: 2 | B6: 电价（含增值税）（元/kWh） | D6: =电价电量计算表!C13 -> 0 | E6: =电价电量计算表!D13 -> #VALUE! | F6: =电价电量计算表!E13 -> #VALUE! | G6: =电价电量计算表!F13 -> #VALUE! | H6: =电价电量计算表!G13 -> #VALUE! | I6: =电价电量计算表!H13 -> #VALUE! | J6: =电价电量计算表!I13 -> #VALUE! | K6: =电价电量计算表!J13 -> #VALUE! | ... AC6: =电价电量计算表!AB13 -> #VALUE!
A7: 3 | B7: 电价（不含增值税）（元/kWh） | D7: =D6/(1+收入和税金!C16%) -> 0 | E7: =E6/(1+收入和税金!D16%) -> #VALUE! | F7: =F6/(1+收入和税金!E16%) -> #VALUE! | G7: =G6/(1+收入和税金!F16%) -> #VALUE! | H7: =H6/(1+收入和税金!G16%) -> #VALUE! | I7: =I6/(1+收入和税金!H16%) -> #VALUE! | J7: =J6/(1+收入和税金!I16%) -> #VALUE! | K7: =K6/(1+收入和税金!J16%) -> #VALUE! | ... AC7: =AC6/(1+收入和税金!AB16%) -> #VALUE!
A8: 4 | B8: 销售收入 | C8: =SUM(D8:AC8) -> #VALUE! | D8: =D9+D10+D11 -> 0 | E8: =E9+E10+E11 -> #VALUE! | F8: =F9+F10+F11 -> #VALUE! | G8: =G9+G10+G11 -> #VALUE! | H8: =H9+H10+H11 -> #VALUE! | I8: =I9+I10+I11 -> #VALUE! | J8: =J9+J10+J11 -> #VALUE! | K8: =K9+K10+K11 -> #VALUE! | ... AC8: =AC9+AC10+AC11 -> #VALUE!
A9: 4.1 | B9: 售电收入 | D9: =D7*收入和税金!C10/10 -> 0 | E9: =E7*收入和税金!D10/10 -> #VALUE! | F9: =F7*收入和税金!E10/10 -> #VALUE! | G9: =G7*收入和税金!F10/10 -> #VALUE! | H9: =H7*收入和税金!G10/10 -> #VALUE! | I9: =I7*收入和税金!H10/10 -> #VALUE! | J9: =J7*收入和税金!I10/10 -> #VALUE! | K9: =K7*收入和税金!J10/10 -> #VALUE! | ... AC9: =AC7*收入和税金!AB10/10 -> #VALUE!
A10: 4.2 | B10: 其他收入（应交所得税） | D10: =收入和税金!C49 -> 0 | E10: =收入和税金!D49 -> 0 | F10: =收入和税金!E49 -> 0 | G10: =收入和税金!F49 -> 0 | H10: =收入和税金!G49 -> 0 | I10: =收入和税金!H49 -> 0 | J10: =收入和税金!I49 -> 0 | K10: =收入和税金!J49 -> 0 | ... AC10: =收入和税金!AB49 -> 0
A11: 4.3 | B11: 其他收入（免交所得税） | D11: =收入和税金!C63 -> 0 | E11: =收入和税金!D63 -> 0 | F11: =收入和税金!E63 -> 0 | G11: =收入和税金!F63 -> 0 | H11: =收入和税金!G63 -> 0 | I11: =收入和税金!H63 -> 0 | J11: =收入和税金!I63 -> 0 | K11: =收入和税金!J63 -> 0 | ... AC11: =收入和税金!AB63 -> 0
A12: 5 | B12: 销售税金附加 | C12: =SUM(D12:AC12) -> #VALUE! | D12: =D13+D14 -> 0 | E12: =E13+E14 -> #VALUE! | F12: =F13+F14 -> #VALUE! | G12: =G13+G14 -> #VALUE! | H12: =H13+H14 -> #VALUE! | I12: =I13+I14 -> #VALUE! | J12: =J13+J14 -> #VALUE! | K12: =K13+K14 -> #VALUE! | ... AC12: =AC13+AC14 -> #VALUE!
A13: 5.1 | B13: 城市维护建设税 | C13: =SUM(D13:AC13) -> #VALUE! | D13: =IF(D37>=0,D37*收入和税金!C26/100,0) -> 0 | E13: =IF(E37>=0,E37*收入和税金!D26/100,0) -> #VALUE! | F13: =IF(F37>=0,F37*收入和税金!E26/100,0) -> #VALUE! | G13: =IF(G37>=0,G37*收入和税金!F26/100,0) -> #VALUE! | H13: =IF(H37>=0,H37*收入和税金!G26/100,0) -> #VALUE! | I13: =IF(I37>=0,I37*收入和税金!H26/100,0) -> #VALUE! | J13: =IF(J37>=0,J37*收入和税金!I26/100,0) -> #VALUE! | K13: =IF(K37>=0,K37*收入和税金!J26/100,0) -> #VALUE! | ... AC13: =IF(AC37>=0,AC37*收入和税金!AB26/100,0) -> #VALUE!
A14: 5.2 | B14: 教育费附加 | C14: =SUM(D14:AC14) -> #VALUE! | D14: =IF(D37>=0,D37*收入和税金!C29/100,0) -> 0 | E14: =IF(E37>=0,E37*收入和税金!D29/100,0) -> #VALUE! | F14: =IF(F37>=0,F37*收入和税金!E29/100,0) -> #VALUE! | G14: =IF(G37>=0,G37*收入和税金!F29/100,0) -> #VALUE! | H14: =IF(H37>=0,H37*收入和税金!G29/100,0) -> #VALUE! | I14: =IF(I37>=0,I37*收入和税金!H29/100,0) -> #VALUE! | J14: =IF(J37>=0,J37*收入和税金!I29/100,0) -> #VALUE! | K14: =IF(K37>=0,K37*收入和税金!J29/100,0) -> #VALUE! | ... AC14: =IF(AC37>=0,AC37*收入和税金!AB29/100,0) -> #VALUE!
A15: 6 | B15: 总成本费用 | C15: =SUM(D15:AC15) -> #REF! | D15: =总成本费用表!D20 -> 0 | E15: =总成本费用表!E20 -> #REF! | F15: =总成本费用表!F20 -> #REF! | G15: =总成本费用表!G20 -> #REF! | H15: =总成本费用表!H20 -> #REF! | I15: =总成本费用表!I20 -> #REF! | J15: =总成本费用表!J20 -> #REF! | K15: =总成本费用表!K20 -> #REF! | ... AC15: =总成本费用表!AC20 -> #REF!
A16: 7 | B16: 增值税返还(即征即退） | C16: =SUM(D16:AC16) -> 0 | D16: =IF(收入和税金!$C$14="是",D37*50%,0) -> 0 | E16: =IF(收入和税金!$C$14="是",E37*50%,0) -> 0 | F16: =IF(收入和税金!$C$14="是",F37*50%,0) -> 0 | G16: =IF(收入和税金!$C$14="是",G37*50%,0) -> 0 | H16: =IF(收入和税金!$C$14="是",H37*50%,0) -> 0 | I16: =IF(收入和税金!$C$14="是",I37*50%,0) -> 0 | J16: =IF(收入和税金!$C$14="是",J37*50%,0) -> 0 | K16: =IF(收入和税金!$C$14="是",K37*50%,0) -> 0 | ... AC16: =IF(收入和税金!$C$14="是",AC37*50%,0) -> 0
A17: 8 | B17: 利润总额 | C17: =SUM(D17:AC17) -> #VALUE! | D17: =D8-D12-D15+D16 -> 0 | E17: =E8-E12-E15+E16 -> #VALUE! | F17: =F8-F12-F15+F16 -> #VALUE! | G17: =G8-G12-G15+G16 -> #VALUE! | H17: =H8-H12-H15+H16 -> #VALUE! | I17: =I8-I12-I15+I16 -> #VALUE! | J17: =J8-J12-J15+J16 -> #VALUE! | K17: =K8-K12-K15+K16 -> #VALUE! | ... AC17: =AC8-AC12-AC15+AC16 -> #VALUE!
A18: 9 | B18: 弥补以前年度亏损 | C18: =SUM(D18:AC18) -> #VALUE! | D18: =D43 -> 0 | E18: =E43 -> #VALUE! | F18: =F43 -> #VALUE! | G18: =G43 -> #VALUE! | H18: =H43 -> #VALUE! | I18: =I43 -> #VALUE! | J18: =J43 -> #VALUE! | K18: =K43 -> #VALUE! | ... AC18: =AC43 -> #VALUE!
A19: 10 | B19: 应纳税所得额 | C19: =SUM(D19:AC19) -> #VALUE! | D19: =IF(D8-D11-D12-D15+D16-D18<=0,0,D8-D11-D12-D15+D16-D18) -> 0 | E19: =IF(E8-E11-E12-E15+E16-E18<=0,0,E8-E11-E12-E15+E16-E18) -> #VALUE! | F19: =IF(F8-F11-F12-F15+F16-F18<=0,0,F8-F11-F12-F15+F16-F18) -> #VALUE! | G19: =IF(G8-G11-G12-G15+G16-G18<=0,0,G8-G11-G12-G15+G16-G18) -> #VALUE! | H19: =IF(H8-H11-H12-H15+H16-H18<=0,0,H8-H11-H12-H15+H16-H18) -> #VALUE! | I19: =IF(I8-I11-I12-I15+I16-I18<=0,0,I8-I11-I12-I15+I16-I18) -> #VALUE! | J19: =IF(J8-J11-J12-J15+J16-J18<=0,0,J8-J11-J12-J15+J16-J18) -> #VALUE! | K19: =IF(K8-K11-K12-K15+K16-K18<=0,0,K8-K11-K12-K15+K16-K18) -> #VALUE! | ... AC19: =IF(AC8-AC11-AC12-AC15+AC16-AC18<=0,0,AC8-AC11-AC12-AC15+AC16-AC18) -> #VALUE!
A20: 11 | B20: 所得税 | C20: =SUM(D20:AC20) -> #VALUE! | D20: =D19*收入和税金!C23%+D16*(25-收入和税金!D23)% -> 0 | E20: =E19*收入和税金!D23%+E16*(25-收入和税金!D23)% -> #VALUE! | F20: =F19*收入和税金!E23%+F16*(25-收入和税金!E23)% -> #VALUE! | G20: =G19*收入和税金!F23%+G16*(25-收入和税金!F23)% -> #VALUE! | H20: =H19*收入和税金!G23%+H16*(25-收入和税金!G23)% -> #VALUE! | I20: =I19*收入和税金!H23%+I16*(25-收入和税金!H23)% -> #VALUE! | J20: =J19*收入和税金!I23%+J16*(25-收入和税金!I23)% -> #VALUE! | K20: =K19*收入和税金!J23%+K16*(25-收入和税金!J23)% -> #VALUE! | L20: =L19*收入和税金!K23%+L16*(25-收入和税金!K23)% -> #VALUE! | ... AC20: =AC19*收入和税金!AB23%+AC16*(25-收入和税金!AB23)% -> #VALUE!
A21: 13 | B21: 净利润（8-11+12） | C21: =SUM(D21:AC21) -> #VALUE! | D21: =D17-D20 -> 0 | E21: =E17-E20 -> #VALUE! | F21: =F17-F20 -> #VALUE! | G21: =G17-G20 -> #VALUE! | H21: =H17-H20 -> #VALUE! | I21: =I17-I20 -> #VALUE! | J21: =J17-J20 -> #VALUE! | K21: =K17-K20 -> #VALUE! | ... AC21: =AC17-AC20 -> #VALUE!
A22: 14 | B22: 期初未分配的利润(去年末未分配利润） | D22: 0 | E22: =D28 -> 0 | F22: =E28 -> #VALUE! | G22: =F28 -> #VALUE! | H22: =G28 -> #VALUE! | I22: =H28 -> #VALUE! | J22: =I28 -> #VALUE! | K22: =J28 -> #VALUE! | L22: =K28 -> #VALUE! | ... AC22: =AB28 -> #VALUE!
A23: 15 | B23: 可供分配的利润（13+14） | D23: =D21+D22 -> 0 | E23: =E21+E22 -> #VALUE! | F23: =F21+F22 -> #VALUE! | G23: =G21+G22 -> #VALUE! | H23: =H21+H22 -> #VALUE! | I23: =I21+I22 -> #VALUE! | J23: =J21+J22 -> #VALUE! | K23: =K21+K22 -> #VALUE! | ... AC23: =AC21+AC22 -> #VALUE!
A24: 16 | B24: 提取法定盈余公积金 | C24: =SUM(D24:AC24) -> #VALUE! | D24: 0 | E24: =IF(AND(E21>0,D31<=投资计划与资金筹措表!$C$10*0.5),MIN(E21*收入和税金!D32%,投资计划与资金筹措表!$C$10*0.5-D31),0) -> #VALUE! | F24: =IF(AND(F21>0,E31<=投资计划与资金筹措表!$C$10*0.5),MIN(F21*收入和税金!E32%,投资计划与资金筹措表!$C$10*0.5-E31),0) -> #VALUE! | G24: =IF(AND(G21>0,F31<=投资计划与资金筹措表!$C$10*0.5),MIN(G21*收入和税金!F32%,投资计划与资金筹措表!$C$10*0.5-F31),0) -> #VALUE! | H24: =IF(AND(H21>0,G31<=投资计划与资金筹措表!$C$10*0.5),MIN(H21*收入和税金!G32%,投资计划与资金筹措表!$C$10*0.5-G31),0) -> #VALUE! | I24: =IF(AND(I21>0,H31<=投资计划与资金筹措表!$C$10*0.5),MIN(I21*收入和税金!H32%,投资计划与资金筹措表!$C$10*0.5-H31),0) -> #VALUE! | J24: =IF(AND(J21>0,I31<=投资计划与资金筹措表!$C$10*0.5),MIN(J21*收入和税金!I32%,投资计划与资金筹措表!$C$10*0.5-I31),0) -> #VALUE! | K24: =IF(AND(K21>0,J31<=投资计划与资金筹措表!$C$10*0.5),MIN(K21*收入和税金!J32%,投资计划与资金筹措表!$C$10*0.5-J31),0) -> #VALUE! | L24: =IF(AND(L21>0,K31<=投资计划与资金筹措表!$C$10*0.5),MIN(L21*收入和税金!K32%,投资计划与资金筹措表!$C$10*0.5-K31),0) -> #VALUE! | ... AC24: =IF(AND(AC21>0,AB31<=投资计划与资金筹措表!$C$10*0.5),MIN(AC21*收入和税金!AB32%,投资计划与资金筹措表!$C$10*0.5-AB31),0) -> #VALUE!
A25: 17 | B25: 可供投资者分配的利润（15-16） | D25: =D23-D24 -> 0 | E25: =E23-E24 -> #VALUE! | F25: =F23-F24 -> #VALUE! | G25: =G23-G24 -> #VALUE! | H25: =H23-H24 -> #VALUE! | I25: =I23-I24 -> #VALUE! | J25: =J23-J24 -> #VALUE! | K25: =K23-K24 -> #VALUE! | ... AC25: =AC23-AC24 -> #VALUE!
A26: 18 | B26: 提取任意盈余公积金 | C26: =SUM(D26:AC26) -> #VALUE! | D26: =IF(D21*收入和税金!C35/100>0,D21*收入和税金!C35/100,0) -> 0 | E26: =IF(E21*收入和税金!D35/100>0,E21*收入和税金!D35/100,0) -> #VALUE! | F26: =IF(F21*收入和税金!E35/100>0,F21*收入和税金!E35/100,0) -> #VALUE! | G26: =IF(G21*收入和税金!F35/100>0,G21*收入和税金!F35/100,0) -> #VALUE! | H26: =IF(H21*收入和税金!G35/100>0,H21*收入和税金!G35/100,0) -> #VALUE! | I26: =IF(I21*收入和税金!H35/100>0,I21*收入和税金!H35/100,0) -> #VALUE! | J26: =IF(J21*收入和税金!I35/100>0,J21*收入和税金!I35/100,0) -> #VALUE! | K26: =IF(K21*收入和税金!J35/100>0,K21*收入和税金!J35/100,0) -> #VALUE! | ... AC26: =IF(AC21*收入和税金!AB35/100>0,AC21*收入和税金!AB35/100,0) -> #VALUE!
A27: 19 | B27: 应付利润 | C27: =SUM(D27:AC27) -> #VALUE! | D27: =IF(D25<=0,0,MAX(MIN(D25*收入和税金!$C$12%,财务计划现金流量表!D5+财务计划现金流量表!D16+财务计划现金流量表!D25+财务计划现金流量表!D26+财务计划现金流量表!D27+财务计划现金流量表!D28+财务计划现金流量表!D30-财务计划现金流量表!D32-财务计划现金流量表!D33-财务计划现金流量表!D35+财务计划现金流量表!C37),0)) -> 0 | E27: =IF(E25<=0,0,MAX(MIN(E25*收入和税金!$C$12%,财务计划现金流量表!E5+财务计划现金流量表!E16+财务计划现金流量表!E25+财务计划现金流量表!E26+财务计划现金流量表!E27+财务计划现金流量表!E28+财务计划现金流量表!E30-财务计划现金流量表!E32-财务计划现金流量表!E33-财务计划现金流量表!E35+财务计划现金流量表!D37),0)) -> #VALUE! | F27: =IF(F25<=0,0,MAX(MIN(F25*收入和税金!$C$12%,财务计划现金流量表!F5+财务计划现金流量表!F16+财务计划现金流量表!F25+财务计划现金流量表!F26+财务计划现金流量表!F27+财务计划现金流量表!F28+财务计划现金流量表!F30-财务计划现金流量表!F32-财务计划现金流量表!F33-财务计划现金流量表!F35+财务计划现金流量表!E37),0)) -> #VALUE! | G27: =IF(G25<=0,0,MAX(MIN(G25*收入和税金!$C$12%,财务计划现金流量表!G5+财务计划现金流量表!G16+财务计划现金流量表!G25+财务计划现金流量表!G26+财务计划现金流量表!G27+财务计划现金流量表!G28+财务计划现金流量表!G30-财务计划现金流量表!G32-财务计划现金流量表!G33-财务计划现金流量表!G35+财务计划现金流量表!F37),0)) -> #VALUE! | H27: =IF(H25<=0,0,MAX(MIN(H25*收入和税金!$C$12%,财务计划现金流量表!H5+财务计划现金流量表!H16+财务计划现金流量表!H25+财务计划现金流量表!H26+财务计划现金流量表!H27+财务计划现金流量表!H28+财务计划现金流量表!H30-财务计划现金流量表!H32-财务计划现金流量表!H33-财务计划现金流量表!H35+财务计划现金流量表!G37),0)) -> #VALUE! | I27: =IF(I25<=0,0,MAX(MIN(I25*收入和税金!$C$12%,财务计划现金流量表!I5+财务计划现金流量表!I16+财务计划现金流量表!I25+财务计划现金流量表!I26+财务计划现金流量表!I27+财务计划现金流量表!I28+财务计划现金流量表!I30-财务计划现金流量表!I32-财务计划现金流量表!I33-财务计划现金流量表!I35+财务计划现金流量表!H37),0)) -> #VALUE! | J27: =IF(J25<=0,0,MAX(MIN(J25*收入和税金!$C$12%,财务计划现金流量表!J5+财务计划现金流量表!J16+财务计划现金流量表!J25+财务计划现金流量表!J26+财务计划现金流量表!J27+财务计划现金流量表!J28+财务计划现金流量表!J30-财务计划现金流量表!J32-财务计划现金流量表!J33-财务计划现金流量表!J35+财务计划现金流量表!I37),0)) -> #VALUE! | K27: =IF(K25<=0,0,MAX(MIN(K25*收入和税金!$C$12%,财务计划现金流量表!K5+财务计划现金流量表!K16+财务计划现金流量表!K25+财务计划现金流量表!K26+财务计划现金流量表!K27+财务计划现金流量表!K28+财务计划现金流量表!K30-财务计划现金流量表!K32-财务计划现金流量表!K33-财务计划现金流量表!K35+财务计划现金流量表!J37),0)) -> #VALUE! | ... AC27: =IF(AC25<=0,0,MAX(MIN(AC25*收入和税金!$C$12%,财务计划现金流量表!AC5+财务计划现金流量表!AC16+财务计划现金流量表!AC25+财务计划现金流量表!AC26+财务计划现金流量表!AC27+财务计划现金流量表!AC28+财务计划现金流量表!AC30-财务计划现金流量表!AC32-财务计划现金流量表!AC33-财务计划现金流量表!AC35+财务计划现金流量表!AB37),0)) -> #VALUE!
A28: 20 | B28: 未分配利润（17-18-19） | D28: =D25-D26-D27 -> 0 | E28: =E25-E26-E27 -> #VALUE! | F28: =F25-F26-F27 -> #VALUE! | G28: =G25-G26-G27 -> #VALUE! | H28: =H25-H26-H27 -> #VALUE! | I28: =I25-I26-I27 -> #VALUE! | J28: =J25-J26-J27 -> #VALUE! | K28: =K25-K26-K27 -> #VALUE! | ... AC28: =AC25-AC26-AC27 -> #VALUE!
A29: 21 | B29: 息税前利润 | C29: =SUM(D29:AC29) -> #VALUE! | D29: =D17+总成本费用表!D12 -> 0 | E29: =E17+总成本费用表!E12 -> #VALUE! | F29: =F17+总成本费用表!F12 -> #VALUE! | G29: =G17+总成本费用表!G12 -> #VALUE! | H29: =H17+总成本费用表!H12 -> #VALUE! | I29: =I17+总成本费用表!I12 -> #VALUE! | J29: =J17+总成本费用表!J12 -> #VALUE! | K29: =K17+总成本费用表!K12 -> #VALUE! | ... AC29: =AC17+总成本费用表!AC12 -> #VALUE!
A30: 22 | B30: 息税折旧摊销前利润 | C30: =SUM(D30:AC30) -> #VALUE! | D30: =D29+总成本费用表!D5+总成本费用表!D11 -> 0 | E30: =E29+总成本费用表!E5+总成本费用表!E11 -> #VALUE! | F30: =F29+总成本费用表!F5+总成本费用表!F11 -> #VALUE! | G30: =G29+总成本费用表!G5+总成本费用表!G11 -> #VALUE! | H30: =H29+总成本费用表!H5+总成本费用表!H11 -> #VALUE! | I30: =I29+总成本费用表!I5+总成本费用表!I11 -> #VALUE! | J30: =J29+总成本费用表!J5+总成本费用表!J11 -> #VALUE! | K30: =K29+总成本费用表!K5+总成本费用表!K11 -> #VALUE! | ... AC30: =AC29+总成本费用表!AC5+总成本费用表!AC11 -> #VALUE!
A31: 23 | B31: 累计盈余公积 | D31: =C31+D24 -> 0 | E31: =D31+E24 -> #VALUE! | F31: =E31+F24 -> #VALUE! | G31: =F31+G24 -> #VALUE! | H31: =G31+H24 -> #VALUE! | I31: =H31+I24 -> #VALUE! | J31: =I31+J24 -> #VALUE! | K31: =J31+K24 -> #VALUE! | ... AC31: =AB31+AC24 -> #VALUE!
A32: 辅助行 | B32: 建设期可抵扣增值税 | C32: =SUM(D32:AC32) -> 0 | D32: =IF(基本参数!$B$16="否",基本参数!B15,0) -> 0
B33: 增值税销项税额 | C33: =SUM(D33:AC33) -> #VALUE! | D33: =D9*收入和税金!C16/100+收入和税金!C48-收入和税金!C49+收入和税金!C62-收入和税金!C63 -> 0 | E33: =E9*收入和税金!D16/100+收入和税金!D48-收入和税金!D49+收入和税金!D62-收入和税金!D63 -> #VALUE! | F33: =F9*收入和税金!E16/100+收入和税金!E48-收入和税金!E49+收入和税金!E62-收入和税金!E63 -> #VALUE! | G33: =G9*收入和税金!F16/100+收入和税金!F48-收入和税金!F49+收入和税金!F62-收入和税金!F63 -> #VALUE! | H33: =H9*收入和税金!G16/100+收入和税金!G48-收入和税金!G49+收入和税金!G62-收入和税金!G63 -> #VALUE! | I33: =I9*收入和税金!H16/100+收入和税金!H48-收入和税金!H49+收入和税金!H62-收入和税金!H63 -> #VALUE! | J33: =J9*收入和税金!I16/100+收入和税金!I48-收入和税金!I49+收入和税金!I62-收入和税金!I63 -> #VALUE! | K33: =K9*收入和税金!J16/100+收入和税金!J48-收入和税金!J49+收入和税金!J62-收入和税金!J63 -> #VALUE! | ... AC33: =AC9*收入和税金!AB16/100+收入和税金!AB48-收入和税金!AB49+收入和税金!AB62-收入和税金!AB63 -> #VALUE!
B34: 增值税销项税额累计 | D34: =IF(COLUMN()-3<=基本参数!$B$2,C34+D33,0) -> 0 | E34: =IF(COLUMN()-3<=基本参数!$B$2,D34+E33,0) -> #VALUE! | F34: =IF(COLUMN()-3<=基本参数!$B$2,E34+F33,0) -> #VALUE! | G34: =IF(COLUMN()-3<=基本参数!$B$2,F34+G33,0) -> #VALUE! | H34: =IF(COLUMN()-3<=基本参数!$B$2,G34+H33,0) -> #VALUE! | I34: =IF(COLUMN()-3<=基本参数!$B$2,H34+I33,0) -> #VALUE! | J34: =IF(COLUMN()-3<=基本参数!$B$2,I34+J33,0) -> #VALUE! | K34: =IF(COLUMN()-3<=基本参数!$B$2,J34+K33,0) -> #VALUE! | ... AC34: =IF(COLUMN()-3<=基本参数!$B$2,AB34+AC33,0) -> #VALUE!
B35: 增值税进项税额 | C35: =SUM(D35:AC35) -> 0 | D35: =成本费用!C74 -> 0 | E35: =成本费用!D74 -> 0 | F35: =成本费用!E74 -> 0 | G35: =成本费用!F74 -> 0 | H35: =成本费用!G74 -> 0 | I35: =成本费用!H74 -> 0 | J35: =成本费用!I74 -> 0 | K35: =成本费用!J74 -> 0 | ... AC35: =成本费用!AB74 -> 0
B36: 增值税进项税额累计 | D36: =IF(COLUMN()-3<=基本参数!$B$2,C36+D35,0) -> 0 | E36: =IF(COLUMN()-3<=基本参数!$B$2,D36+E35,0) -> 0 | F36: =IF(COLUMN()-3<=基本参数!$B$2,E36+F35,0) -> 0 | G36: =IF(COLUMN()-3<=基本参数!$B$2,F36+G35,0) -> 0 | H36: =IF(COLUMN()-3<=基本参数!$B$2,G36+H35,0) -> 0 | I36: =IF(COLUMN()-3<=基本参数!$B$2,H36+I35,0) -> 0 | J36: =IF(COLUMN()-3<=基本参数!$B$2,I36+J35,0) -> 0 | K36: =IF(COLUMN()-3<=基本参数!$B$2,J36+K35,0) -> 0 | ... AC36: =IF(COLUMN()-3<=基本参数!$B$2,AB36+AC35,0) -> 0
B37: 应纳增值税额 | C37: =SUM(D37:AC37) -> #VALUE! | D37: =IF(D34-D36<=SUM($D$32:D32),0,MIN(D34-D36-SUM($D$32:D32),D33-D35)) -> 0 | E37: =IF(E34-E36<=SUM($D$32:E32),0,MIN(E34-E36-SUM($D$32:E32),E33-E35)) -> #VALUE! | F37: =IF(F34-F36<=SUM($D$32:F32),0,MIN(F34-F36-SUM($D$32:F32),F33-F35)) -> #VALUE! | G37: =IF(G34-G36<=SUM($D$32:G32),0,MIN(G34-G36-SUM($D$32:G32),G33-G35)) -> #VALUE! | H37: =IF(H34-H36<=SUM($D$32:H32),0,MIN(H34-H36-SUM($D$32:H32),H33-H35)) -> #VALUE! | I37: =IF(I34-I36<=SUM($D$32:I32),0,MIN(I34-I36-SUM($D$32:I32),I33-I35)) -> #VALUE! | J37: =IF(J34-J36<=SUM($D$32:J32),0,MIN(J34-J36-SUM($D$32:J32),J33-J35)) -> #VALUE! | K37: =IF(K34-K36<=SUM($D$32:K32),0,MIN(K34-K36-SUM($D$32:K32),K33-K35)) -> #VALUE! | ... AC37: =IF(AC34-AC36<=SUM($D$32:AC32),0,MIN(AC34-AC36-SUM($D$32:AC32),AC33-AC35)) -> #VALUE!
A38: 辅助行 | B38: 前5年亏损 | I38: =H39+H45 -> #VALUE! | J38: =I39+I45 -> #VALUE! | K38: =J39+J45 -> #VALUE! | L38: =K39+K45 -> #VALUE! | M38: =L39+L45 -> #VALUE! | N38: =M39+M45 -> #VALUE! | O38: =N39+N45 -> #VALUE! | P38: =O39+O45 -> #VALUE! | ... AC38: =AB39+AB45 -> #VALUE!
B39: 前4年亏损 | H39: =G40+G46 -> #VALUE! | I39: =H40+H46 -> #VALUE! | J39: =I40+I46 -> #VALUE! | K39: =J40+J46 -> #VALUE! | L39: =K40+K46 -> #VALUE! | M39: =L40+L46 -> #VALUE! | N39: =M40+M46 -> #VALUE! | O39: =N40+N46 -> #VALUE! | ... AC39: =AB40+AB46 -> #VALUE!
B40: 前3年亏损 | G40: =F41+F47 -> #VALUE! | H40: =G41+G47 -> #VALUE! | I40: =H41+H47 -> #VALUE! | J40: =I41+I47 -> #VALUE! | K40: =J41+J47 -> #VALUE! | L40: =K41+K47 -> #VALUE! | M40: =L41+L47 -> #VALUE! | N40: =M41+M47 -> #VALUE! | ... AC40: =AB41+AB47 -> #VALUE!
B41: 前2年亏损 | F41: =E42+E48 -> #VALUE! | G41: =F42+F48 -> #VALUE! | H41: =G42+G48 -> #VALUE! | I41: =H42+H48 -> #VALUE! | J41: =I42+I48 -> #VALUE! | K41: =J42+J48 -> #VALUE! | L41: =K42+K48 -> #VALUE! | M41: =L42+L48 -> #VALUE! | ... AC41: =AB42+AB48 -> #VALUE!
B42: 前1年亏损 | E42: =MIN(0,D17) -> 0 | F42: =MIN(0,E17) -> #VALUE! | G42: =MIN(0,F17) -> #VALUE! | H42: =MIN(0,G17) -> #VALUE! | I42: =MIN(0,H17) -> #VALUE! | J42: =MIN(0,I17) -> #VALUE! | K42: =MIN(0,J17) -> #VALUE! | L42: =MIN(0,K17) -> #VALUE! | ... AC42: =MIN(0,AB17) -> #VALUE!
B43: 弥补以前年度亏损 | D43: =IF(D17<0,0,MIN(D17,-SUM(D38:D42))) -> 0 | E43: =IF(E17<0,0,MIN(E17,-SUM(E38:E42))) -> #VALUE! | F43: =IF(F17<0,0,MIN(F17,-SUM(F38:F42))) -> #VALUE! | G43: =IF(G17<0,0,MIN(G17,-SUM(G38:G42))) -> #VALUE! | H43: =IF(H17<0,0,MIN(H17,-SUM(H38:H42))) -> #VALUE! | I43: =IF(I17<0,0,MIN(I17,-SUM(I38:I42))) -> #VALUE! | J43: =IF(J17<0,0,MIN(J17,-SUM(J38:J42))) -> #VALUE! | K43: =IF(K17<0,0,MIN(K17,-SUM(K38:K42))) -> #VALUE! | ... AC43: =IF(AC17<0,0,MIN(AC17,-SUM(AC38:AC42))) -> #VALUE!
B44: 弥补前5年 | D44: =IF(D43>0,MIN(-D38,D43),0) -> 0 | E44: =IF(E43>0,MIN(-E38,E43),0) -> #VALUE! | F44: =IF(F43>0,MIN(-F38,F43),0) -> #VALUE! | G44: =IF(G43>0,MIN(-G38,G43),0) -> #VALUE! | H44: =IF(H43>0,MIN(-H38,H43),0) -> #VALUE! | I44: =IF(I43>0,MIN(-I38,I43),0) -> #VALUE! | J44: =IF(J43>0,MIN(-J38,J43),0) -> #VALUE! | K44: =IF(K43>0,MIN(-K38,K43),0) -> #VALUE! | ... AC44: =IF(AC43>0,MIN(-AC38,AC43),0) -> #VALUE!
B45: 弥补前4年 | D45: =IF(D43-D44>0,MIN(D43-D44,-D39),0) -> 0 | E45: =IF(E43-E44>0,MIN(E43-E44,-E39),0) -> #VALUE! | F45: =IF(F43-F44>0,MIN(F43-F44,-F39),0) -> #VALUE! | G45: =IF(G43-G44>0,MIN(G43-G44,-G39),0) -> #VALUE! | H45: =IF(H43-H44>0,MIN(H43-H44,-H39),0) -> #VALUE! | I45: =IF(I43-I44>0,MIN(I43-I44,-I39),0) -> #VALUE! | J45: =IF(J43-J44>0,MIN(J43-J44,-J39),0) -> #VALUE! | K45: =IF(K43-K44>0,MIN(K43-K44,-K39),0) -> #VALUE! | ... AC45: =IF(AC43-AC44>0,MIN(AC43-AC44,-AC39),0) -> #VALUE!
B46: 弥补前3年 | D46: =IF(D43-D44-D45>0,MIN(D43-D44-D45,-D40),0) -> 0 | E46: =IF(E43-E44-E45>0,MIN(E43-E44-E45,-E40),0) -> #VALUE! | F46: =IF(F43-F44-F45>0,MIN(F43-F44-F45,-F40),0) -> #VALUE! | G46: =IF(G43-G44-G45>0,MIN(G43-G44-G45,-G40),0) -> #VALUE! | H46: =IF(H43-H44-H45>0,MIN(H43-H44-H45,-H40),0) -> #VALUE! | I46: =IF(I43-I44-I45>0,MIN(I43-I44-I45,-I40),0) -> #VALUE! | J46: =IF(J43-J44-J45>0,MIN(J43-J44-J45,-J40),0) -> #VALUE! | K46: =IF(K43-K44-K45>0,MIN(K43-K44-K45,-K40),0) -> #VALUE! | ... AC46: =IF(AC43-AC44-AC45>0,MIN(AC43-AC44-AC45,-AC40),0) -> #VALUE!
B47: 弥补前2年 | D47: =IF(D43-D44-D45-D46>0,MIN(D43-D44-D45-D46,-D41),0) -> 0 | E47: =IF(E43-E44-E45-E46>0,MIN(E43-E44-E45-E46,-E41),0) -> #VALUE! | F47: =IF(F43-F44-F45-F46>0,MIN(F43-F44-F45-F46,-F41),0) -> #VALUE! | G47: =IF(G43-G44-G45-G46>0,MIN(G43-G44-G45-G46,-G41),0) -> #VALUE! | H47: =IF(H43-H44-H45-H46>0,MIN(H43-H44-H45-H46,-H41),0) -> #VALUE! | I47: =IF(I43-I44-I45-I46>0,MIN(I43-I44-I45-I46,-I41),0) -> #VALUE! | J47: =IF(J43-J44-J45-J46>0,MIN(J43-J44-J45-J46,-J41),0) -> #VALUE! | K47: =IF(K43-K44-K45-K46>0,MIN(K43-K44-K45-K46,-K41),0) -> #VALUE! | ... AC47: =IF(AC43-AC44-AC45-AC46>0,MIN(AC43-AC44-AC45-AC46,-AC41),0) -> #VALUE!
B48: 弥补前1年 | D48: =IF(D43-D44-D45-D46-D47>0,MIN(D43-D44-D45-D46-D47,-D42),0) -> 0 | E48: =IF(E43-E44-E45-E46-E47>0,MIN(E43-E44-E45-E46-E47,-E42),0) -> #VALUE! | F48: =IF(F43-F44-F45-F46-F47>0,MIN(F43-F44-F45-F46-F47,-F42),0) -> #VALUE! | G48: =IF(G43-G44-G45-G46-G47>0,MIN(G43-G44-G45-G46-G47,-G42),0) -> #VALUE! | H48: =IF(H43-H44-H45-H46-H47>0,MIN(H43-H44-H45-H46-H47,-H42),0) -> #VALUE! | I48: =IF(I43-I44-I45-I46-I47>0,MIN(I43-I44-I45-I46-I47,-I42),0) -> #VALUE! | J48: =IF(J43-J44-J45-J46-J47>0,MIN(J43-J44-J45-J46-J47,-J42),0) -> #VALUE! | K48: =IF(K43-K44-K45-K46-K47>0,MIN(K43-K44-K45-K46-K47,-K42),0) -> #VALUE! | ... AC48: =IF(AC43-AC44-AC45-AC46-AC47>0,MIN(AC43-AC44-AC45-AC46-AC47,-AC42),0) -> #VALUE!

Sheet 财务计划现金流量表
A1: 财务计划现金流量表
A2: 人民币单位：万元
A3: 序号 | B3: 项目 | C3: 合计 | D3: 建设期 | E3: 运行期
D4: 第1年 | E4: 第2年 | F4: 第3年 | G4: 第4年 | H4: 第5年 | I4: 第6年 | J4: 第7年 | K4: 第8年 | L4: 第9年 | M4: 第10年 | N4: 第11年 | O4: 第12年 | P4: 第13年 | Q4: 第14年 | R4: 第15年 | S4: 第16年 | T4: 第17年 | U4: 第18年 | V4: 第19年 | W4: 第20年 | X4: 第21年 | Y4: 第22年 | Z4: 第23年 | AA4: 第24年 | AB4: 第25年 | AC4: 第26年
A5: 1 | B5: 经营活动净现金流量 | C5: =SUM(D5:AC5) -> #VALUE! | D5: =D6-D10 -> 0 | E5: =E6-E10 -> #VALUE! | F5: =F6-F10 -> #VALUE! | G5: =G6-G10 -> #VALUE! | H5: =H6-H10 -> #VALUE! | I5: =I6-I10 -> #VALUE! | J5: =J6-J10 -> #VALUE! | K5: =K6-K10 -> #VALUE! | ... AC5: =AC6-AC10 -> #VALUE!
A6: 1.1 | B6: 现金流入 | C6: =SUM(D6:AC6) -> #VALUE! | D6: =SUM(D7:D9) -> 0 | E6: =SUM(E7:E9) -> #VALUE! | F6: =SUM(F7:F9) -> #VALUE! | G6: =SUM(G7:G9) -> #VALUE! | H6: =SUM(H7:H9) -> #VALUE! | I6: =SUM(I7:I9) -> #VALUE! | J6: =SUM(J7:J9) -> #VALUE! | K6: =SUM(K7:K9) -> #VALUE! | ... AC6: =SUM(AC7:AC9) -> #VALUE!
A7: 1.1.1 | B7: 销售收入 | C7: =SUM(D7:AC7) -> #VALUE! | D7: =利润与利润分配表!D9*(1+收入和税金!C16%) -> 0 | E7: =利润与利润分配表!E9*(1+收入和税金!D16%) -> #VALUE! | F7: =利润与利润分配表!F9*(1+收入和税金!E16%) -> #VALUE! | G7: =利润与利润分配表!G9*(1+收入和税金!F16%) -> #VALUE! | H7: =利润与利润分配表!H9*(1+收入和税金!G16%) -> #VALUE! | I7: =利润与利润分配表!I9*(1+收入和税金!H16%) -> #VALUE! | J7: =利润与利润分配表!J9*(1+收入和税金!I16%) -> #VALUE! | K7: =利润与利润分配表!K9*(1+收入和税金!J16%) -> #VALUE! | ... AC7: =利润与利润分配表!AC9*(1+收入和税金!AB16%) -> #VALUE!
A8: 1.1.3 | B8: 其他收入（应税) | C8: =SUM(D8:AC8) -> 0 | D8: =收入和税金!C48 -> 0 | E8: =收入和税金!D48 -> 0 | F8: =收入和税金!E48 -> 0 | G8: =收入和税金!F48 -> 0 | H8: =收入和税金!G48 -> 0 | I8: =收入和税金!H48 -> 0 | J8: =收入和税金!I48 -> 0 | K8: =收入和税金!J48 -> 0 | ... AC8: =收入和税金!AB48 -> 0
A9: 1.1.4 | B9: 其他收入(免税) | C9: =SUM(D9:AC9) -> 0 | D9: =收入和税金!C62 -> 0 | E9: =收入和税金!D62 -> 0 | F9: =收入和税金!E62 -> 0 | G9: =收入和税金!F62 -> 0 | H9: =收入和税金!G62 -> 0 | I9: =收入和税金!H62 -> 0 | J9: =收入和税金!I62 -> 0 | K9: =收入和税金!J62 -> 0 | ... AC9: =收入和税金!AB62 -> 0
A10: 1.2 | B10: 现金流出 | C10: =SUM(D10:AC10) -> #REF! | D10: =SUM(D11:D15) -> 0 | E10: =SUM(E11:E15) -> #REF! | F10: =SUM(F11:F15) -> #REF! | G10: =SUM(G11:G15) -> #REF! | H10: =SUM(H11:H15) -> #REF! | I10: =SUM(I11:I15) -> #REF! | J10: =SUM(J11:J15) -> #REF! | K10: =SUM(K11:K15) -> #REF! | ... AC10: =SUM(AC11:AC15) -> #REF!
A11: 1.2.1 | B11: 经营成本 | C11: =SUM(D11:AC11) -> #REF! | D11: =总成本费用表!D21 -> 0 | E11: =总成本费用表!E21 -> #REF! | F11: =总成本费用表!F21 -> #REF! | G11: =总成本费用表!G21 -> #REF! | H11: =总成本费用表!H21 -> #REF! | I11: =总成本费用表!I21 -> #REF! | J11: =总成本费用表!J21 -> #REF! | K11: =总成本费用表!K21 -> #REF! | ... AC11: =总成本费用表!AC21 -> #REF!
A12: 1.2.3 | B12: 销售税金附加 | C12: =SUM(D12:AC12) -> #VALUE! | D12: =利润与利润分配表!D12 -> 0 | E12: =利润与利润分配表!E12 -> #VALUE! | F12: =利润与利润分配表!F12 -> #VALUE! | G12: =利润与利润分配表!G12 -> #VALUE! | H12: =利润与利润分配表!H12 -> #VALUE! | I12: =利润与利润分配表!I12 -> #VALUE! | J12: =利润与利润分配表!J12 -> #VALUE! | K12: =利润与利润分配表!K12 -> #VALUE! | ... AC12: =利润与利润分配表!AC12 -> #VALUE!
A13: 1.2.4 | B13: 实缴增值税 | C13: =SUM(D13:AC13) -> #VALUE! | D13: =IF(利润与利润分配表!D37<0,0-利润与利润分配表!D16,利润与利润分配表!D37-利润与利润分配表!D16) -> 0 | E13: =IF(利润与利润分配表!E37<0,0-利润与利润分配表!E16,利润与利润分配表!E37-利润与利润分配表!E16) -> #VALUE! | F13: =IF(利润与利润分配表!F37<0,0-利润与利润分配表!F16,利润与利润分配表!F37-利润与利润分配表!F16) -> #VALUE! | G13: =IF(利润与利润分配表!G37<0,0-利润与利润分配表!G16,利润与利润分配表!G37-利润与利润分配表!G16) -> #VALUE! | H13: =IF(利润与利润分配表!H37<0,0-利润与利润分配表!H16,利润与利润分配表!H37-利润与利润分配表!H16) -> #VALUE! | I13: =IF(利润与利润分配表!I37<0,0-利润与利润分配表!I16,利润与利润分配表!I37-利润与利润分配表!I16) -> #VALUE! | J13: =IF(利润与利润分配表!J37<0,0-利润与利润分配表!J16,利润与利润分配表!J37-利润与利润分配表!J16) -> #VALUE! | K13: =IF(利润与利润分配表!K37<0,0-利润与利润分配表!K16,利润与利润分配表!K37-利润与利润分配表!K16) -> #VALUE! | ... AC13: =IF(利润与利润分配表!AC37<0,0-利润与利润分配表!AC16,利润与利润分配表!AC37-利润与利润分配表!AC16) -> #VALUE!
A14: 1.2.5 | B14: 进项税 | C14: =SUM(D14:AC14) -> 0 | D14: =成本费用!C74 -> 0 | E14: =成本费用!D74 -> 0 | F14: =成本费用!E74 -> 0 | G14: =成本费用!F74 -> 0 | H14: =成本费用!G74 -> 0 | I14: =成本费用!H74 -> 0 | J14: =成本费用!I74 -> 0 | K14: =成本费用!J74 -> 0 | ... AC14: =成本费用!AB74 -> 0
A15: 1.2.6 | B15: 所得税 | C15: =SUM(D15:AC15) -> #VALUE! | D15: =利润与利润分配表!D20 -> 0 | E15: =利润与利润分配表!E20 -> #VALUE! | F15: =利润与利润分配表!F20 -> #VALUE! | G15: =利润与利润分配表!G20 -> #VALUE! | H15: =利润与利润分配表!H20 -> #VALUE! | I15: =利润与利润分配表!I20 -> #VALUE! | J15: =利润与利润分配表!J20 -> #VALUE! | K15: =利润与利润分配表!K20 -> #VALUE! | ... AC15: =利润与利润分配表!AC20 -> #VALUE!
A16: 2 | B16: 投资活动净现金流量 | C16: =SUM(D16:AC16) -> 0 | D16: =D17-D20 -> 0 | E16: =E17-E20 -> 0 | F16: =F17-F20 -> 0 | G16: =G17-G20 -> 0 | H16: =H17-H20 -> 0 | I16: =I17-I20 -> 0 | J16: =J17-J20 -> 0 | K16: =K17-K20 -> 0 | ... AC16: =AC17-AC20 -> 0
A17: 2.1 | B17: 现金流入 | C17: =SUM(D17:AC17) -> 0 | D17: =D18+D19 -> 0 | E17: =E18+E19 -> 0 | F17: =F18+F19 -> 0 | G17: =G18+G19 -> 0 | H17: =H18+H19 -> 0 | I17: =I18+I19 -> 0 | J17: =J18+J19 -> 0 | K17: =K18+K19 -> 0 | ... AC17: =AC18+AC19 -> 0
A18: 2.1.1 | B18: 回收固定资产余值 | C18: =SUM(D18:AC18) -> 0 | D18: 0 | E18: =IF(COLUMN()-3=基本参数!$B$2,成本费用!D89*成本费用!$C$3/100,0) -> 0 | F18: =IF(COLUMN()-3=基本参数!$B$2,成本费用!E89*成本费用!$C$3/100,0) -> 0 | G18: =IF(COLUMN()-3=基本参数!$B$2,成本费用!F89*成本费用!$C$3/100,0) -> 0 | H18: =IF(COLUMN()-3=基本参数!$B$2,成本费用!G89*成本费用!$C$3/100,0) -> 0 | I18: =IF(COLUMN()-3=基本参数!$B$2,成本费用!H89*成本费用!$C$3/100,0) -> 0 | J18: =IF(COLUMN()-3=基本参数!$B$2,成本费用!I89*成本费用!$C$3/100,0) -> 0 | K18: =IF(COLUMN()-3=基本参数!$B$2,成本费用!J89*成本费用!$C$3/100,0) -> 0 | L18: =IF(COLUMN()-3=基本参数!$B$2,成本费用!K89*成本费用!$C$3/100,0) -> 0 | ... AC18: =IF(COLUMN()-3=基本参数!$B$2,成本费用!AB89*成本费用!$C$3/100,0) -> 0
A19: 2.1.2 | B19: 回收流动资金 | C19: =SUM(D19:AC19) -> 0 | D19: 0 | E19: =IF(COLUMN()-3=基本参数!$B$2,投资计划与资金筹措表!$C$8,0) -> 0 | F19: =IF(COLUMN()-3=基本参数!$B$2,投资计划与资金筹措表!$C$8,0) -> 0 | G19: =IF(COLUMN()-3=基本参数!$B$2,投资计划与资金筹措表!$C$8,0) -> 0 | H19: =IF(COLUMN()-3=基本参数!$B$2,投资计划与资金筹措表!$C$8,0) -> 0 | I19: =IF(COLUMN()-3=基本参数!$B$2,投资计划与资金筹措表!$C$8,0) -> 0 | J19: =IF(COLUMN()-3=基本参数!$B$2,投资计划与资金筹措表!$C$8,0) -> 0 | K19: =IF(COLUMN()-3=基本参数!$B$2,投资计划与资金筹措表!$C$8,0) -> 0 | L19: =IF(COLUMN()-3=基本参数!$B$2,投资计划与资金筹措表!$C$8,0) -> 0 | ... AC19: =IF(COLUMN()-3=基本参数!$B$2,投资计划与资金筹措表!$C$8,0) -> 0
A20: 2.2 | B20: 现金流出 | C20: =SUM(D20:AC20) -> 0 | D20: =D21+D22 -> 0 | E20: =E21+E22 -> 0 | F20: =F21+F22 -> 0 | G20: =G21+G22 -> 0 | H20: =H21+H22 -> 0 | I20: =I21+I22 -> 0 | J20: =J21+J22 -> 0 | K20: =K21+K22 -> 0 | ... AC20: =AC21+AC22 -> 0
A21: 2.2.1 | B21: 建设投资 | C21: =SUM(D21:AC21) -> 0 | D21: =投资计划与资金筹措表!D6+投资计划与资金筹措表!D7 -> 0 | E21: =投资计划与资金筹措表!E6+投资计划与资金筹措表!E7 -> 0 | F21: =投资计划与资金筹措表!F6+投资计划与资金筹措表!F7 -> 0 | G21: =投资计划与资金筹措表!G6+投资计划与资金筹措表!G7 -> 0 | H21: =投资计划与资金筹措表!H6+投资计划与资金筹措表!H7 -> 0 | I21: =投资计划与资金筹措表!I6+投资计划与资金筹措表!I7 -> 0 | J21: =投资计划与资金筹措表!J6+投资计划与资金筹措表!J7 -> 0 | K21: =投资计划与资金筹措表!K6+投资计划与资金筹措表!K7 -> 0 | ... AC21: =投资计划与资金筹措表!AC6+投资计划与资金筹措表!AC7 -> 0
A22: 2.2.2 | B22: 流动资金 | C22: =SUM(D22:AC22) -> 0 | D22: =投资计划与资金筹措表!D8 -> 0 | E22: =投资计划与资金筹措表!E8 -> 0 | F22: 0 | G22: 0 | H22: 0 | I22: 0 | J22: 0 | K22: 0 | L22: 0 | M22: 0 | N22: 0 | O22: 0 | P22: 0 | Q22: 0 | R22: 0 | S22: 0 | T22: 0 | U22: 0 | V22: 0 | W22: 0 | X22: 0 | Y22: 0 | Z22: 0 | AA22: 0 | AB22: 0 | AC22: 0
A23: 3 | B23: 筹资活动净现金流量 | C23: =SUM(D23:AC23) -> #VALUE! | D23: =D24-D31 -> 0 | E23: =E24-E31 -> #VALUE! | F23: =F24-F31 -> #VALUE! | G23: =G24-G31 -> #VALUE! | H23: =H24-H31 -> #VALUE! | I23: =I24-I31 -> #VALUE! | J23: =J24-J31 -> #VALUE! | K23: =K24-K31 -> #VALUE! | ... AC23: =AC24-AC31 -> #VALUE!
A24: 3.1 | B24: 现金流入 | C24: =SUM(D24:AC24) -> #VALUE! | D24: =SUM(D25:D30) -> 0 | E24: =SUM(E25:E30) -> #VALUE! | F24: =SUM(F25:F30) -> #VALUE! | G24: =SUM(G25:G30) -> #VALUE! | H24: =SUM(H25:H30) -> #VALUE! | I24: =SUM(I25:I30) -> #VALUE! | J24: =SUM(J25:J30) -> #VALUE! | K24: =SUM(K25:K30) -> #VALUE! | ... AC24: =SUM(AC25:AC30) -> #VALUE!
A25: 3.1.1 | B25: 项目资本金投入 | C25: =SUM(D25:AC25) -> 0 | D25: =投资计划与资金筹措表!D10 -> 0 | E25: =投资计划与资金筹措表!E10 -> 0 | F25: 0 | G25: 0 | H25: 0 | I25: 0 | J25: 0 | K25: 0 | L25: 0 | M25: 0 | N25: 0 | O25: 0 | P25: 0 | Q25: 0 | R25: 0 | S25: 0 | T25: 0 | U25: 0 | V25: 0 | W25: 0 | X25: 0 | Y25: 0 | Z25: 0 | AA25: 0 | AB25: 0 | AC25: 0
A26: 3.1.2 | B26: 建设投资借款 | C26: =SUM(D26:AC26) -> 0 | D26: =投资计划与资金筹措表!D13 -> 0 | E26: =投资计划与资金筹措表!E13 -> 0 | F26: =投资计划与资金筹措表!F13 -> 0 | G26: =投资计划与资金筹措表!G13 -> 0 | H26: =投资计划与资金筹措表!H13 -> 0 | I26: =投资计划与资金筹措表!I13 -> 0 | J26: =投资计划与资金筹措表!J13 -> 0 | K26: =投资计划与资金筹措表!K13 -> 0 | ... AC26: =投资计划与资金筹措表!AC13 -> 0
A27: 3.1.3 | B27: 流动资金借款 | C27: =SUM(D27:AC27) -> 0 | D27: =投资计划与资金筹措表!D17 -> 0 | E27: =投资计划与资金筹措表!E17 -> 0 | F27: 0 | G27: 0 | H27: 0 | I27: 0 | J27: 0 | K27: 0 | L27: 0 | M27: 0 | N27: 0 | O27: 0 | P27: 0 | Q27: 0 | R27: 0 | S27: 0 | T27: 0 | U27: 0 | V27: 0 | W27: 0 | X27: 0 | Y27: 0 | Z27: 0 | AA27: 0 | AB27: 0 | AC27: 0
A28: 3.1.4 | B28: 债券 | C28: =SUM(D28:AC28) -> 0 | D28: 0 | E28: 0 | F28: 0 | G28: 0 | H28: 0 | I28: 0 | J28: 0 | K28: 0 | L28: 0 | M28: 0 | N28: 0 | O28: 0 | P28: 0 | Q28: 0 | R28: 0 | S28: 0 | T28: 0 | U28: 0 | V28: 0 | W28: 0 | X28: 0 | Y28: 0 | Z28: 0 | AA28: 0 | AB28: 0 | AC28: 0
A29: 3.1.5 | B29: 短期借款 | C29: =SUM(D29:AC29) -> #VALUE! | D29: =借款还本付息计划表!D17 -> 0 | E29: =借款还本付息计划表!E17 -> #VALUE! | F29: =借款还本付息计划表!F17 -> #VALUE! | G29: =借款还本付息计划表!G17 -> #VALUE! | H29: =借款还本付息计划表!H17 -> #VALUE! | I29: =借款还本付息计划表!I17 -> #VALUE! | J29: =借款还本付息计划表!J17 -> #VALUE! | K29: =借款还本付息计划表!K17 -> #VALUE! | ... AC29: =借款还本付息计划表!AC17 -> #VALUE!
A30: 3.1.6 | B30: 其他流入 | C30: =SUM(D30:AC30) -> 0 | D30: 0 | E30: 0 | F30: 0 | G30: 0 | H30: 0 | I30: 0 | J30: 0 | K30: 0 | L30: 0 | M30: 0 | N30: 0 | O30: 0 | P30: 0 | Q30: 0 | R30: 0 | S30: 0 | T30: 0 | U30: 0 | V30: 0 | W30: 0 | X30: 0 | Y30: 0 | Z30: 0 | AA30: 0 | AB30: 0 | AC30: 0
A31: 3.2 | B31: 现金流出 | C31: =SUM(D31:AC31) -> #VALUE! | D31: =SUM(D32:D35) -> 0 | E31: =SUM(E32:E35) -> #VALUE! | F31: =SUM(F32:F35) -> #VALUE! | G31: =SUM(G32:G35) -> #VALUE! | H31: =SUM(H32:H35) -> #VALUE! | I31: =SUM(I32:I35) -> #VALUE! | J31: =SUM(J32:J35) -> #VALUE! | K31: =SUM(K32:K35) -> #VALUE! | ... AC31: =SUM(AC32:AC35) -> #VALUE!
A32: 3.2.1 | B32: 各种利息支出 | C32: =SUM(D32:AC32) -> #VALUE! | D32: =总成本费用表!D12 -> 0 | E32: =总成本费用表!E12 -> 0 | F32: =总成本费用表!F12 -> #VALUE! | G32: =总成本费用表!G12 -> #VALUE! | H32: =总成本费用表!H12 -> #VALUE! | I32: =总成本费用表!I12 -> #VALUE! | J32: =总成本费用表!J12 -> #VALUE! | K32: =总成本费用表!K12 -> #VALUE! | ... AC32: =总成本费用表!AC12 -> #VALUE!
A33: 3.2.2 | B33: 偿还债务本金 | C33: =SUM(D33:AC33) -> #VALUE! | D33: =借款还本付息计划表!D8+借款还本付息计划表!D14+借款还本付息计划表!D18 -> 0 | E33: =借款还本付息计划表!E8+借款还本付息计划表!E14+借款还本付息计划表!E18 -> #VALUE! | F33: =借款还本付息计划表!F8+借款还本付息计划表!F14+借款还本付息计划表!F18 -> #VALUE! | G33: =借款还本付息计划表!G8+借款还本付息计划表!G14+借款还本付息计划表!G18 -> #VALUE! | H33: =借款还本付息计划表!H8+借款还本付息计划表!H14+借款还本付息计划表!H18 -> #VALUE! | I33: =借款还本付息计划表!I8+借款还本付息计划表!I14+借款还本付息计划表!I18 -> #VALUE! | J33: =借款还本付息计划表!J8+借款还本付息计划表!J14+借款还本付息计划表!J18 -> #VALUE! | K33: =借款还本付息计划表!K8+借款还本付息计划表!K14+借款还本付息计划表!K18 -> #VALUE! | ... AC33: =借款还本付息计划表!AC8+借款还本付息计划表!AC14+借款还本付息计划表!AC18 -> #VALUE!
A34: 3.2.3 | B34: 应付利润 | C34: =SUM(D34:AC34) -> #VALUE! | D34: =利润与利润分配表!D27 -> 0 | E34: =利润与利润分配表!E27 -> #VALUE! | F34: =利润与利润分配表!F27 -> #VALUE! | G34: =利润与利润分配表!G27 -> #VALUE! | H34: =利润与利润分配表!H27 -> #VALUE! | I34: =利润与利润分配表!I27 -> #VALUE! | J34: =利润与利润分配表!J27 -> #VALUE! | K34: =利润与利润分配表!K27 -> #VALUE! | ... AC34: =利润与利润分配表!AC27 -> #VALUE!
A35: 3.2.4 | B35: 其他流出 | C35: =SUM(D35:AC35) -> 0 | D35: 0 | E35: 0 | F35: 0 | G35: 0 | H35: 0 | I35: 0 | J35: 0 | K35: 0 | L35: 0 | M35: 0 | N35: 0 | O35: 0 | P35: 0 | Q35: 0 | R35: 0 | S35: 0 | T35: 0 | U35: 0 | V35: 0 | W35: 0 | X35: 0 | Y35: 0 | Z35: 0 | AA35: 0 | AB35: 0 | AC35: 0
A36: 4 | B36: 净现金流量 | C36: =SUM(D36:AC36) -> #VALUE! | D36: =D5+D16+D23 -> 0 | E36: =E5+E16+E23 -> #VALUE! | F36: =F5+F16+F23 -> #VALUE! | G36: =G5+G16+G23 -> #VALUE! | H36: =H5+H16+H23 -> #VALUE! | I36: =I5+I16+I23 -> #VALUE! | J36: =J5+J16+J23 -> #VALUE! | K36: =K5+K16+K23 -> #VALUE! | ... AC36: =AC5+AC16+AC23 -> #VALUE!
A37: 5 | B37: 累计盈余资金 | D37: =C37+D36 -> 0 | E37: =D37+E36 -> #VALUE! | F37: =E37+F36 -> #VALUE! | G37: =F37+G36 -> #VALUE! | H37: =G37+H36 -> #VALUE! | I37: =H37+I36 -> #VALUE! | J37: =I37+J36 -> #VALUE! | K37: =J37+K36 -> #VALUE! | ... AC37: =AB37+AC36 -> #VALUE!
A38: 辅助行 | B38: 应还本息合计 | D38: =借款还本付息计划表!D9+借款还本付息计划表!D8+借款还本付息计划表!D19+借款还本付息计划表!D13 -> 0 | E38: =借款还本付息计划表!E9+借款还本付息计划表!E8+借款还本付息计划表!E19+借款还本付息计划表!E13 -> 0 | F38: =借款还本付息计划表!F9+借款还本付息计划表!F8+借款还本付息计划表!F19+借款还本付息计划表!F13 -> #VALUE! | G38: =借款还本付息计划表!G9+借款还本付息计划表!G8+借款还本付息计划表!G19+借款还本付息计划表!G13 -> #VALUE! | H38: =借款还本付息计划表!H9+借款还本付息计划表!H8+借款还本付息计划表!H19+借款还本付息计划表!H13 -> #VALUE! | I38: =借款还本付息计划表!I9+借款还本付息计划表!I8+借款还本付息计划表!I19+借款还本付息计划表!I13 -> #VALUE! | J38: =借款还本付息计划表!J9+借款还本付息计划表!J8+借款还本付息计划表!J19+借款还本付息计划表!J13 -> #VALUE! | K38: =借款还本付息计划表!K9+借款还本付息计划表!K8+借款还本付息计划表!K19+借款还本付息计划表!K13 -> #VALUE! | ... AC38: =借款还本付息计划表!AC9+借款还本付息计划表!AC8+借款还本付息计划表!AC19+借款还本付息计划表!AC13 -> #VALUE!
B39: 可供偿债现金 | D39: =D5+D16+D25+D26+D27+D28+D30+C37 -> 0 | E39: =E5+E16+E25+E26+E27+E28+E30+D37 -> #VALUE! | F39: =F5+F16+F25+F26+F27+F28+F30+E37 -> #VALUE! | G39: =G5+G16+G25+G26+G27+G28+G30+F37 -> #VALUE! | H39: =H5+H16+H25+H26+H27+H28+H30+G37 -> #VALUE! | I39: =I5+I16+I25+I26+I27+I28+I30+H37 -> #VALUE! | J39: =J5+J16+J25+J26+J27+J28+J30+I37 -> #VALUE! | K39: =K5+K16+K25+K26+K27+K28+K30+J37 -> #VALUE! | ... AC39: =AC5+AC16+AC25+AC26+AC27+AC28+AC30+AB37 -> #VALUE!
B40: 偿债后余额 | D40: =IF(D39-D38>0,0,(D38-D39)) -> 0 | E40: =IF(E39-E38>0,0,(E38-E39)) -> #VALUE! | F40: =IF(F39-F38>0,0,(F38-F39)) -> #VALUE! | G40: =IF(G39-G38>0,0,(G38-G39)) -> #VALUE! | H40: =IF(H39-H38>0,0,(H38-H39)) -> #VALUE! | I40: =IF(I39-I38>0,0,(I38-I39)) -> #VALUE! | J40: =IF(J39-J38>0,0,(J38-J39)) -> #VALUE! | K40: =IF(K39-K38>0,0,(K38-K39)) -> #VALUE! | ... AC40: =IF(AC39-AC38>0,0,(AC38-AC39)) -> #VALUE!

Sheet 项目投资现金流量表
A1: 项目投资现金流量表
A2: 人民币单位：万元
A3: 序号 | B3: 项目 | C3: 合计 | D3: 建设期 | E3: 运行期
D4: 第1年 | E4: 第2年 | F4: 第3年 | G4: 第4年 | H4: 第5年 | I4: 第6年 | J4: 第7年 | K4: 第8年 | L4: 第9年 | M4: 第10年 | N4: 第11年 | O4: 第12年 | P4: 第13年 | Q4: 第14年 | R4: 第15年 | S4: 第16年 | T4: 第17年 | U4: 第18年 | V4: 第19年 | W4: 第20年 | X4: 第21年 | Y4: 第22年 | Z4: 第23年 | AA4: 第24年 | AB4: 第25年 | AC4: 第26年
A5: 1 | B5: 现金流入 | C5: =SUM(D5:AC5) -> #VALUE! | D5: =SUM(D6:D10) -> 0 | E5: =SUM(E6:E10) -> #VALUE! | F5: =SUM(F6:F10) -> #VALUE! | G5: =SUM(G6:G10) -> #VALUE! | H5: =SUM(H6:H10) -> #VALUE! | I5: =SUM(I6:I10) -> #VALUE! | J5: =SUM(J6:J10) -> #VALUE! | K5: =SUM(K6:K10) -> #VALUE! | ... AC5: =SUM(AC6:AC10) -> #VALUE!
A6: 1.1 | B6: 销售收入 | C6: =SUM(D6:AC6) -> #VALUE! | D6: =财务计划现金流量表!D7 -> 0 | E6: =财务计划现金流量表!E7 -> #VALUE! | F6: =财务计划现金流量表!F7 -> #VALUE! | G6: =财务计划现金流量表!G7 -> #VALUE! | H6: =财务计划现金流量表!H7 -> #VALUE! | I6: =财务计划现金流量表!I7 -> #VALUE! | J6: =财务计划现金流量表!J7 -> #VALUE! | K6: =财务计划现金流量表!K7 -> #VALUE! | ... AC6: =财务计划现金流量表!AC7 -> #VALUE!
A7: 1.2 | B7: 其他收入(应税) | C7: =SUM(D7:AC7) -> 0 | D7: =财务计划现金流量表!D8 -> 0 | E7: =财务计划现金流量表!E8 -> 0 | F7: =财务计划现金流量表!F8 -> 0 | G7: =财务计划现金流量表!G8 -> 0 | H7: =财务计划现金流量表!H8 -> 0 | I7: =财务计划现金流量表!I8 -> 0 | J7: =财务计划现金流量表!J8 -> 0 | K7: =财务计划现金流量表!K8 -> 0 | ... AC7: =财务计划现金流量表!AC8 -> 0
A8: 1.3 | B8: 其他收入(免税) | C8: =SUM(D8:AC8) -> 0 | D8: =财务计划现金流量表!D9 -> 0 | E8: =财务计划现金流量表!E9 -> 0 | F8: =财务计划现金流量表!F9 -> 0 | G8: =财务计划现金流量表!G9 -> 0 | H8: =财务计划现金流量表!H9 -> 0 | I8: =财务计划现金流量表!I9 -> 0 | J8: =财务计划现金流量表!J9 -> 0 | K8: =财务计划现金流量表!K9 -> 0 | ... AC8: =财务计划现金流量表!AC9 -> 0
A9: 1.4 | B9: 回收固定资产余值 | C9: =SUM(D9:AC9) -> 0 | D9: =财务计划现金流量表!D18 -> 0 | E9: =财务计划现金流量表!E18 -> 0 | F9: =财务计划现金流量表!F18 -> 0 | G9: =财务计划现金流量表!G18 -> 0 | H9: =财务计划现金流量表!H18 -> 0 | I9: =财务计划现金流量表!I18 -> 0 | J9: =财务计划现金流量表!J18 -> 0 | K9: =财务计划现金流量表!K18 -> 0 | ... AC9: =财务计划现金流量表!AC18 -> 0
A10: 1.5 | B10: 回收流动资金 | C10: =SUM(D10:AC10) -> 0 | D10: =财务计划现金流量表!D19 -> 0 | E10: =财务计划现金流量表!E19 -> 0 | F10: =财务计划现金流量表!F19 -> 0 | G10: =财务计划现金流量表!G19 -> 0 | H10: =财务计划现金流量表!H19 -> 0 | I10: =财务计划现金流量表!I19 -> 0 | J10: =财务计划现金流量表!J19 -> 0 | K10: =财务计划现金流量表!K19 -> 0 | ... AC10: =财务计划现金流量表!AC19 -> 0
A11: 2 | B11: 现金流出 | C11: =SUM(D11:AC11) -> #REF! | D11: =SUM(D12:D17) -> 0 | E11: =SUM(E12:E17) -> #REF! | F11: =SUM(F12:F17) -> #REF! | G11: =SUM(G12:G17) -> #REF! | H11: =SUM(H12:H17) -> #REF! | I11: =SUM(I12:I17) -> #REF! | J11: =SUM(J12:J17) -> #REF! | K11: =SUM(K12:K17) -> #REF! | ... AC11: =SUM(AC12:AC17) -> #REF!
A12: 2.1 | B12: 建设投资 | C12: =SUM(D12:AC12) -> 0 | D12: =财务计划现金流量表!D21 -> 0 | E12: =财务计划现金流量表!E21 -> 0 | F12: =财务计划现金流量表!F21 -> 0 | G12: =财务计划现金流量表!G21 -> 0 | H12: =财务计划现金流量表!H21 -> 0 | I12: =财务计划现金流量表!I21 -> 0 | J12: =财务计划现金流量表!J21 -> 0 | K12: =财务计划现金流量表!K21 -> 0 | ... AC12: =财务计划现金流量表!AC21 -> 0
A13: 2.2 | B13: 流动资金 | C13: =SUM(D13:AC13) -> 0 | D13: =财务计划现金流量表!D22 -> 0 | E13: =财务计划现金流量表!E22 -> 0 | F13: =财务计划现金流量表!F22 -> 0 | G13: =财务计划现金流量表!G22 -> 0 | H13: =财务计划现金流量表!H22 -> 0 | I13: =财务计划现金流量表!I22 -> 0 | J13: =财务计划现金流量表!J22 -> 0 | K13: =财务计划现金流量表!K22 -> 0 | ... AC13: =财务计划现金流量表!AC22 -> 0
A14: 2.3 | B14: 经营成本 | C14: =SUM(D14:AC14) -> #REF! | D14: =总成本费用表!D21 -> 0 | E14: =总成本费用表!E21 -> #REF! | F14: =总成本费用表!F21 -> #REF! | G14: =总成本费用表!G21 -> #REF! | H14: =总成本费用表!H21 -> #REF! | I14: =总成本费用表!I21 -> #REF! | J14: =总成本费用表!J21 -> #REF! | K14: =总成本费用表!K21 -> #REF! | ... AC14: =总成本费用表!AC21 -> #REF!
A15: 2.4 | B15: 实缴增值税 | C15: =SUM(D15:AC15) -> #VALUE! | D15: =财务计划现金流量表!D13 -> 0 | E15: =财务计划现金流量表!E13 -> #VALUE! | F15: =财务计划现金流量表!F13 -> #VALUE! | G15: =财务计划现金流量表!G13 -> #VALUE! | H15: =财务计划现金流量表!H13 -> #VALUE! | I15: =财务计划现金流量表!I13 -> #VALUE! | J15: =财务计划现金流量表!J13 -> #VALUE! | K15: =财务计划现金流量表!K13 -> #VALUE! | ... AC15: =财务计划现金流量表!AC13 -> #VALUE!
A16: 2.5 | B16: 进项税 | C16: =SUM(D16:AC16) -> 0 | D16: =财务计划现金流量表!D14 -> 0 | E16: =财务计划现金流量表!E14 -> 0 | F16: =财务计划现金流量表!F14 -> 0 | G16: =财务计划现金流量表!G14 -> 0 | H16: =财务计划现金流量表!H14 -> 0 | I16: =财务计划现金流量表!I14 -> 0 | J16: =财务计划现金流量表!J14 -> 0 | K16: =财务计划现金流量表!K14 -> 0 | ... AC16: =财务计划现金流量表!AC14 -> 0
A17: 2.6 | B17: 销售税金附加 | C17: =SUM(D17:AC17) -> #VALUE! | D17: =财务计划现金流量表!D12 -> 0 | E17: =财务计划现金流量表!E12 -> #VALUE! | F17: =财务计划现金流量表!F12 -> #VALUE! | G17: =财务计划现金流量表!G12 -> #VALUE! | H17: =财务计划现金流量表!H12 -> #VALUE! | I17: =财务计划现金流量表!I12 -> #VALUE! | J17: =财务计划现金流量表!J12 -> #VALUE! | K17: =财务计划现金流量表!K12 -> #VALUE! | ... AC17: =财务计划现金流量表!AC12 -> #VALUE!
A18: 3 | B18: 所得税前净现金流量(1-2) | C18: =SUM(D18:AC18) -> #VALUE! | D18: =D5-D11 -> 0 | E18: =E5-E11 -> #VALUE! | F18: =F5-F11 -> #VALUE! | G18: =G5-G11 -> #VALUE! | H18: =H5-H11 -> #VALUE! | I18: =I5-I11 -> #VALUE! | J18: =J5-J11 -> #VALUE! | K18: =K5-K11 -> #VALUE! | ... AC18: =AC5-AC11 -> #VALUE!
A19: 4 | B19: 累计所得税前净现金流量 | D19: =IF(COLUMN()-3<=基本参数!$B$4,C19+D18,0) -> 0 | E19: =IF(COLUMN()-3<=基本参数!$B$4,D19+E18,0) -> #VALUE! | F19: =IF(COLUMN()-3<=基本参数!$B$4,E19+F18,0) -> #VALUE! | G19: =IF(COLUMN()-3<=基本参数!$B$4,F19+G18,0) -> #VALUE! | H19: =IF(COLUMN()-3<=基本参数!$B$4,G19+H18,0) -> #VALUE! | I19: =IF(COLUMN()-3<=基本参数!$B$4,H19+I18,0) -> #VALUE! | J19: =IF(COLUMN()-3<=基本参数!$B$4,I19+J18,0) -> #VALUE! | K19: =IF(COLUMN()-3<=基本参数!$B$4,J19+K18,0) -> #VALUE! | ... AC19: =IF(COLUMN()-3<=基本参数!$B$4,AB19+AC18,0) -> 0
A20: 5 | B20: 调整所得税 | C20: =SUM(D20:AC20) -> #VALUE! | D20: =IF(利润与利润分配表!D29*收入和税金!C23/100>0,利润与利润分配表!D29*收入和税金!C23/100,0) -> 0 | E20: =IF(利润与利润分配表!E29*收入和税金!D23/100>0,利润与利润分配表!E29*收入和税金!D23/100,0) -> #VALUE! | F20: =IF(利润与利润分配表!F29*收入和税金!E23/100>0,利润与利润分配表!F29*收入和税金!E23/100,0) -> #VALUE! | G20: =IF(利润与利润分配表!G29*收入和税金!F23/100>0,利润与利润分配表!G29*收入和税金!F23/100,0) -> #VALUE! | H20: =IF(利润与利润分配表!H29*收入和税金!G23/100>0,利润与利润分配表!H29*收入和税金!G23/100,0) -> #VALUE! | I20: =IF(利润与利润分配表!I29*收入和税金!H23/100>0,利润与利润分配表!I29*收入和税金!H23/100,0) -> #VALUE! | J20: =IF(利润与利润分配表!J29*收入和税金!I23/100>0,利润与利润分配表!J29*收入和税金!I23/100,0) -> #VALUE! | K20: =IF(利润与利润分配表!K29*收入和税金!J23/100>0,利润与利润分配表!K29*收入和税金!J23/100,0) -> #VALUE! | ... AC20: =IF(利润与利润分配表!AC29*收入和税金!AB23/100>0,利润与利润分配表!AC29*收入和税金!AB23/100,0) -> #VALUE!
A21: 6 | B21: 所得税后净现金流量（3-5） | C21: =SUM(D21:AC21) -> #VALUE! | D21: =D18-D20 -> 0 | E21: =E18-E20 -> #VALUE! | F21: =F18-F20 -> #VALUE! | G21: =G18-G20 -> #VALUE! | H21: =H18-H20 -> #VALUE! | I21: =I18-I20 -> #VALUE! | J21: =J18-J20 -> #VALUE! | K21: =K18-K20 -> #VALUE! | ... AC21: =AC18-AC20 -> #VALUE!
A22: 7 | B22: 累计所得税后净现金流量 | D22: =IF(COLUMN()-4<=基本参数!$B$4,C22+D21,0) -> 0 | E22: =IF(COLUMN()-4<=基本参数!$B$4,D22+E21,0) -> #VALUE! | F22: =IF(COLUMN()-4<=基本参数!$B$4,E22+F21,0) -> #VALUE! | G22: =IF(COLUMN()-4<=基本参数!$B$4,F22+G21,0) -> #VALUE! | H22: =IF(COLUMN()-4<=基本参数!$B$4,G22+H21,0) -> #VALUE! | I22: =IF(COLUMN()-4<=基本参数!$B$4,H22+I21,0) -> #VALUE! | J22: =IF(COLUMN()-4<=基本参数!$B$4,I22+J21,0) -> #VALUE! | K22: =IF(COLUMN()-4<=基本参数!$B$4,J22+K21,0) -> #VALUE! | ... AC22: =IF(COLUMN()-4<=基本参数!$B$4,AB22+AC21,0) -> #VALUE!
A23: 计算指标：
A24: 全投资内部收益率（税前）（%） | C24: =IRR(D18:AC18)*100 -> #VALUE!
A25: 全投资内部收益率（税后）（%） | C25: =IRR(D21:AC21)*100 -> #VALUE!
A26: 全投资净现值（税前）（万元） | C26: =NPV(基本参数!B23/100,D18:AC18) -> #VALUE!
A27: 全投资净现值（税后）（万元） | C27: =NPV(基本参数!B24/100,D21:AC21) -> #VALUE!
A28: 投资回收期（税前）（年） | C28: =MATCH(0-10^-100,D19:AC19,1)-LOOKUP(0-10^-100,D19:AC19)/INDEX(D18:AC18,MATCH(0-10^-100,D19:AC19,1)+1) -> #N/A
A29: 投资回收期（税后）（年） | C29: =MATCH(0-10^-100,D22:AC22,1)-LOOKUP(0-10^-100,D22:AC22)/INDEX(D21:AC21,MATCH(0-10^-100,D22:AC22,1)+1) -> #N/A
A30: 动态投资回收期（税前）（年） | C30: =MATCH(0-10^-100,D33:AC33,1)-LOOKUP(0-10^-100,D33:AC33)/INDEX(D32:AC32,MATCH(0-10^-100,D33:AC33,1)+1) -> #N/A
A31: 动态投资回收期（税后）（年） | C31: =MATCH(0-10^-100,D35:AC35,1)-LOOKUP(0-10^-100,D35:AC35)/INDEX(D34:AC34,MATCH(0-10^-100,D35:AC35,1)+1) -> #N/A
A32: 辅助行 | B32: 所得税前净现金流量现值 | D32: =D18*(1+基本参数!$B$23%)^(1-(COLUMN()-3)) -> 0 | E32: =E18*(1+基本参数!$B$23%)^(1-(COLUMN()-3)) -> #VALUE! | F32: =F18*(1+基本参数!$B$23%)^(1-(COLUMN()-3)) -> #VALUE! | G32: =G18*(1+基本参数!$B$23%)^(1-(COLUMN()-3)) -> #VALUE! | H32: =H18*(1+基本参数!$B$23%)^(1-(COLUMN()-3)) -> #VALUE! | I32: =I18*(1+基本参数!$B$23%)^(1-(COLUMN()-3)) -> #VALUE! | J32: =J18*(1+基本参数!$B$23%)^(1-(COLUMN()-3)) -> #VALUE! | K32: =K18*(1+基本参数!$B$23%)^(1-(COLUMN()-3)) -> #VALUE! | ... AC32: =AC18*(1+基本参数!$B$23%)^(1-(COLUMN()-3)) -> #VALUE!
B33: 累计所得税前净现金流量现值 | D33: =IF(COLUMN()-3<=基本参数!$B$2,C33+D32,0) -> 0 | E33: =IF(COLUMN()-3<=基本参数!$B$2,D33+E32,0) -> #VALUE! | F33: =IF(COLUMN()-3<=基本参数!$B$2,E33+F32,0) -> #VALUE! | G33: =IF(COLUMN()-3<=基本参数!$B$2,F33+G32,0) -> #VALUE! | H33: =IF(COLUMN()-3<=基本参数!$B$2,G33+H32,0) -> #VALUE! | I33: =IF(COLUMN()-3<=基本参数!$B$2,H33+I32,0) -> #VALUE! | J33: =IF(COLUMN()-3<=基本参数!$B$2,I33+J32,0) -> #VALUE! | K33: =IF(COLUMN()-3<=基本参数!$B$2,J33+K32,0) -> #VALUE! | ... AC33: =IF(COLUMN()-3<=基本参数!$B$2,AB33+AC32,0) -> #VALUE!
B34: 所得税后净现金流量现值 | D34: =D21*(1+基本参数!$B$24%)^(1-(COLUMN()-3)) -> 0 | E34: =E21*(1+基本参数!$B$24%)^(1-(COLUMN()-3)) -> #VALUE! | F34: =F21*(1+基本参数!$B$24%)^(1-(COLUMN()-3)) -> #VALUE! | G34: =G21*(1+基本参数!$B$24%)^(1-(COLUMN()-3)) -> #VALUE! | H34: =H21*(1+基本参数!$B$24%)^(1-(COLUMN()-3)) -> #VALUE! | I34: =I21*(1+基本参数!$B$24%)^(1-(COLUMN()-3)) -> #VALUE! | J34: =J21*(1+基本参数!$B$24%)^(1-(COLUMN()-3)) -> #VALUE! | K34: =K21*(1+基本参数!$B$24%)^(1-(COLUMN()-3)) -> #VALUE! | ... AC34: =AC21*(1+基本参数!$B$24%)^(1-(COLUMN()-3)) -> #VALUE!
B35: 累计所得税后净现金流量现值 | D35: =IF(COLUMN()-3<=基本参数!$B$2,C35+D34,0) -> 0 | E35: =IF(COLUMN()-3<=基本参数!$B$2,D35+E34,0) -> #VALUE! | F35: =IF(COLUMN()-3<=基本参数!$B$2,E35+F34,0) -> #VALUE! | G35: =IF(COLUMN()-3<=基本参数!$B$2,F35+G34,0) -> #VALUE! | H35: =IF(COLUMN()-3<=基本参数!$B$2,G35+H34,0) -> #VALUE! | I35: =IF(COLUMN()-3<=基本参数!$B$2,H35+I34,0) -> #VALUE! | J35: =IF(COLUMN()-3<=基本参数!$B$2,I35+J34,0) -> #VALUE! | K35: =IF(COLUMN()-3<=基本参数!$B$2,J35+K34,0) -> #VALUE! | ... AC35: =IF(COLUMN()-3<=基本参数!$B$2,AB35+AC34,0) -> #VALUE!

Sheet 项目资本金现金流量表
A1: 项目资本金现金流量表
A2: 人民币单位：万元
A3: 序号 | B3: 项目 | C3: 合计 | D3: 建设期 | E3: 运行期
D4: 第1年 | E4: 第2年 | F4: 第3年 | G4: 第4年 | H4: 第5年 | I4: 第6年 | J4: 第7年 | K4: 第8年 | L4: 第9年 | M4: 第10年 | N4: 第11年 | O4: 第12年 | P4: 第13年 | Q4: 第14年 | R4: 第15年 | S4: 第16年 | T4: 第17年 | U4: 第18年 | V4: 第19年 | W4: 第20年 | X4: 第21年 | Y4: 第22年 | Z4: 第23年 | AA4: 第24年 | AB4: 第25年 | AC4: 第26年
A5: 1 | B5: 现金流入 | C5: =SUM(D5:AC5) -> #VALUE! | D5: =SUM(D6:D10) -> 0 | E5: =SUM(E6:E10) -> #VALUE! | F5: =SUM(F6:F10) -> #VALUE! | G5: =SUM(G6:G10) -> #VALUE! | H5: =SUM(H6:H10) -> #VALUE! | I5: =SUM(I6:I10) -> #VALUE! | J5: =SUM(J6:J10) -> #VALUE! | K5: =SUM(K6:K10) -> #VALUE! | ... AC5: =SUM(AC6:AC10) -> #VALUE!
A6: 1.1 | B6: 销售收入 | C6: =SUM(D6:AC6) -> #VALUE! | D6: =项目投资现金流量表!D6 -> 0 | E6: =项目投资现金流量表!E6 -> #VALUE! | F6: =项目投资现金流量表!F6 -> #VALUE! | G6: =项目投资现金流量表!G6 -> #VALUE! | H6: =项目投资现金流量表!H6 -> #VALUE! | I6: =项目投资现金流量表!I6 -> #VALUE! | J6: =项目投资现金流量表!J6 -> #VALUE! | K6: =项目投资现金流量表!K6 -> #VALUE! | ... AC6: =项目投资现金流量表!AC6 -> #VALUE!
A7: 1.2 | B7: 其他收入(应税) | C7: =SUM(D7:AC7) -> 0 | D7: =项目投资现金流量表!D7 -> 0 | E7: =项目投资现金流量表!E7 -> 0 | F7: =项目投资现金流量表!F7 -> 0 | G7: =项目投资现金流量表!G7 -> 0 | H7: =项目投资现金流量表!H7 -> 0 | I7: =项目投资现金流量表!I7 -> 0 | J7: =项目投资现金流量表!J7 -> 0 | K7: =项目投资现金流量表!K7 -> 0 | ... AC7: =项目投资现金流量表!AC7 -> 0
A8: 1.3 | B8: 其他收入(免税) | C8: =SUM(D8:AC8) -> 0 | D8: =项目投资现金流量表!D8 -> 0 | E8: =项目投资现金流量表!E8 -> 0 | F8: =项目投资现金流量表!F8 -> 0 | G8: =项目投资现金流量表!G8 -> 0 | H8: =项目投资现金流量表!H8 -> 0 | I8: =项目投资现金流量表!I8 -> 0 | J8: =项目投资现金流量表!J8 -> 0 | K8: =项目投资现金流量表!K8 -> 0 | ... AC8: =项目投资现金流量表!AC8 -> 0
A9: 1.4 | B9: 回收固定资产余值 | C9: =SUM(D9:AC9) -> 0 | D9: =项目投资现金流量表!D9 -> 0 | E9: =项目投资现金流量表!E9 -> 0 | F9: =项目投资现金流量表!F9 -> 0 | G9: =项目投资现金流量表!G9 -> 0 | H9: =项目投资现金流量表!H9 -> 0 | I9: =项目投资现金流量表!I9 -> 0 | J9: =项目投资现金流量表!J9 -> 0 | K9: =项目投资现金流量表!K9 -> 0 | ... AC9: =项目投资现金流量表!AC9 -> 0
A10: 1.5 | B10: 回收流动资金 | C10: =SUM(D10:AC10) -> 0 | D10: =项目投资现金流量表!D10 -> 0 | E10: =项目投资现金流量表!E10 -> 0 | F10: =项目投资现金流量表!F10 -> 0 | G10: =项目投资现金流量表!G10 -> 0 | H10: =项目投资现金流量表!H10 -> 0 | I10: =项目投资现金流量表!I10 -> 0 | J10: =项目投资现金流量表!J10 -> 0 | K10: =项目投资现金流量表!K10 -> 0 | ... AC10: =项目投资现金流量表!AC10 -> 0
A11: 1.6 | B11: 新增短期贷款
A12: 2 | B12: 现金流出 | C12: =SUM(D12:AC12) -> #VALUE! | D12: =SUM(D13:D20) -> 0 | E12: =SUM(E13:E20) -> #VALUE! | F12: =SUM(F13:F20) -> #VALUE! | G12: =SUM(G13:G20) -> #VALUE! | H12: =SUM(H13:H20) -> #VALUE! | I12: =SUM(I13:I20) -> #VALUE! | J12: =SUM(J13:J20) -> #VALUE! | K12: =SUM(K13:K20) -> #VALUE! | ... AC12: =SUM(AC13:AC20) -> #VALUE!
A13: 2.1 | B13: 项目资本金 | C13: =SUM(D13:AC13) -> 0 | D13: =投资计划与资金筹措表!D10 -> 0 | E13: =投资计划与资金筹措表!E10 -> 0 | F13: =投资计划与资金筹措表!F10 -> 0 | G13: =投资计划与资金筹措表!G10 -> 0 | H13: =投资计划与资金筹措表!H10 -> 0 | I13: =投资计划与资金筹措表!I10 -> 0 | J13: =投资计划与资金筹措表!J10 -> 0 | K13: =投资计划与资金筹措表!K10 -> 0 | ... AC13: =投资计划与资金筹措表!AC10 -> 0
A14: 2.2 | B14: 借款本金偿还 | C14: =SUM(D14:AC14) -> #VALUE! | D14: =财务计划现金流量表!D33 -> 0 | E14: =财务计划现金流量表!E33 -> #VALUE! | F14: =财务计划现金流量表!F33 -> #VALUE! | G14: =财务计划现金流量表!G33 -> #VALUE! | H14: =财务计划现金流量表!H33 -> #VALUE! | I14: =财务计划现金流量表!I33 -> #VALUE! | J14: =财务计划现金流量表!J33 -> #VALUE! | K14: =财务计划现金流量表!K33 -> #VALUE! | ... AC14: =财务计划现金流量表!AC33 -> #VALUE!
A15: 2.3 | B15: 借款利息支付 | C15: =SUM(D15:AC15) -> #VALUE! | D15: =总成本费用表!D12 -> 0 | E15: =总成本费用表!E12 -> 0 | F15: =总成本费用表!F12 -> #VALUE! | G15: =总成本费用表!G12 -> #VALUE! | H15: =总成本费用表!H12 -> #VALUE! | I15: =总成本费用表!I12 -> #VALUE! | J15: =总成本费用表!J12 -> #VALUE! | K15: =总成本费用表!K12 -> #VALUE! | ... AC15: =总成本费用表!AC12 -> #VALUE!
A16: 2.4 | B16: 经营成本 | C16: =SUM(D16:AC16) -> #REF! | D16: =总成本费用表!D21 -> 0 | E16: =总成本费用表!E21 -> #REF! | F16: =总成本费用表!F21 -> #REF! | G16: =总成本费用表!G21 -> #REF! | H16: =总成本费用表!H21 -> #REF! | I16: =总成本费用表!I21 -> #REF! | J16: =总成本费用表!J21 -> #REF! | K16: =总成本费用表!K21 -> #REF! | ... AC16: =总成本费用表!AC21 -> #REF!
A17: 2.5 | B17: 销售税金附加 | C17: =SUM(D17:AC17) -> #VALUE! | D17: =项目投资现金流量表!D17 -> 0 | E17: =项目投资现金流量表!E17 -> #VALUE! | F17: =项目投资现金流量表!F17 -> #VALUE! | G17: =项目投资现金流量表!G17 -> #VALUE! | H17: =项目投资现金流量表!H17 -> #VALUE! | I17: =项目投资现金流量表!I17 -> #VALUE! | J17: =项目投资现金流量表!J17 -> #VALUE! | K17: =项目投资现金流量表!K17 -> #VALUE! | ... AC17: =项目投资现金流量表!AC17 -> #VALUE!
A18: 2.6 | B18: 所得税 | C18: =SUM(D18:AC18) -> #VALUE! | D18: =财务计划现金流量表!D15 -> 0 | E18: =财务计划现金流量表!E15 -> #VALUE! | F18: =财务计划现金流量表!F15 -> #VALUE! | G18: =财务计划现金流量表!G15 -> #VALUE! | H18: =财务计划现金流量表!H15 -> #VALUE! | I18: =财务计划现金流量表!I15 -> #VALUE! | J18: =财务计划现金流量表!J15 -> #VALUE! | K18: =财务计划现金流量表!K15 -> #VALUE! | ... AC18: =财务计划现金流量表!AC15 -> #VALUE!
A19: 2.7 | B19: 实缴增值税 | C19: =SUM(D19:AC19) -> #VALUE! | D19: =财务计划现金流量表!D13 -> 0 | E19: =财务计划现金流量表!E13 -> #VALUE! | F19: =财务计划现金流量表!F13 -> #VALUE! | G19: =财务计划现金流量表!G13 -> #VALUE! | H19: =财务计划现金流量表!H13 -> #VALUE! | I19: =财务计划现金流量表!I13 -> #VALUE! | J19: =财务计划现金流量表!J13 -> #VALUE! | K19: =财务计划现金流量表!K13 -> #VALUE! | ... AC19: =财务计划现金流量表!AC13 -> #VALUE!
A20: 2.8 | B20: 进项税 | C20: =SUM(D20:AC20) -> 0 | D20: =项目投资现金流量表!D16 -> 0 | E20: =项目投资现金流量表!E16 -> 0 | F20: =项目投资现金流量表!F16 -> 0 | G20: =项目投资现金流量表!G16 -> 0 | H20: =项目投资现金流量表!H16 -> 0 | I20: =项目投资现金流量表!I16 -> 0 | J20: =项目投资现金流量表!J16 -> 0 | K20: =项目投资现金流量表!K16 -> 0 | ... AC20: =项目投资现金流量表!AC16 -> 0
A21: 3 | B21: 净现金流量（1-2） | C21: =SUM(D21:AC21) -> #VALUE! | D21: =D5-D12 -> 0 | E21: =E5-E12 -> #VALUE! | F21: =F5-F12 -> #VALUE! | G21: =G5-G12 -> #VALUE! | H21: =H5-H12 -> #VALUE! | I21: =I5-I12 -> #VALUE! | J21: =J5-J12 -> #VALUE! | K21: =K5-K12 -> #VALUE! | ... AC21: =AC5-AC12 -> #VALUE!
A22: 计算指标：
A23: 资本金内部收益率（%） | C23: =IRR(D21:AC21)*100 -> #VALUE!
A24: 资本金财务净现值(万元) | C24: =NPV(基本参数!B22/100,D21:AC21) -> #VALUE!

Sheet 资产负债表
A1: 资产负债表
A2: 人民币单位：万元
A3: 序号 | B3: 项目 | C3: 建设期 | D3: 运行期
C4: 第1年 | D4: 第2年 | E4: 第3年 | F4: 第4年 | G4: 第5年 | H4: 第6年 | I4: 第7年 | J4: 第8年 | K4: 第9年 | L4: 第10年 | M4: 第11年 | N4: 第12年 | O4: 第13年 | P4: 第14年 | Q4: 第15年 | R4: 第16年 | S4: 第17年 | T4: 第18年 | U4: 第19年 | V4: 第20年 | W4: 第21年 | X4: 第22年 | Y4: 第23年 | Z4: 第24年 | AA4: 第25年 | AB4: 第26年
A5: 1 | B5: 资产 | C5: =C6+C9+C10+C11+C12 -> 0 | D5: =D6+D9+D10+D11+D12 -> #VALUE! | E5: =E6+E9+E10+E11+E12 -> #VALUE! | F5: =F6+F9+F10+F11+F12 -> #VALUE! | G5: =G6+G9+G10+G11+G12 -> #VALUE! | H5: =H6+H9+H10+H11+H12 -> #VALUE! | I5: =I6+I9+I10+I11+I12 -> #VALUE! | J5: =J6+J9+J10+J11+J12 -> #VALUE! | ... AB5: =AB6+AB9+AB10+AB11+AB12 -> #VALUE!
A6: 1.1 | B6: 流动资产总额 | C6: =C7+C8 -> 0 | D6: =D7+D8 -> #VALUE! | E6: =E7+E8 -> #VALUE! | F6: =F7+F8 -> #VALUE! | G6: =G7+G8 -> #VALUE! | H6: =H7+H8 -> #VALUE! | I6: =I7+I8 -> #VALUE! | J6: =J7+J8 -> #VALUE! | ... AB6: =AB7+AB8 -> #VALUE!
A7: 1.1.1 | B7: 累计盈余资金 | C7: =财务计划现金流量表!D37 -> 0 | D7: =财务计划现金流量表!E37 -> #VALUE! | E7: =财务计划现金流量表!F37 -> #VALUE! | F7: =财务计划现金流量表!G37 -> #VALUE! | G7: =财务计划现金流量表!H37 -> #VALUE! | H7: =财务计划现金流量表!I37 -> #VALUE! | I7: =财务计划现金流量表!J37 -> #VALUE! | J7: =财务计划现金流量表!K37 -> #VALUE! | ... AB7: =财务计划现金流量表!AC37 -> #VALUE!
A8: 1.1.2 | B8: 流动资产 | C8: =IF(COLUMN()-2<基本参数!$B$2,SUM(财务计划现金流量表!$D$22:D22),0) -> 0 | D8: =IF(COLUMN()-2<基本参数!$B$2,SUM(财务计划现金流量表!$D$22:E22),0) -> 0 | E8: =IF(COLUMN()-2<基本参数!$B$2,SUM(财务计划现金流量表!$D$22:F22),0) -> 0 | F8: =IF(COLUMN()-2<基本参数!$B$2,SUM(财务计划现金流量表!$D$22:G22),0) -> 0 | G8: =IF(COLUMN()-2<基本参数!$B$2,SUM(财务计划现金流量表!$D$22:H22),0) -> 0 | H8: =IF(COLUMN()-2<基本参数!$B$2,SUM(财务计划现金流量表!$D$22:I22),0) -> 0 | I8: =IF(COLUMN()-2<基本参数!$B$2,SUM(财务计划现金流量表!$D$22:J22),0) -> 0 | J8: =IF(COLUMN()-2<基本参数!$B$2,SUM(财务计划现金流量表!$D$22:K22),0) -> 0 | ... AB8: =IF(COLUMN()-2<基本参数!$B$2,SUM(财务计划现金流量表!$D$22:AC22),0) -> 0
A9: 1.2 | B9: 在建工程 | C9: =成本费用!C88 -> 0
A10: 1.3 | B10: 净值 | C10: =IF(COLUMN()-2<=基本参数!$B$2,成本费用!C90-SUM(项目投资现金流量表!$D$9:项目投资现金流量表!D9),0) -> 0 | D10: =IF(COLUMN()-2<=基本参数!$B$2,成本费用!D90-SUM(项目投资现金流量表!$D$9:项目投资现金流量表!E9),0) -> 0 | E10: =IF(COLUMN()-2<=基本参数!$B$2,成本费用!E90-SUM(项目投资现金流量表!$D$9:项目投资现金流量表!F9),0) -> 0 | F10: =IF(COLUMN()-2<=基本参数!$B$2,成本费用!F90-SUM(项目投资现金流量表!$D$9:项目投资现金流量表!G9),0) -> 0 | G10: =IF(COLUMN()-2<=基本参数!$B$2,成本费用!G90-SUM(项目投资现金流量表!$D$9:项目投资现金流量表!H9),0) -> 0 | H10: =IF(COLUMN()-2<=基本参数!$B$2,成本费用!H90-SUM(项目投资现金流量表!$D$9:项目投资现金流量表!I9),0) -> 0 | I10: =IF(COLUMN()-2<=基本参数!$B$2,成本费用!I90-SUM(项目投资现金流量表!$D$9:项目投资现金流量表!J9),0) -> 0 | J10: =IF(COLUMN()-2<=基本参数!$B$2,成本费用!J90-SUM(项目投资现金流量表!$D$9:项目投资现金流量表!K9),0) -> 0 | ... AB10: =IF(COLUMN()-2<=基本参数!$B$2,成本费用!AB90-SUM(项目投资现金流量表!$D$9:项目投资现金流量表!AC9),0) -> 0
A11: 1.4 | B11: 无形及其他资产净值 | C11: =-SUM(成本费用!$C$56:C56) -> 0 | D11: =SUM(基本参数!$B$13:$B$14)-SUM(成本费用!$C$56:D56) -> 0 | E11: =SUM(基本参数!$B$13:$B$14)-SUM(成本费用!$C$56:E56) -> 0 | F11: =SUM(基本参数!$B$13:$B$14)-SUM(成本费用!$C$56:F56) -> 0 | G11: =SUM(基本参数!$B$13:$B$14)-SUM(成本费用!$C$56:G56) -> 0 | H11: =SUM(基本参数!$B$13:$B$14)-SUM(成本费用!$C$56:H56) -> 0 | I11: =SUM(基本参数!$B$13:$B$14)-SUM(成本费用!$C$56:I56) -> 0 | J11: =SUM(基本参数!$B$13:$B$14)-SUM(成本费用!$C$56:J56) -> 0 | K11: =SUM(基本参数!$B$13:$B$14)-SUM(成本费用!$C$56:K56) -> 0 | ... AB11: =SUM(基本参数!$B$13:$B$14)-SUM(成本费用!$C$56:AB56) -> 0
A12: 1.5 | B12: 可抵扣增值税形成资产 | C12: 0 | D12: =IF(COLUMN()-2<=基本参数!$B$2,IF(D28>0,D28,0),0) -> #VALUE! | E12: =IF(COLUMN()-2<=基本参数!$B$2,IF(E28>0,E28,0),0) -> #VALUE! | F12: =IF(COLUMN()-2<=基本参数!$B$2,IF(F28>0,F28,0),0) -> #VALUE! | G12: =IF(COLUMN()-2<=基本参数!$B$2,IF(G28>0,G28,0),0) -> #VALUE! | H12: =IF(COLUMN()-2<=基本参数!$B$2,IF(H28>0,H28,0),0) -> #VALUE! | I12: =IF(COLUMN()-2<=基本参数!$B$2,IF(I28>0,I28,0),0) -> #VALUE! | J12: =IF(COLUMN()-2<=基本参数!$B$2,IF(J28>0,J28,0),0) -> #VALUE! | K12: =IF(COLUMN()-2<=基本参数!$B$2,IF(K28>0,K28,0),0) -> #VALUE! | ... AB12: =IF(COLUMN()-2<=基本参数!$B$2,IF(AB28>0,AB28,0),0) -> #VALUE!
A13: 2 | B13: 负债及所有者权益（2.4+2.5） | C13: =C19+C20 -> 0 | D13: =D19+D20 -> #VALUE! | E13: =E19+E20 -> #VALUE! | F13: =F19+F20 -> #VALUE! | G13: =G19+G20 -> #VALUE! | H13: =H19+H20 -> #VALUE! | I13: =I19+I20 -> #VALUE! | J13: =J19+J20 -> #VALUE! | ... AB13: =AB19+AB20 -> #VALUE!
A14: 2.1 | B14: 流动负债总额 | C14: =C15+C16 -> 0 | D14: =D15+D16 -> #VALUE! | E14: =E15+E16 -> #VALUE! | F14: =F15+F16 -> #VALUE! | G14: =G15+G16 -> #VALUE! | H14: =H15+H16 -> #VALUE! | I14: =I15+I16 -> #VALUE! | J14: =J15+J16 -> #VALUE! | ... AB14: =AB15+AB16 -> #VALUE!
A15: 2.1.1 | B15: 短期借款 | C15: =借款还本付息计划表!D20 -> 0 | D15: =借款还本付息计划表!E20 -> #VALUE! | E15: =借款还本付息计划表!F20 -> #VALUE! | F15: =借款还本付息计划表!G20 -> #VALUE! | G15: =借款还本付息计划表!H20 -> #VALUE! | H15: =借款还本付息计划表!I20 -> #VALUE! | I15: =借款还本付息计划表!J20 -> #VALUE! | J15: =借款还本付息计划表!K20 -> #VALUE! | ... AB15: =借款还本付息计划表!AC20 -> #VALUE!
A16: 2.1.2 | B16: 其他 | C16: 0 | D16: 0 | E16: 0 | F16: 0 | G16: 0 | H16: 0 | I16: 0 | J16: 0 | K16: 0 | L16: 0 | M16: 0 | N16: 0 | O16: 0 | P16: 0 | Q16: 0 | R16: 0 | S16: 0 | T16: 0 | U16: 0 | V16: 0 | W16: 0 | X16: 0 | Y16: 0 | Z16: 0 | AA16: 0 | AB16: 0
A17: 2.2 | B17: 建设投资借款 | C17: =借款还本付息计划表!E6 -> 0 | D17: =借款还本付息计划表!F6 -> 0 | E17: =借款还本付息计划表!G6 -> 0 | F17: =借款还本付息计划表!H6 -> 0 | G17: =借款还本付息计划表!I6 -> 0 | H17: =借款还本付息计划表!J6 -> 0 | I17: =借款还本付息计划表!K6 -> 0 | J17: =借款还本付息计划表!L6 -> 0 | ... AB17: =借款还本付息计划表!AD6 -> 0
A18: 2.3 | B18: 流动资金借款 | C18: =IF(COLUMN()-2<基本参数!$B$2,借款还本付息计划表!D12,0) -> 0 | D18: =IF(COLUMN()-2<基本参数!$B$2,借款还本付息计划表!E12,0) -> 0 | E18: =IF(COLUMN()-2<基本参数!$B$2,借款还本付息计划表!F12,0) -> 0 | F18: =IF(COLUMN()-2<基本参数!$B$2,借款还本付息计划表!G12,0) -> 0 | G18: =IF(COLUMN()-2<基本参数!$B$2,借款还本付息计划表!H12,0) -> 0 | H18: =IF(COLUMN()-2<基本参数!$B$2,借款还本付息计划表!I12,0) -> 0 | I18: =IF(COLUMN()-2<基本参数!$B$2,借款还本付息计划表!J12,0) -> 0 | J18: =IF(COLUMN()-2<基本参数!$B$2,借款还本付息计划表!K12,0) -> 0 | ... AB18: =IF(COLUMN()-2<基本参数!$B$2,借款还本付息计划表!AC12,0) -> 0
A19: 2.4 | B19: 负债小计（2.1+2.2+2.3） | C19: =C14+C17+C18 -> 0 | D19: =D14+D17+D18 -> #VALUE! | E19: =E14+E17+E18 -> #VALUE! | F19: =F14+F17+F18 -> #VALUE! | G19: =G14+G17+G18 -> #VALUE! | H19: =H14+H17+H18 -> #VALUE! | I19: =I14+I17+I18 -> #VALUE! | J19: =J14+J17+J18 -> #VALUE! | ... AB19: =AB14+AB17+AB18 -> #VALUE!
A20: 2.5 | B20: 所有者权益 | C20: =C21+C22+C23+C24 -> 0 | D20: =D21+D22+D23+D24 -> #VALUE! | E20: =E21+E22+E23+E24 -> #VALUE! | F20: =F21+F22+F23+F24 -> #VALUE! | G20: =G21+G22+G23+G24 -> #VALUE! | H20: =H21+H22+H23+H24 -> #VALUE! | I20: =I21+I22+I23+I24 -> #VALUE! | J20: =J21+J22+J23+J24 -> #VALUE! | ... AB20: =AB21+AB22+AB23+AB24 -> #VALUE!
A21: 2.5.1 | B21: 资本金 | C21: =财务计划现金流量表!D25 -> 0 | D21: =IF(COLUMN()-2<=基本参数!$B$2,C21+财务计划现金流量表!E25,0) -> 0 | E21: =IF(COLUMN()-2<=基本参数!$B$2,D21+财务计划现金流量表!F25,0) -> 0 | F21: =IF(COLUMN()-2<=基本参数!$B$2,E21+财务计划现金流量表!G25,0) -> 0 | G21: =IF(COLUMN()-2<=基本参数!$B$2,F21+财务计划现金流量表!H25,0) -> 0 | H21: =IF(COLUMN()-2<=基本参数!$B$2,G21+财务计划现金流量表!I25,0) -> 0 | I21: =IF(COLUMN()-2<=基本参数!$B$2,H21+财务计划现金流量表!J25,0) -> 0 | J21: =IF(COLUMN()-2<=基本参数!$B$2,I21+财务计划现金流量表!K25,0) -> 0 | K21: =IF(COLUMN()-2<=基本参数!$B$2,J21+财务计划现金流量表!L25,0) -> 0 | ... AB21: =IF(COLUMN()-2<=基本参数!$B$2,AA21+财务计划现金流量表!AC25,0) -> 0
A22: 2.5.2 | B22: 资本公积 | C22: 0 | D22: 0 | E22: 0 | F22: 0 | G22: 0 | H22: 0 | I22: 0 | J22: 0 | K22: 0 | L22: 0 | M22: 0 | N22: 0 | O22: 0 | P22: 0 | Q22: 0 | R22: 0 | S22: 0 | T22: 0 | U22: 0 | V22: 0 | W22: 0 | X22: 0 | Y22: 0 | Z22: 0 | AA22: 0 | AB22: 0
A23: 2.5.3 | B23: 累计盈余公积金 | C23: =利润与利润分配表!D31 -> 0 | D23: =利润与利润分配表!E31 -> #VALUE! | E23: =利润与利润分配表!F31 -> #VALUE! | F23: =利润与利润分配表!G31 -> #VALUE! | G23: =利润与利润分配表!H31 -> #VALUE! | H23: =利润与利润分配表!I31 -> #VALUE! | I23: =利润与利润分配表!J31 -> #VALUE! | J23: =利润与利润分配表!K31 -> #VALUE! | ... AB23: =利润与利润分配表!AC31 -> #VALUE!
A24: 2.5.4 | B24: 累计未分配利润 | C24: =利润与利润分配表!D28 -> 0 | D24: =利润与利润分配表!E28 -> #VALUE! | E24: =利润与利润分配表!F28 -> #VALUE! | F24: =利润与利润分配表!G28 -> #VALUE! | G24: =利润与利润分配表!H28 -> #VALUE! | H24: =利润与利润分配表!I28 -> #VALUE! | I24: =利润与利润分配表!J28 -> #VALUE! | J24: =利润与利润分配表!K28 -> #VALUE! | ... AB24: =利润与利润分配表!AC28 -> #VALUE!
B25: 资产负债平衡 | C25: =C5-C13 -> 0 | D25: =D5-D13 -> #VALUE! | E25: =E5-E13 -> #VALUE! | F25: =F5-F13 -> #VALUE! | G25: =G5-G13 -> #VALUE! | H25: =H5-H13 -> #VALUE! | I25: =I5-I13 -> #VALUE! | J25: =J5-J13 -> #VALUE! | ... AB25: =AB5-AB13 -> #VALUE!
A26: 计算指标：资产负债率（%） | C26: =IF(COLUMN()-1<=基本参数!$B$3,0,IF(COLUMN()-1<=基本参数!$B$2,C19/C5*100,0)) -> #DIV/0! | D26: =IF(COLUMN()-1<=基本参数!$B$3,0,IF(COLUMN()-1<=基本参数!$B$2,D19/D5*100,0)) -> #VALUE! | E26: =IF(COLUMN()-1<=基本参数!$B$3,0,IF(COLUMN()-1<=基本参数!$B$2,E19/E5*100,0)) -> #VALUE! | F26: =IF(COLUMN()-1<=基本参数!$B$3,0,IF(COLUMN()-1<=基本参数!$B$2,F19/F5*100,0)) -> #VALUE! | G26: =IF(COLUMN()-1<=基本参数!$B$3,0,IF(COLUMN()-1<=基本参数!$B$2,G19/G5*100,0)) -> #VALUE! | H26: =IF(COLUMN()-1<=基本参数!$B$3,0,IF(COLUMN()-1<=基本参数!$B$2,H19/H5*100,0)) -> #VALUE! | I26: =IF(COLUMN()-1<=基本参数!$B$3,0,IF(COLUMN()-1<=基本参数!$B$2,I19/I5*100,0)) -> #VALUE! | J26: =IF(COLUMN()-1<=基本参数!$B$3,0,IF(COLUMN()-1<=基本参数!$B$2,J19/J5*100,0)) -> #VALUE! | ... AB26: =IF(COLUMN()-1<=基本参数!$B$3,0,IF(COLUMN()-1<=基本参数!$B$2,AB19/AB5*100,0)) -> 0
A27: 辅助 | B27: 销项-进项 | C27: =利润与利润分配表!D33-利润与利润分配表!D35 -> 0 | D27: =利润与利润分配表!E33-利润与利润分配表!E35 -> #VALUE! | E27: =利润与利润分配表!F33-利润与利润分配表!F35 -> #VALUE! | F27: =利润与利润分配表!G33-利润与利润分配表!G35 -> #VALUE! | G27: =利润与利润分配表!H33-利润与利润分配表!H35 -> #VALUE! | H27: =利润与利润分配表!I33-利润与利润分配表!I35 -> #VALUE! | I27: =利润与利润分配表!J33-利润与利润分配表!J35 -> #VALUE! | J27: =利润与利润分配表!K33-利润与利润分配表!K35 -> #VALUE! | ... AB27: =利润与利润分配表!AC33-利润与利润分配表!AC35 -> #VALUE!
B28: 可抵扣进项税形成资产 | C28: 0 | D28: =SUM(利润与利润分配表!$D$32:D32)-SUM($D$27:D27) -> #VALUE! | E28: =SUM(利润与利润分配表!$D$32:E32)-SUM($D$27:E27) -> #VALUE! | F28: =SUM(利润与利润分配表!$D$32:F32)-SUM($D$27:F27) -> #VALUE! | G28: =SUM(利润与利润分配表!$D$32:G32)-SUM($D$27:G27) -> #VALUE! | H28: =SUM(利润与利润分配表!$D$32:H32)-SUM($D$27:H27) -> #VALUE! | I28: =SUM(利润与利润分配表!$D$32:I32)-SUM($D$27:I27) -> #VALUE! | J28: =SUM(利润与利润分配表!$D$32:J32)-SUM($D$27:J27) -> #VALUE! | K28: =SUM(利润与利润分配表!$D$32:K32)-SUM($D$27:K27) -> #VALUE! | ... AB28: =SUM(利润与利润分配表!$D$32:AB32)-SUM($D$27:AB27) -> #VALUE!
B29: ROE | C29: =IF(COLUMN()-2<=基本参数!$B$3,0,利润与利润分配表!D21*2/(C20+C20)) -> 0 | D29: =IF(COLUMN()-2<=基本参数!$B$3,0,利润与利润分配表!E21*2/(C20+D20)) -> #VALUE! | E29: =IF(COLUMN()-2<=基本参数!$B$3,0,利润与利润分配表!F21*2/(D20+E20)) -> #VALUE! | F29: =IF(COLUMN()-2<=基本参数!$B$3,0,利润与利润分配表!G21*2/(E20+F20)) -> #VALUE! | G29: =IF(COLUMN()-2<=基本参数!$B$3,0,利润与利润分配表!H21*2/(F20+G20)) -> #VALUE! | H29: =IF(COLUMN()-2<=基本参数!$B$3,0,利润与利润分配表!I21*2/(G20+H20)) -> #VALUE! | I29: =IF(COLUMN()-2<=基本参数!$B$3,0,利润与利润分配表!J21*2/(H20+I20)) -> #VALUE! | J29: =IF(COLUMN()-2<=基本参数!$B$3,0,利润与利润分配表!K21*2/(I20+J20)) -> #VALUE! | K29: =IF(COLUMN()-2<=基本参数!$B$3,0,利润与利润分配表!L21*2/(J20+K20)) -> #VALUE! | ... AB29: =IF(COLUMN()-2<=基本参数!$B$3,0,利润与利润分配表!AC21*2/(AA20+AB20)) -> #VALUE!

Sheet EVA测算表
A1: EVA测算表
A2: 人民币单位：万元
A3: 序号 | B3: 项目 | C3: 合计 | D3: 建设期 | E3: 运行期
D4: 第1年 | E4: 第2年 | F4: 第3年 | G4: 第4年 | H4: 第5年 | I4: 第6年 | J4: 第7年 | K4: 第8年 | L4: 第9年 | M4: 第10年 | N4: 第11年 | O4: 第12年 | P4: 第13年 | Q4: 第14年 | R4: 第15年 | S4: 第16年 | T4: 第17年 | U4: 第18年 | V4: 第19年 | W4: 第20年 | X4: 第21年 | Y4: 第22年 | Z4: 第23年 | AA4: 第24年 | AB4: 第25年 | AC4: 第26年
A5: 1 | B5: 税后净营业利润 | C5: =SUM(D5:AC5) -> #VALUE! | D5: =D6+D7*(1-收入和税金!C23/100) -> 0 | E5: =E6+E7*(1-收入和税金!D23/100) -> #VALUE! | F5: =F6+F7*(1-收入和税金!E23/100) -> #VALUE! | G5: =G6+G7*(1-收入和税金!F23/100) -> #VALUE! | H5: =H6+H7*(1-收入和税金!G23/100) -> #VALUE! | I5: =I6+I7*(1-收入和税金!H23/100) -> #VALUE! | J5: =J6+J7*(1-收入和税金!I23/100) -> #VALUE! | K5: =K6+K7*(1-收入和税金!J23/100) -> #VALUE! | ... AC5: =AC6+AC7*(1-收入和税金!AB23/100) -> #VALUE!
A6: 1.1 | B6: 净利润 | C6: =SUM(D6:AC6) -> #VALUE! | D6: =利润与利润分配表!D21 -> 0 | E6: =利润与利润分配表!E21 -> #VALUE! | F6: =利润与利润分配表!F21 -> #VALUE! | G6: =利润与利润分配表!G21 -> #VALUE! | H6: =利润与利润分配表!H21 -> #VALUE! | I6: =利润与利润分配表!I21 -> #VALUE! | J6: =利润与利润分配表!J21 -> #VALUE! | K6: =利润与利润分配表!K21 -> #VALUE! | ... AC6: =利润与利润分配表!AC21 -> #VALUE!
A7: 1.2 | B7: 利息支出 | C7: =SUM(D7:AC7) -> #VALUE! | D7: =总成本费用表!D12 -> 0 | E7: =总成本费用表!E12 -> 0 | F7: =总成本费用表!F12 -> #VALUE! | G7: =总成本费用表!G12 -> #VALUE! | H7: =总成本费用表!H12 -> #VALUE! | I7: =总成本费用表!I12 -> #VALUE! | J7: =总成本费用表!J12 -> #VALUE! | K7: =总成本费用表!K12 -> #VALUE! | ... AC7: =总成本费用表!AC12 -> #VALUE!
A8: 2 | B8: 资本成本 | C8: =SUM(D8:AC8) -> #VALUE! | D8: =IF(COLUMN()-3<=基本参数!$B$2,((D9+C9)/2+(D10+C10)/2-(C11+D11)/2*IF(COLUMN()-3<=基本参数!$B$3,1))*基本参数!$B$25/100,0) -> 0 | E8: =IF(COLUMN()-3<=基本参数!$B$2,((E9+D9)/2+(E10+D10)/2-(D11+E11)/2*IF(COLUMN()-3<=基本参数!$B$3,1))*基本参数!$B$25/100,0) -> #VALUE! | F8: =IF(COLUMN()-3<=基本参数!$B$2,((F9+E9)/2+(F10+E10)/2-(E11+F11)/2*IF(COLUMN()-3<=基本参数!$B$3,1))*基本参数!$B$25/100,0) -> #VALUE! | G8: =IF(COLUMN()-3<=基本参数!$B$2,((G9+F9)/2+(G10+F10)/2-(F11+G11)/2*IF(COLUMN()-3<=基本参数!$B$3,1))*基本参数!$B$25/100,0) -> #VALUE! | H8: =IF(COLUMN()-3<=基本参数!$B$2,((H9+G9)/2+(H10+G10)/2-(G11+H11)/2*IF(COLUMN()-3<=基本参数!$B$3,1))*基本参数!$B$25/100,0) -> #VALUE! | I8: =IF(COLUMN()-3<=基本参数!$B$2,((I9+H9)/2+(I10+H10)/2-(H11+I11)/2*IF(COLUMN()-3<=基本参数!$B$3,1))*基本参数!$B$25/100,0) -> #VALUE! | J8: =IF(COLUMN()-3<=基本参数!$B$2,((J9+I9)/2+(J10+I10)/2-(I11+J11)/2*IF(COLUMN()-3<=基本参数!$B$3,1))*基本参数!$B$25/100,0) -> #VALUE! | K8: =IF(COLUMN()-3<=基本参数!$B$2,((K9+J9)/2+(K10+J10)/2-(J11+K11)/2*IF(COLUMN()-3<=基本参数!$B$3,1))*基本参数!$B$25/100,0) -> #VALUE! | ... AC8: =IF(COLUMN()-3<=基本参数!$B$2,((AC9+AB9)/2+(AC10+AB10)/2-(AB11+AC11)/2*IF(COLUMN()-3<=基本参数!$B$3,1))*基本参数!$B$25/100,0) -> #VALUE!
A9: 2.1 | B9: 所有者权益 | D9: =资产负债表!C20 -> 0 | E9: =资产负债表!D20 -> #VALUE! | F9: =资产负债表!E20 -> #VALUE! | G9: =资产负债表!F20 -> #VALUE! | H9: =资产负债表!G20 -> #VALUE! | I9: =资产负债表!H20 -> #VALUE! | J9: =资产负债表!I20 -> #VALUE! | K9: =资产负债表!J20 -> #VALUE! | ... AC9: =资产负债表!AB20 -> #VALUE!
A10: 2.2 | B10: 负债小计 | D10: =资产负债表!C19 -> 0 | E10: =资产负债表!D19 -> #VALUE! | F10: =资产负债表!E19 -> #VALUE! | G10: =资产负债表!F19 -> #VALUE! | H10: =资产负债表!G19 -> #VALUE! | I10: =资产负债表!H19 -> #VALUE! | J10: =资产负债表!I19 -> #VALUE! | K10: =资产负债表!J19 -> #VALUE! | ... AC10: =资产负债表!AB19 -> #VALUE!
A11: 2.3 | B11: 在建工程 | D11: =资产负债表!C9 -> 0
A12: 3 | B12: EVA | C12: =SUM(D12:AC12) -> #VALUE! | D12: =D5-D8 -> 0 | E12: =E5-E8 -> #VALUE! | F12: =F5-F8 -> #VALUE! | G12: =G5-G8 -> #VALUE! | H12: =H5-H8 -> #VALUE! | I12: =I5-I8 -> #VALUE! | J12: =J5-J8 -> #VALUE! | K12: =K5-K8 -> #VALUE! | ... AC12: =AC5-AC8 -> #VALUE!
A13: 4 | B13: △EVA | D13: 0 | E13: =IF(COLUMN()-3<=基本参数!$B$2+1,E12-D12,0) -> #VALUE! | F13: =IF(COLUMN()-3<=基本参数!$B$2+1,F12-E12,0) -> #VALUE! | G13: =IF(COLUMN()-3<=基本参数!$B$2+1,G12-F12,0) -> #VALUE! | H13: =IF(COLUMN()-3<=基本参数!$B$2+1,H12-G12,0) -> #VALUE! | I13: =IF(COLUMN()-3<=基本参数!$B$2+1,I12-H12,0) -> #VALUE! | J13: =IF(COLUMN()-3<=基本参数!$B$2+1,J12-I12,0) -> #VALUE! | K13: =IF(COLUMN()-3<=基本参数!$B$2+1,K12-J12,0) -> #VALUE! | L13: =IF(COLUMN()-3<=基本参数!$B$2+1,L12-K12,0) -> #VALUE! | ... AC13: =IF(COLUMN()-3<=基本参数!$B$2+1,AC12-AB12,0) -> #VALUE!

Sheet 财务指标一览表
A1: 财务指标一览表
A2: 序号 | B2: 项目 | C2: 单位 | D2: 数值
A3: 1 | B3: 投资回收期（税前） | C3: 年 | D3: =项目投资现金流量表!C28 -> #N/A
A4: 2 | B4: 投资回收期（税后） | C4: 年 | D4: =项目投资现金流量表!C29 -> #N/A
A5: 3 | B5: 全投资内部收益率（税前） | C5: % | D5: =项目投资现金流量表!C24 -> #VALUE!
A6: 4 | B6: 全投资内部收益率（税后） | C6: % | D6: =项目投资现金流量表!C25 -> #VALUE!
A7: 5 | B7: 全投资净现值（税前） | C7: 万元 | D7: =项目投资现金流量表!C26 -> #VALUE!
A8: 6 | B8: 全投资净现值（税后） | C8: 万元 | D8: =项目投资现金流量表!C27 -> #VALUE!
A9: 7 | B9: 资本金内部收益率 | C9: % | D9: =项目资本金现金流量表!C23 -> #VALUE!
A10: 8 | B10: 资本金财务净现值 | C10: 万元 | D10: =项目资本金现金流量表!C24 -> #VALUE!
A11: 9 | B11: 总投资收益率（ROI） | C11: % | D11: =(利润与利润分配表!C29-SUMIF(利润与利润分配表!D4:X4,"<="&基本参数!B3,利润与利润分配表!D29:X29))/基本参数!B4/投资计划与资金筹措表!C5*100 -> #VALUE!
A12: 10 | B12: 投资利税率 | C12: % | D12: =(利润与利润分配表!C12+利润与利润分配表!C17-SUMIF(利润与利润分配表!D4:X4,"<="&基本参数!B3,利润与利润分配表!D12:X12)-SUMIF(利润与利润分配表!D4:X4,"<="&基本参数!B3,利润与利润分配表!D17:X17))/基本参数!B4/投资计划与资金筹措表!C5*100 -> #VALUE!
A13: 11 | B13: 资本金净利润率（ROE） | C13: % | D13: =(利润与利润分配表!C21-SUMIF(利润与利润分配表!D4:X4,"<="&基本参数!B3,利润与利润分配表!D21:X21))/基本参数!B4/项目资本金现金流量表!C13*100 -> #VALUE!
A14: 12 | B14: 资产负债率（最大值） | C14: % | D14: =MAX(资产负债表!C26:AB26) -> #DIV/0!
A15: 13 | B15: 盈亏平衡点（生产能力利用率） | C15: % | D15: =(总成本费用表!C20-SUMIF(总成本费用表!D4:AC4,"<="&基本参数!B3,总成本费用表!D20:AC20))/(利润与利润分配表!C8-利润与利润分配表!C12)*100 -> #REF!
A16: 14 | B16: 盈亏平衡点（年产量） | C16: MWh | D16: =(利润与利润分配表!C5/基本参数!B4)*D15/100 -> #VALUE!
A17: 15 | B17: 度电投资 | C17: 元/kWh | D17: =基本参数!J11/基本参数!F12/基本参数!B4/基本参数!B7*10 -> #DIV/0!
A18: 16 | B18: 度电利润 | C18: 元/kWh | D18: =利润与利润分配表!C17/基本参数!F12/基本参数!B4/基本参数!B7*10 -> #VALUE!
A19: 17 | B19: 平准化度电成本（LCOE） | C19: 元/kWh | D19: =逐年财务指标一览表!B27 -> #VALUE!
B20: 年份 | D20: 第1年 | E20: 第2年 | F20: 第3年 | G20: 第4年 | H20: 第5年
A21: 14 | B21: 前五年利润总额 | C21: 万元 | D21: =利润与利润分配表!E17 -> #VALUE! | E21: =利润与利润分配表!F17 -> #VALUE! | F21: =利润与利润分配表!G17 -> #VALUE! | G21: =利润与利润分配表!H17 -> #VALUE! | H21: =利润与利润分配表!I17 -> #VALUE!
A22: 15 | B22: 前五年EVA | C22: 万元 | D22: =EVA测算表!E12 -> #VALUE! | E22: =EVA测算表!F12 -> #VALUE! | F22: =EVA测算表!G12 -> #VALUE! | G22: =EVA测算表!H12 -> #VALUE! | H22: =EVA测算表!I12 -> #VALUE!
A23: 16 | B23: 前五年ROE | C23: % | D23: =资产负债表!D29*100 -> #VALUE! | E23: =资产负债表!E29*100 -> #VALUE! | F23: =资产负债表!F29*100 -> #VALUE! | G23: =资产负债表!G29*100 -> #VALUE! | H23: =资产负债表!H29*100 -> #VALUE!

Sheet 逐年财务指标一览表
A1: 指标 | B1: 第1年 | C1: 第2年 | D1: 第3年 | E1: 第4年 | F1: 第5年 | G1: 第6年 | H1: 第7年 | I1: 第8年 | J1: 第9年 | K1: 第10年 | L1: 第11年 | M1: 第12年 | N1: 第13年 | O1: 第14年 | P1: 第15年 | Q1: 第16年 | R1: 第17年 | S1: 第18年 | T1: 第19年 | U1: 第20年 | V1: 第21年 | W1: 第22年 | X1: 第23年 | Y1: 第24年 | Z1: 第25年 | AA1: 第26年
A2: 度电成本（元/kWh) | B2: =总成本费用表!D20*10000/(利润与利润分配表!D5*1000) -> #DIV/0! | C2: =总成本费用表!E20*10000/(利润与利润分配表!E5*1000) -> #REF! | D2: =总成本费用表!F20*10000/(利润与利润分配表!F5*1000) -> #REF! | E2: =总成本费用表!G20*10000/(利润与利润分配表!G5*1000) -> #REF! | F2: =总成本费用表!H20*10000/(利润与利润分配表!H5*1000) -> #REF! | G2: =总成本费用表!I20*10000/(利润与利润分配表!I5*1000) -> #REF! | H2: =总成本费用表!J20*10000/(利润与利润分配表!J5*1000) -> #REF! | I2: =总成本费用表!K20*10000/(利润与利润分配表!K5*1000) -> #REF! | ... AA2: =总成本费用表!AC20*10000/(利润与利润分配表!AC5*1000) -> #REF!
A3: 度电利润（元/kWh) | B3: =利润与利润分配表!D17*10000/(利润与利润分配表!D5*1000) -> #DIV/0! | C3: =利润与利润分配表!E17*10000/(利润与利润分配表!E5*1000) -> #VALUE! | D3: =利润与利润分配表!F17*10000/(利润与利润分配表!F5*1000) -> #VALUE! | E3: =利润与利润分配表!G17*10000/(利润与利润分配表!G5*1000) -> #VALUE! | F3: =利润与利润分配表!H17*10000/(利润与利润分配表!H5*1000) -> #VALUE! | G3: =利润与利润分配表!I17*10000/(利润与利润分配表!I5*1000) -> #VALUE! | H3: =利润与利润分配表!J17*10000/(利润与利润分配表!J5*1000) -> #VALUE! | I3: =利润与利润分配表!K17*10000/(利润与利润分配表!K5*1000) -> #VALUE! | ... AA3: =利润与利润分配表!AC17*10000/(利润与利润分配表!AC5*1000) -> #VALUE!
A4: 综合电价（税前）（元/kWh) | B4: =利润与利润分配表!D6 -> 0 | C4: =利润与利润分配表!E6 -> #VALUE! | D4: =利润与利润分配表!F6 -> #VALUE! | E4: =利润与利润分配表!G6 -> #VALUE! | F4: =利润与利润分配表!H6 -> #VALUE! | G4: =利润与利润分配表!I6 -> #VALUE! | H4: =利润与利润分配表!J6 -> #VALUE! | I4: =利润与利润分配表!K6 -> #VALUE! | ... AA4: =利润与利润分配表!AC6 -> #VALUE!
A5: 财务费用（万元） | B5: =总成本费用表!D12 -> 0 | C5: =总成本费用表!E12 -> 0 | D5: =总成本费用表!F12 -> #VALUE! | E5: =总成本费用表!G12 -> #VALUE! | F5: =总成本费用表!H12 -> #VALUE! | G5: =总成本费用表!I12 -> #VALUE! | H5: =总成本费用表!J12 -> #VALUE! | I5: =总成本费用表!K12 -> #VALUE! | ... AA5: =总成本费用表!AC12 -> #VALUE!
A6: 资本金净现金流（万元） | B6: =项目资本金现金流量表!D21 -> 0 | C6: =项目资本金现金流量表!E21 -> #VALUE! | D6: =项目资本金现金流量表!F21 -> #VALUE! | E6: =项目资本金现金流量表!G21 -> #VALUE! | F6: =项目资本金现金流量表!H21 -> #VALUE! | G6: =项目资本金现金流量表!I21 -> #VALUE! | H6: =项目资本金现金流量表!J21 -> #VALUE! | I6: =项目资本金现金流量表!K21 -> #VALUE! | ... AA6: =项目资本金现金流量表!AC21 -> #VALUE!
A7: EVA（万元） | B7: =EVA测算表!D12 -> 0 | C7: =EVA测算表!E12 -> #VALUE! | D7: =EVA测算表!F12 -> #VALUE! | E7: =EVA测算表!G12 -> #VALUE! | F7: =EVA测算表!H12 -> #VALUE! | G7: =EVA测算表!I12 -> #VALUE! | H7: =EVA测算表!J12 -> #VALUE! | I7: =EVA测算表!K12 -> #VALUE! | ... AA7: =EVA测算表!AC12 -> #VALUE!
A8: ROE（%） | B8: =资产负债表!C29 -> 0 | C8: =资产负债表!D29 -> #VALUE! | D8: =资产负债表!E29 -> #VALUE! | E8: =资产负债表!F29 -> #VALUE! | F8: =资产负债表!G29 -> #VALUE! | G8: =资产负债表!H29 -> #VALUE! | H8: =资产负债表!I29 -> #VALUE! | I8: =资产负债表!J29 -> #VALUE! | ... AA8: =资产负债表!AB29 -> #VALUE!
A10: 图像：
A11: 1.做整个运营期的折线图，运营期有几年就显示几年；需要注意的是财务费用的年度和运营期不一致
A12: 2.度电成本、度电利润、综合电价显示在左侧坐标轴，剩余三个指标显示在右侧坐标轴，六个曲线做在同一张折线图上
A13: 3.在图的旁边做这几项指标的勾选，使用户可以勾选折线图显示哪几个指标
A14: 4.上表仅供作图使用，不显示在界面中
B17: 1 | C17: 2 | D17: 3 | E17: 4 | F17: 5 | G17: 6 | H17: 7 | I17: 8 | J17: 9 | K17: 10 | L17: 11 | M17: 12 | N17: 13 | O17: 14 | P17: 15 | Q17: 16 | R17: 17 | S17: 18 | T17: 19 | U17: 20 | V17: 21 | W17: 22 | X17: 23 | Y17: 24 | Z17: 25 | AA17: 26
A18: 折现因子 | B18: =1/(1+$B$19)^(B17-1) -> 1 | C18: =1/(1+$B$19)^(C17-1) -> 0.96814793 | D18: =1/(1+$B$19)^(D17-1) -> 0.93731042 | E18: =1/(1+$B$19)^(E17-1) -> 0.90745515 | F18: =1/(1+$B$19)^(F17-1) -> 0.87855082 | G18: =1/(1+$B$19)^(G17-1) -> 0.85056716 | H18: =1/(1+$B$19)^(H17-1) -> 0.82347484 | I18: =1/(1+$B$19)^(I17-1) -> 0.79724547 | ... AA18: =1/(1+$B$19)^(AA17-1) -> 0.44518761
A19: WACC | B19: =基本参数!B25% -> 0.0329
A20: 运维成本 | B20: =总成本费用表!D21 -> 0 | C20: =总成本费用表!E21 -> #REF! | D20: =总成本费用表!F21 -> #REF! | E20: =总成本费用表!G21 -> #REF! | F20: =总成本费用表!H21 -> #REF! | G20: =总成本费用表!I21 -> #REF! | H20: =总成本费用表!J21 -> #REF! | I20: =总成本费用表!K21 -> #REF! | ... AA20: =总成本费用表!AC21 -> #REF!
A21: 进项税抵扣 | B21: =利润与利润分配表!D33-利润与利润分配表!D37 -> 0 | C21: =利润与利润分配表!E33-利润与利润分配表!E37 -> #VALUE! | D21: =利润与利润分配表!F33-利润与利润分配表!F37 -> #VALUE! | E21: =利润与利润分配表!G33-利润与利润分配表!G37 -> #VALUE! | F21: =利润与利润分配表!H33-利润与利润分配表!H37 -> #VALUE! | G21: =利润与利润分配表!I33-利润与利润分配表!I37 -> #VALUE! | H21: =利润与利润分配表!J33-利润与利润分配表!J37 -> #VALUE! | I21: =利润与利润分配表!K33-利润与利润分配表!K37 -> #VALUE! | ... AA21: =利润与利润分配表!AC33-利润与利润分配表!AC37 -> #VALUE!
A22: 残值 | C22: =项目资本金现金流量表!E9 -> 0 | D22: =项目资本金现金流量表!F9 -> 0 | E22: =项目资本金现金流量表!G9 -> 0 | F22: =项目资本金现金流量表!H9 -> 0 | G22: =项目资本金现金流量表!I9 -> 0 | H22: =项目资本金现金流量表!J9 -> 0 | I22: =项目资本金现金流量表!K9 -> 0 | J22: =项目资本金现金流量表!L9 -> 0 | ... AA22: =项目资本金现金流量表!AC9 -> 0
A23: 静态初始投资 | B23: =项目投资现金流量表!D12 -> 0 | C23: =项目投资现金流量表!E12 -> 0 | D23: =项目投资现金流量表!F12 -> 0 | E23: =项目投资现金流量表!G12 -> 0 | F23: =项目投资现金流量表!H12 -> 0 | G23: =项目投资现金流量表!I12 -> 0 | H23: =项目投资现金流量表!J12 -> 0 | I23: =项目投资现金流量表!K12 -> 0 | ... AA23: =项目投资现金流量表!AC12 -> 0
A24: 发电量 | B24: =利润与利润分配表!D5 -> 0 | C24: =利润与利润分配表!E5 -> #VALUE! | D24: =利润与利润分配表!F5 -> #VALUE! | E24: =利润与利润分配表!G5 -> #VALUE! | F24: =利润与利润分配表!H5 -> #VALUE! | G24: =利润与利润分配表!I5 -> #VALUE! | H24: =利润与利润分配表!J5 -> #VALUE! | I24: =利润与利润分配表!K5 -> #VALUE! | ... AA24: =利润与利润分配表!AC5 -> #VALUE!
A25: 成本折现 | B25: =(B23-B21+B20-B22)*B18 -> 0 | C25: =(C23-C21+C20-C22)*C18 -> #VALUE! | D25: =(D23-D21+D20-D22)*D18 -> #VALUE! | E25: =(E23-E21+E20-E22)*E18 -> #VALUE! | F25: =(F23-F21+F20-F22)*F18 -> #VALUE! | G25: =(G23-G21+G20-G22)*G18 -> #VALUE! | H25: =(H23-H21+H20-H22)*H18 -> #VALUE! | I25: =(I23-I21+I20-I22)*I18 -> #VALUE! | ... AA25: =(AA23-AA21+AA20-AA22)*AA18 -> #VALUE!
A26: 发电量折现 | B26: =B24*B18 -> 0 | C26: =C24*C18 -> #VALUE! | D26: =D24*D18 -> #VALUE! | E26: =E24*E18 -> #VALUE! | F26: =F24*F18 -> #VALUE! | G26: =G24*G18 -> #VALUE! | H26: =H24*H18 -> #VALUE! | I26: =I24*I18 -> #VALUE! | ... AA26: =AA24*AA18 -> #VALUE!
A27: LCOE(元/kWh) | B27: =SUM(B25:AA25)/(SUM(B26:AA26))*10 -> #VALUE!
